Workbook

Sheet Sheet1
A3: Row Labels | B3: Count of Email
A4: bfre2137@chi.sysco.com | B4: 11
A5: jswe4549@boston.sysco.com | B5: 9
A6: jbow2741@boston.sysco.com | B6: 8
A7: mweb1884@int.sysco.com | B7: 8
A8: kgor4562@sysco.com | B8: 7
A9: dbla0356@mt.sysco.com | B9: 7
A10: jgla2956@metrony.sysco.com | B10: 7
A11: pgra9460@sd.sysco.com | B11: 6
A12: swil2146@cha.sysco.com | B12: 6
A13: khau4953@sfo.sysco.com | B13: 6
A14: hper2530@wcf.sysco.com | B14: 5
A15: snai1403@boston.sysco.com | B15: 5
... A452: jran8733@syr.sysco.com | B452: 1
A453: (blank)
A454: Grand Total | B454: 707

Sheet Tickets
A1: Dispositioned By | B1: Date | C1: Status | D1: Response | E1: Details | F1: Ticket Number | G1: Id | H1: Start time | I1: Completion time | J1: Email | K1: Name | L1: Sysco Sales Consultants email (add multiple with semicolon " ; " ) | M1: Order Number (Marketplace orders begin with the letter "M" or the Item SKU begins with the number "6". Example: #M4c5def9f971d) REQUIRED to process options 1-4. You may put "N/A" for options 5-7 below | N1: I would like to: | O1: Report an Issue with Item Received: Please Insert 3 or more Images showing the damage. All Images should be in "JPEG" format to be accepted by Supplier. Please do not attach movies. | P1: Additional Image of concern (#2) Jpeg format Only | Q1: Additional Image of concern (#3) Jpeg format Only | R1: Report an Issue with Item Received: Please provide a brief on the issue (Item arrived spoiled, damaged, broken, etc) and amount of products impacted out of total | S1: Report an Item not Delivered: Please provide sku "beginning with number "6" and quantity not received. All incidents MUST be reported 30 days from order date for suppliers to process. | T1: Enable or Disable Accounts (Please do not change header of template) | U1: Please add details on product request (fact sheets, availability, matching sets, substitutes, etc) | V1: Enabling/Disabling Account on Marketplace: Please upload an excel or CSV file with the following 3 columns in excel format: (Opco ID | Customer Number | Enable (TRUE)/Disable (FALSE)). Please re | W1: Other: Please Provide details of your inquiry (If there is an issue with the order, you MUST use option #3 and report an incident) | X1: Cancel an Order | Y1: ETA on Delivery (Sysco Shop is NOW enabled to show Delivery Details)
A2: Kashif | D2: We have routed your request to the seller. Please feel free to reach out next week if you do not see an update by then. | E2: Delete | G2: 1 | H2: 46200.646 | I2: 46200.646 | J2: kkhu6683@sysco.com | K2: Kashif Khurshid | L2: =OfficeForms.Table[[#This Row],[Email]] -> kkhu6683@sysco.com | M2: mefksdfrgkrg | N2: Cancel an Order (Marketplace Third Party product orders are not eligible for Returns/Refunds or exchanges and is indicated at time of purchase) | X2: We Can only cancel an order if its in "awaiting acceptance" state and has not been accepted by the Seller. Once the order is accepted, it will no longer be cancellable and rejecting delivery will still hold the customer liable thus please confirm prior to placing any marketplace order. Also note that Sysco Shop does not have the ability to place orders automatically on behalf of customers.
A3: Kashif | E3: Delete | G3: 2 | H3: 46200.65 | I3: 46200.652 | J3: kkhu6683@sysco.com | K3: Kashif Khurshid | L3: =OfficeForms.Table[[#This Row],[Email]] -> kkhu6683@sysco.com | M3: fdhygiiulkfhsd | N3: Report an Issue with an Order Received (All Issues MUST be reported within 14 days of order and submitted with Images and Description of Issue) | O3: https://sysco-my.sharepoint.com/personal/kkhu6683_sysco_com/Documents/Apps/Microsoft%20Forms/Untitled%20form/Question/The%20Caffe%201_Kashif%20Khurshid.jpeg; https://sysco-my.sharepoint.com/personal/kkhu6683_sysco_com/Documents/Apps/Microsoft%20Forms/Untitled%20form/Question/The%20Caffe%202_Kashif%20Khurshid.jpeg | R3: test testinggrhgfhgfhbgfngfb
A4: Kashif | E4: Delete | G4: 3 | H4: 46202.469 | I4: 46202.47 | J4: kkhu6683@sysco.com | K4: Kashif Khurshid | L4: =OfficeForms.Table[[#This Row],[Email]] -> kkhu6683@sysco.com | M4: efewf | N4: 7. Other | W4: dewd
A5: Kashif | E5: Delete | G5: 4 | H5: 46202.47 | I5: 46202.471 | J5: hali8845@corp.sysco.com | K5: Hassan Ali | L5: =OfficeForms.Table[[#This Row],[Email]] -> hali8845@corp.sysco.com | M5: N/A | N5: 1. Receive ETA on Delivery (Marketplace orders have a 5-7 Business Day lead time and currently there is not an option to expedite deliver) | Y5: Marketplace orders have a 5-7 Business Day lead time and currently there is not an option to expedite deliver. Customer is liable for retrieving package if the business is closed or the address is incorrect. Please ensure Delivery address is updated in Salesforce prior to ordering.
A6: Kashif | C6: Sent | D6: We apologize for the inconvenience. A support ticket has been opened with the supplier. Please feel free to reach out if you do not see an activity on your account by next week. | E6: created in Mirakle | G6: 5 | H6: 46202.474 | I6: 46202.477 | J6: wpow2255@sysco.com | K6: Tony Powers | L6: =OfficeForms.Table[[#This Row],[Email]] -> wpow2255@sysco.com | M6: M85a82b1b7b9c | N6: 3. Report an Issue with an Order Received (All Issues MUST be reported within 14 days of order and submitted with Images and Description of Issue) | O6: https://sysco-my.sharepoint.com/personal/kkhu6683_sysco_com/Documents/Apps/Microsoft%20Forms/Untitled%20form/Question/3rdparty3_Tony%20Powers.jpg | P6: https://sysco-my.sharepoint.com/personal/kkhu6683_sysco_com/Documents/Apps/Microsoft%20Forms/Untitled%20form/Report%20an%20Issue%20with%20Item%20Received%20Please%20Insert%203%201/3rdpartyhot_Tony%20Powers.jpg | Q6: https://sysco-my.sharepoint.com/personal/kkhu6683_sysco_com/Documents/Apps/Microsoft%20Forms/Untitled%20form/Report%20an%20Issue%20with%20Item%20Received%20Please%20Insert%203/3rdparty2_Tony%20Powers.jpg | R6: items were received completely thawed and hot. Not safe to serve
A7: Kashif | C7: Sent | D7: We apologize for the inconvenience. A support ticket has been opened with the supplier. Please feel free to reach out if you do not see an activity on your account by next week. | E7: https://syscous-prod.mirakl.net/mmp/operator/order/Mf685c21465c4-A/message?sort=date%2CDESC&limit=25 | G7: 6 | H7: 46202.498 | I7: 46202.504 | J7: hkin1331@kc.sysco.com | K7: Haley King | L7: =OfficeForms.Table[[#This Row],[Email]] -> hkin1331@kc.sysco.com | M7: Mf685c21465c4 | N7: 3. Report an Issue with an Order Received (All Issues MUST be reported within 14 days of order and submitted with Images and Description of Issue) | R7: Not size of product description
A8: Kashif | C8: Sent | D8: We apologize for the inconvenience. A support ticket has been opened with the supplier. Please feel free to reach out if you do not see an activity on your account by next week. | E8: https://syscous-prod.mirakl.net/mmp/operator/order/Mee63e533470c-A/message/bbe15d84-7a18-42d9-9c11-f515ad5be06f/details | G8: 7 | H8: 46202.515 | I8: 46202.516 | J8: pgra9460@sd.sysco.com | K8: Peter Grap | L8: =OfficeForms.Table[[#This Row],[Email]] -> pgra9460@sd.sysco.com | M8: Mee63e533470c | N8: 4. Report an Order not Delivered ( Please note that customer rejecting delivery will suffice as a delivery issue) | S8: SUPC 6022496 Dove choc (2cs) - tracking reports delivered, but customer did not receive. Nobody named 'ibarra' works at this location, and Fedex claimed that was who received the order.
A9: Kashif | C9: Sent | D9: Unfortunately, this order has been processed, and the Seller is unable to cancel. Please note, Marketplace Third Party product orders are not eligible for Returns/Refunds or exchanges and is indicated at time of purchase. We wish we could be of more help but given Marketplace's policy, we are unable to assist further on this order. | G9: 8 | H9: 46202.653 | I9: 46202.656 | J9: nfon6129@emd.sysco.com | K9: Nick Fontana | L9: =OfficeForms.Table[[#This Row],[Email]] -> nfon6129@emd.sysco.com | M9: Mb5a6fa6ccf65 | N9: 2. Cancel an Order (Marketplace Third Party product orders are not eligible for Returns/Refunds or exchanges and is indicated at time of purchase) | X9: We Can only cancel an order if its in "awaiting acceptance" state and has not been accepted by the Seller. Once the order is accepted, it will no longer be cancellable and rejecting delivery will still hold the customer liable thus please confirm prior to placing any marketplace order. Also note that Sysco Shop does not have the ability to place orders automatically on behalf of customers.
A10: Kashif | C10: Sent | D10: We apologize for the inconvenience. A support ticket has been opened with the supplier. Please feel free to reach out if you do not see an activity on your account by next week. | E10: https://syscous-prod.mirakl.net/mmp/operator/order/M4e8180f441d4-A/message/1d20a812-1f34-4962-acc3-7261aeb2e93f/details | G10: 9 | H10: 46202.833 | I10: 46202.838 | J10: jmat3941@int.sysco.com | K10: Jeremy Matthews | L10: =OfficeForms.Table[[#This Row],[Email]] -> jmat3941@int.sysco.com | M10: M4e8180f441d4 | N10: 3. Report an Issue with an Order Received (All Issues MUST be reported within 14 days of order and submitted with Images and Description of Issue) | O10: https://sysco-my.sharepoint.com/personal/kkhu6683_sysco_com/Documents/Apps/Microsoft%20Forms/Untitled%20form/Question/Beignet1_Jeremy%20Matthews.jpg | P10: https://sysco-my.sharepoint.com/personal/kkhu6683_sysco_com/Documents/Apps/Microsoft%20Forms/Untitled%20form/Report%20an%20Issue%20with%20Item%20Received%20Please%20Insert%203%201/beignet3_Jeremy%20Matthews.jpg | Q10: https://sysco-my.sharepoint.com/personal/kkhu6683_sysco_com/Documents/Apps/Microsoft%20Forms/Untitled%20form/Report%20an%20Issue%20with%20Item%20Received%20Please%20Insert%203/Beignet4_Jeremy%20Matthews.jpg | R10: Item arrived thawed and proofed, not frozen.
A11: Kashif | C11: Sent | D11: Unfortunately, this order has been processed, and the Seller is unable to cancel. Please note, Marketplace Third Party product orders are not eligible for Returns/Refunds or exchanges and is indicated at time of purchase. We wish we could be of more help but given Marketplace's policy, we are unable to assist further on this order. | G11: 10 | H11: 46203.391 | I11: 46203.398 | J11: mcan3533@min.sysco.com | K11: Martin Canfield | L11: =OfficeForms.Table[[#This Row],[Email]] -> mcan3533@min.sysco.com | M11: Mc0f2cf114a79 | N11: 7. Other | W11: My customer ordered the wrong size Flavor-Ice. She wanted the 5.5 giant size but ordered the much smaller size which she can't sell. If it was one case, we would ask them to find a way to sell it. But its eight cases and they want to send them back.
A12: Kashif | C12: Sent | D12: We have routed your request to the seller. Please feel free to reach out next week if you do not see an update by then. | E12: https://syscous-prod.mirakl.net/mmp/operator/order/Mffc98f09d1a7-A/message?sort=date%2CDESC&limit=25 | G12: 11 | H12: 46203.423 | I12: 46203.427 | J12: jsca2787@philly.sysco.com | K12: Jennifer Bell | L12: =OfficeForms.Table[[#This Row],[Email]] -> jsca2787@philly.sysco.com | M12: Mffc98f09d1a7 | N12: 3. Report an Issue with an Order Received (All Issues MUST be reported within 14 days of order and submitted with Images and Description of Issue) | O12: https://sysco-my.sharepoint.com/personal/kkhu6683_sysco_com/Documents/Apps/Microsoft%20Forms/Untitled%20form/Question/Malvern%20Mispick_Jennifer%20Bell.jpeg | R12: Ramen noodles received, ordered cheddar crackers - Mispick
A13: Kashif | C13: Sent | D13: Thank you for sharing. Please fill out the form again and select option #3 "issue with order received" and complete the additional details before we can proceed with a ticket | G13: 12 | H13: 46203.448 | I13: 46203.452 | J13: jswe4549@boston.sysco.com | K13: Jean Sweet | L13: =OfficeForms.Table[[#This Row],[Email]] -> jswe4549@boston.sysco.com | M13: Ma825a338a0f6 | N13: 7. Other | W13: Customer received freeze dried apple instead of straw- please issue credit- new cs has be re-ordered
A14: Kashif | C14: Sent | D14: We apologize for the inconvenience. A support ticket has been opened with the supplier. Please feel free to reach out if you do not see an activity on your account by next week. | E14: https://syscous-prod.mirakl.net/mmp/operator/order/M9f8b6d10da2e-A/message?sort=date%2CDESC&limit=25 | G14: 13 | H14: 46203.46 | I14: 46203.465 | J14: acro7701@sysco.com | K14: Alexis Croushore | L14: =OfficeForms.Table[[#This Row],[Email]] -> acro7701@sysco.com | M14: M9f8b6d10da2e | N14: 3. Report an Issue with an Order Received (All Issues MUST be reported within 14 days of order and submitted with Images and Description of Issue) | O14: https://sysco-my.sharepoint.com/personal/kkhu6683_sysco_com/Documents/Apps/Microsoft%20Forms/Untitled%20form/Question/5E439EF2-156A-4C78-91E8-CBBA0E871768_Alexis%20Croushore.png | P14: https://sysco-my.sharepoint.com/personal/kkhu6683_sysco_com/Documents/Apps/Microsoft%20Forms/Untitled%20form/Report%20an%20Issue%20with%20Item%20Received%20Please%20Insert%203%201/IMG_4678_Alexis%20Croushore.PNG | R14: Some lids do not fit the cups, some lids no not have holes. Wants to return 6/6 cases , 308.87 total.
A15: Kashif | C15: New | D15: We have routed your request to the seller. Please feel free to reach out next week if you do not see an update by then. | G15: 14 | H15: 46203.508 | I15: 46203.51 | J15: sriz5487@shr.sysco.com | K15: Stefanie Rizzo-Zahn | L15: =OfficeForms.Table[[#This Row],[Email]] -> sriz5487@shr.sysco.com | M15: #M827c03c17592 | N15: 7. Other (Do NOT use for Order/Product Related Issues) | W15: Customer needs to order the top for this portion cup. Please help assist what that item is so we can get it ordered
A16: Kashif | C16: Sent | D16: We apologize for the inconvenience. A support ticket has been opened with the supplier. Please feel free to reach out if you do not see an activity on your account by next week. | E16: https://syscous-prod.mirakl.net/mmp/operator/order/Mbc51e08c2606-A/message?sort=date%2CDESC&limit=25 | G16: 15 | H16: 46203.555 | I16: 46203.559 | J16: blin7890@ntx.sysco.com | K16: Lin John | L16: =OfficeForms.Table[[#This Row],[Email]] -> blin7890@ntx.sysco.com | M16: Mbc51e08c2606-A | N16: 3. Report an Issue with an Order Received (All Issues MUST be reported within 14 days of order and submitted with Images and Description of Issue) | O16: https://sysco-my.sharepoint.com/personal/kkhu6683_sysco_com/Documents/Apps/Microsoft%20Forms/Untitled%20form/Question/Image%20(72)_Lin%20John.jpg; https://sysco-my.sharepoint.com/personal/kkhu6683_sysco_com/Documents/Apps/Microsoft%20Forms/Untitled%20form/Question/image%20(21)_Lin%20John.png | R16: 3 leaked or broken bottle pf passion fruit syrup
A17: Kashif | C17: Sent | D17: Unfortunately, this order has been processed, and the Seller is unable to cancel. Please note, Marketplace Third Party product orders are not eligible for Returns/Refunds or exchanges and is indicated at time of purchase. We wish we could be of more help but given Marketplace's policy, we are unable to assist further on this order. | G17: 16 | H17: 46203.571 | I17: 46203.572 | J17: jswe4549@boston.sysco.com | K17: Jean Sweet | L17: =OfficeForms.Table[[#This Row],[Email]] -> jswe4549@boston.sysco.com | M17: Me1135712a256 | N17: 7. Other (Do NOT use for Order/Product Related Issues) | W17: Customer ordered in error- SC has called the MFG and they said they can return- please advise on a return label
A18: Kashif | C18: Sent | D18: We have routed your request to the seller. Please feel free to reach out next week if you do not see an update by then. | E18: https://syscous-prod.mirakl.net/mmp/operator/order/Mad6533fba6f2-A/message?sort=date%2CDESC&limit=25 | G18: 17 | H18: 46203.647 | I18: 46203.648 | J18: cwar7858@ctx.sysco.com | K18: Charlie Ward | L18: =OfficeForms.Table[[#This Row],[Email]] -> cwar7858@ctx.sysco.com | M18: Mad6533fba6f2 | N18: 7. Other (Do NOT use for Order/Product Related Issues) | W18: UPS says it has attempted to deliver twice but business was closed. business was NOT closed, employees were inside. Please leave notes to try harder or simply leave the package, that is fine per customer
A19: Kashif | C19: Sent | D19: Unfortunately, this order has been processed, and the Seller is unable to cancel. Please note, Marketplace Third Party product orders are not eligible for Returns/Refunds or exchanges and is indicated at time of purchase. We wish we could be of more help but given Marketplace's policy, we are unable to assist further on this order. | G19: 18 | H19: 46203.744 | I19: 46203.746 | J19: pste6327@mt.sysco.com | K19: Paul Stelmack | L19: =OfficeForms.Table[[#This Row],[Email]] -> pste6327@mt.sysco.com | M19: M346b5eb63018 | N19: 7. Other (Do NOT use for Order/Product Related Issues) | W19: This customer says he did not mean to order this, asked for a return, can we credit back at all? Sorry new account learning the ropes
A20: Kashif | C20: Sent | D20: Thank you for sharing, If you do not see activity on your account by next week, please reach back out. | E20: https://syscous-prod.mirakl.net/mmp/operator/order/Mf21fe5c2517b-A/message/e5b4c079-e8cd-43fb-8c45-a9747ba2dd33/details | G20: 19 | H20: 46203.788 | I20: 46203.792 | J20: ggal6788@rs.sysco.com | K20: Gustavo Galvez | L20: =OfficeForms.Table[[#This Row],[Email]] -> ggal6788@rs.sysco.com | M20: Mf21fe5c2517b | N20: 4. Report an Order not Delivered ( Please note that customer rejecting delivery will suffice as a delivery issue) | S20: 6064771; 6064775
A21: Kashif | C21: New | D21: We have routed your request to the seller. Please feel free to reach out next week if you do not see an update by then. | G21: 20 | H21: 46204.301 | I21: 46204.302 | J21: acar1081@rnc.sysco.com | K21: Aileen Carr | L21: =OfficeForms.Table[[#This Row],[Email]] -> acar1081@rnc.sysco.com | M21: na | N21: 7. Other (Do NOT use for Order/Product Related Issues) | W21: Are these items available yet on Marketplace? https://everydaysupplyco.com/search?sort_by=relevance&q=just&type=product&filter.p.t.category=fb-1-16&filter.v.price.gte=&filter.v.price.lte= https://everydaysupplyco.com/search?sort_by=relevance&q=just&type=product&filter.p.t.category=fb-1-16&filter.v.price.gte=&filter.v.price.lte=
A22: Kashif | C22: Sent | D22: It appears to have been delivered. The seller has completed the order from their end and wish we could assist further. I would encourage the seller to connect directly with the delivery provider. | G22: 21 | H22: 46204.36 | I22: 46204.364 | J22: fmem6919@corp.sysco.com | K22: Fredy Membreno | L22: =OfficeForms.Table[[#This Row],[Email]] -> fmem6919@corp.sysco.com | M22: M4c5def9f971d | N22: 1. Receive ETA on Delivery (Marketplace orders have a 5-7 Business Day lead time and currently there is not an option to expedite deliver) | Y22: Marketplace orders have a 5-7 Business Day lead time and currently there is not an option to expedite deliver. Customer is liable for retrieving package if the business is closed or the address is incorrect. Please ensure Delivery address is updated in Salesforce prior to ordering.
A23: Kashif | C23: Sent | D23: We have enabled these customer account to view and order Marketplace Third Party Products. Please note it will take about 24 hours to take effect. | G23: 22 | H23: 46204.381 | I23: 46204.383 | J23: smoo5472@wmn.sysco.com | K23: Shane Moore | L23: =OfficeForms.Table[[#This Row],[Email]] -> smoo5472@wmn.sysco.com | M23: 047-933682 Cru Restaurant (enable) | N23: 6. Enable/Disable Customer for Marketplace Products (All TRS customers are enabled by default, LCC and CMU may have restrictions, please confirm prior to requesting)
A24: Kashif | C24: Sent | D24: Unfortunately this Marketplace sellers does not offer samples at this time. | G24: 23 | H24: 46204.425 | I24: 46204.426 | J24: kgwa2062@balt.sysco.com | K24: Karim Gwaduri | L24: =OfficeForms.Table[[#This Row],[Email]] -> kgwa2062@balt.sysco.com | M24: 012-241715 | N24: 5. Information on Product/Supplier (Please provide SUPC number that begins with "6xxxxxx" | U24: a new client of mine is looking to sample item 6066520. there is no SC information on shop so i don't know who to contact. please provide me with contact information so i can reach out to the broker or PSA or just let me know if we are able to send a free sample to them. thank you!
A25: Kashif | C25: Sent | D25: It appears to have been delivered. The seller has completed the order from their end and wish we could assist further. I would encourage the seller to connect directly with the delivery provider. | G25: 24 | H25: 46204.535 | I25: 46204.537 | J25: kelt9557@la.sysco.com | K25: Kirsten Eltzholtz | L25: =OfficeForms.Table[[#This Row],[Email]] -> kelt9557@la.sysco.com | M25: MD832AFB41047 | N25: 3. Report an Issue with an Order Received (All Issues MUST be reported within 14 days of order and submitted with Images and Description of Issue) | R25: The customer ordered the wrong product and does not want it.
A26: Kashif | C26: Sent | D26: We have routed your request to the seller. Please feel free to reach out next week if you do not see an update by then. | G26: 25 | H26: 46204.617 | I26: 46204.618 | J26: pgra9460@sd.sysco.com | K26: Peter Grap | L26: =OfficeForms.Table[[#This Row],[Email]] -> pgra9460@sd.sysco.com | M26: n/a | N26: 5. Information on Product/Supplier (Please provide SUPC number that begins with "6xxxxxx" | U26: Customer reports that item 6086673 (prevail jerky) may have the pack size & contents listed incorrectly. Please advise on the correct pack size that will be shipped for this item.
A27: Kashif | C27: Sent | D27: Unfortunately, this order has been processed, and the Seller is unable to cancel. Please note, Marketplace Third Party product orders are not eligible for Returns/Refunds or exchanges and is indicated at time of purchase. We wish we could be of more help but given Marketplace's policy, we are unable to assist further on this order. | G27: 26 | H27: 46204.627 | I27: 46204.628 | J27: gner8973@sfl.sysco.com | K27: Giselle Neri | L27: =OfficeForms.Table[[#This Row],[Email]] -> gner8973@sfl.sysco.com | M27: Mc8050f9d386e | N27: 2. Cancel an Order (Marketplace Third Party product orders are not eligible for Returns/Refunds or exchanges and is indicated at time of purchase) | X27: We Can only cancel an order if its in "awaiting acceptance" state and has not been accepted by the Seller. Once the order is accepted, it will no longer be cancellable and rejecting delivery will still hold the customer liable thus please confirm prior to placing any marketplace order. Also note that Sysco Shop does not have the ability to place orders automatically on behalf of customers.
A28: Kashif | C28: New | D28: We have routed your request to the seller. Please feel free to reach out next week if you do not see an update by then. | G28: 27 | H28: 46204.718 | I28: 46204.721 | J28: kkuz3544@sd.sysco.com | K28: Kristen Kuznicki | L28: =OfficeForms.Table[[#This Row],[Email]] -> kkuz3544@sd.sysco.com | M28: 036-744930 - not an order inquiry | N28: 7. Other (Do NOT use for Order/Product Related Issues) | W28: Hello, I tried e-mailing & sent pics but I see there is no where to include them here. I am trying to locate two Karat products: 20oz white paper bowl (#10009400) and the lid for it (karat #c-kdl142-pp/10390300). The #'s starting w/1's are what the customer sent. TY for your help!
A29: Kashif | C29: Escalate | D29: We have routed your request to the seller. Please feel free to reach out next week if you do not see an update by then. | G29: 28 | H29: 46204.878 | I29: 46204.88 | J29: jgla2956@metrony.sysco.com | K29: Justin Glasser | L29: =OfficeForms.Table[[#This Row],[Email]] -> jgla2956@metrony.sysco.com | M29: M59c6fe193ab, M439221894fd4, M44c96521c56c, Mb59b4691f145, M659c3273e591. This customer is fraud and we need to cancel orders immediately and halt shipping. | N29: 2. Cancel an Order (Marketplace Third Party product orders are not eligible for Returns/Refunds or exchanges and is indicated at time of purchase) | X29: We Can only cancel an order if its in "awaiting acceptance" state and has not been accepted by the Seller. Once the order is accepted, it will no longer be cancellable and rejecting delivery will still hold the customer liable thus please confirm prior to placing any marketplace order. Also note that Sysco Shop does not have the ability to place orders automatically on behalf of customers.
A30: Kashif | C30: Sent | D30: We apologize for the inconvenience. A support ticket has been opened with the supplier. Please feel free to reach out if you do not see an activity on your account by next week. | E30: https://syscous-prod.mirakl.net/mmp/operator/order/M43dee9a2bcff-A/message?sort=date%2CDESC&limit=25 | G30: 29 | H30: 46205.532 | I30: 46205.541 | J30: jswe4549@boston.sysco.com | K30: Jean Sweet | L30: =OfficeForms.Table[[#This Row],[Email]] -> jswe4549@boston.sysco.com | M30: M43dee9a2bcff | N30: 3. Report an Issue with an Order Received (All Issues MUST be reported within 14 days of order and submitted with Images and Description of Issue) | O30: https://sysco-my.sharepoint.com/personal/kkhu6683_sysco_com/Documents/Apps/Microsoft%20Forms/Untitled%20form/Question/loafy%20mispick_Jean%20Sweet.jpg | P30: https://sysco-my.sharepoint.com/personal/kkhu6683_sysco_com/Documents/Apps/Microsoft%20Forms/Untitled%20form/Report%20an%20Issue%20with%20Item%20Received%20Please%20Insert%203%201/loafy%202_Jean%20Sweet.jpg | Q30: https://sysco-my.sharepoint.com/personal/kkhu6683_sysco_com/Documents/Apps/Microsoft%20Forms/Untitled%20form/Report%20an%20Issue%20with%20Item%20Received%20Please%20Insert%203/loafy%20mispick_Jean%20Sweet.jpg | R30: Good afternoon, Our customer ordered 3rd party strawberry freeze dried but received apple instead they need a credit please- - the got apple freeze dried
A31: Kashif | C31: Sent | D31: It appears that the ticket is incomplete, Please fill it out again and be sure to complete all information required for us to Process. | G31: 30 | H31: 46205.553 | I31: 46205.557 | J31: pgra9460@sd.sysco.com | K31: Peter Grap | L31: =OfficeForms.Table[[#This Row],[Email]] -> pgra9460@sd.sysco.com | M31: Customer 036-501692 (east mesa central #23) | invoice 136A4288M (120cs Kize brownie) | N31: 1. Receive ETA on Delivery (Marketplace orders have a 5-7 Business Day lead time and currently there is not an option to expedite deliver) | Y31: Marketplace orders have a 5-7 Business Day lead time and currently there is not an option to expedite deliver. Customer is liable for retrieving package if the business is closed or the address is incorrect. Please ensure Delivery address is updated in Salesforce prior to ordering.
A32: Kashif | C32: Sent | G32: 31 | H32: 46205.576 | I32: 46205.577 | J32: tbru0701@rnc.sysco.com | K32: Thomas Bruner | L32: =OfficeForms.Table[[#This Row],[Email]] -> tbru0701@rnc.sysco.com | M32: 137-695638 | N32: 5. Information on Product/Supplier (Please provide SUPC number that begins with "6xxxxxx" | U32: Is item #6070014 available in full sugar? Not sugar free?
A33: Kashif | C33: Sent | D33: This item is currently out of stock and the seller does not have an ETA on its availability yet. If you do not see this back on after 2 weeks, please feel free to reach out to us. | G33: 32 | H33: 46205.64 | I33: 46205.641 | J33: afeo2641@wcf.sysco.com | K33: Aniello Feola | L33: =OfficeForms.Table[[#This Row],[Email]] -> afeo2641@wcf.sysco.com | M33: . | N33: 5. Information on Product/Supplier (Please provide SUPC number that begins with "6xxxxxx" | U33: 6056985 When will this product be available again?
A34: Kashif | C34: Sent | D34: We apologize for the inconvenience. A support ticket has been opened with the supplier. Please feel free to reach out if you do not see an activity on your account by next week. | E34: https://syscous-prod.mirakl.net/mmp/operator/order/M1e95df72e263-A/message?sort=date%2CDESC&limit=25 | G34: 33 | H34: 46205.695 | I34: 46205.703 | J34: mmor7615@lv.sysco.com | K34: Manuel Moreno | L34: =OfficeForms.Table[[#This Row],[Email]] -> mmor7615@lv.sysco.com | M34: M1e95df72e263 | N34: 3. Report an Issue with an Order Received (All Issues MUST be reported within 14 days of order and submitted with Images and Description of Issue) | O34: https://sysco-my.sharepoint.com/personal/kkhu6683_sysco_com/Documents/Apps/Microsoft%20Forms/Untitled%20form/Question/Dragon%20Ridge%203rd%20party%20Spoiled%20Mushroom%202_Manuel%20Moreno.jpeg; https://sysco-my.sharepoint.com/personal/kkhu6683_sysco_com/Documents/Apps/Microsoft%20Forms/Untitled%20form/Question/Dragon%20Ridge%203rd%20party%20Spoiled%20Mushroom_Manuel%20Moreno.jpeg | R34: The item arrived spoiled. The mushroom was not able to breathe and was wet and slimy
A35: Kashif | C35: Sent | D35: Unfortunately, this order has been processed, and the Seller is unable to cancel. Please note, Marketplace Third Party product orders are not eligible for Returns/Refunds or exchanges and is indicated at time of purchase. We wish we could be of more help but given Marketplace's policy, we are unable to assist further on this order. | G35: 34 | H35: 46206.049 | I35: 46206.051 | J35: emar1379@va.sysco.com | K35: Ever Martinez | L35: =OfficeForms.Table[[#This Row],[Email]] -> emar1379@va.sysco.com | M35: M692433f9aa33 | N35: 2. Cancel an Order (Marketplace Third Party product orders are not eligible for Returns/Refunds or exchanges and is indicated at time of purchase) | X35: We Can only cancel an order if its in "awaiting acceptance" state and has not been accepted by the Seller. Once the order is accepted, it will no longer be cancellable and rejecting delivery will still hold the customer liable thus please confirm prior to placing any marketplace order. Also note that Sysco Shop does not have the ability to place orders automatically on behalf of customers.
A36: Kashif | C36: Sent | D36: We have routed your request to the seller. Please feel free to reach out next week if you do not see an update by then. | E36: It Appears the item was damaged in Transit. We have reached out to the Seller to proceed with a refund. https://www.fedex.com/fedextrack/?trknbr=510032640802&trkqual=12030~510032640802~FDEG | G36: 35 | H36: 46208.567 | I36: 46208.568 | J36: cmcc9289@int.sysco.com | K36: Charles McClellan | L36: =OfficeForms.Table[[#This Row],[Email]] -> cmcc9289@int.sysco.com | M36: M1fcbf9ab2aa5 | N36: 1. Receive ETA on Delivery (Marketplace orders have a 5-7 Business Day lead time and currently there is not an option to expedite deliver) | Y36: Marketplace orders have a 5-7 Business Day lead time and currently there is not an option to expedite deliver. Customer is liable for retrieving package if the business is closed or the address is incorrect. Please ensure Delivery address is updated in Salesforce prior to ordering.
A37: Kashif | C37: Sent | D37: It does appear to have inventory. Please ensure the account being used is located in united states and has access to marketplace products. There are times where Suppliers limit the geos they serve which may impact what customers can see and purchase. | E37: GTIN 10815812014131 Alternate Product ID 10815812014131 Manufacturer Product Code 815812014134 | G37: 36 | H37: 46208.65 | I37: 46208.657 | J37: sriz5487@shr.sysco.com | K37: Stefanie Rizzo-Zahn | L37: =OfficeForms.Table[[#This Row],[Email]] -> sriz5487@shr.sysco.com | M37: #M827c03c17592 | N37: 3. Report an Issue with an Order Received (All Issues MUST be reported within 14 days of order and submitted with Images and Description of Issue) | R37: Customer received this item but needs to order the lid for this portion cup and it's not available to order on Sysco Marketplace. Order 872894788129 The lid is Matching Lid: FP-PL400-PET can you help me find this item in Syco Shop so I can order for the customer please
A38: Kashif | C38: Sent | D38: Thank you for sharing. We have reached out to the seller and have created a support ticket. Please feel free to reach out to us next week if you do not see any activity on this order. | E38: https://syscous-prod.mirakl.net/mmp/operator/order/M3f64100d26ca-A/message/03d9c98f-56e4-4887-a3a1-31b4724f22ac/details | G38: 37 | H38: 46209.362 | I38: 46209.363 | J38: ckne2908@boston.sysco.com | K38: Christopher Knell | L38: =OfficeForms.Table[[#This Row],[Email]] -> ckne2908@boston.sysco.com | M38: M3f64100d26ca | N38: 4. Report an Order not Delivered ( Please note that customer rejecting delivery will suffice as a delivery issue) | S38: 6020888 - 1 not received
A39: Kashif | C39: Sent | D39: Marketplace has a policy for reporting any incidents to the seller within the first 14 days of delivery. Any incidents such as these should be reported within that timeframe so that we may open a support ticket with the seller. Unfortunately, this falls outside of the allotted time and thus we are unable to assist further. | E39: https://tools.usps.com/tracking/9434636106196334818968 | F39: https://tools.usps.com/tracking/9434636106196334818968 | G39: 38 | H39: 46209.38 | I39: 46209.388 | J39: tmey5037@indy.sysco.com | K39: Tammy Meyer | L39: =OfficeForms.Table[[#This Row],[Email]] -> tmey5037@indy.sysco.com | M39: M98fe533adb93 | N39: 4. Report an Order not Delivered ( Please note that customer rejecting delivery will suffice as a delivery issue) | S39: 6063641-1 6063646-1 6063652-1
A40: Kashif | C40: Sent | D40: Unfortunately, this order has been processed, and the Seller is unable to cancel. Please note, Marketplace Third Party product orders are not eligible for Returns/Refunds or exchanges and is indicated at time of purchase. We wish we could be of more help but given Marketplace's policy, we are unable to assist further on this order. | G40: 39 | H40: 46209.548 | I40: 46209.55 | J40: jswe4549@boston.sysco.com | K40: Jean Sweet | L40: =OfficeForms.Table[[#This Row],[Email]] -> jswe4549@boston.sysco.com | M40: 156B3431M Date: 5/23/26 | N40: 3. Report an Issue with an Order Received (All Issues MUST be reported within 14 days of order and submitted with Images and Description of Issue) | R40: This was order was refused upon delivery so now we need a credit for 45.43. INV 1556B3431M
A41: Kashif | C41: Sent | D41: It appears that the ticket is incomplete, Please fill it out again and be sure to complete all information required for us to Process. | G41: 40 | H41: 46209.561 | I41: 46209.564 | J41: fsta4629@boston.sysco.com | K41: Francine Stadelmann | L41: =OfficeForms.Table[[#This Row],[Email]] -> fsta4629@boston.sysco.com | M41: 056174743 Wright in my Kitchen | N41: 5. Information on Product/Supplier (Please provide SUPC number that begins with "6xxxxxx" | U41: Is this one 5lb or two 5 5lb case
A42: Kashif | C42: Sent | D42: Unfortunately, this order has been processed, and the Seller is unable to cancel. Please note, Marketplace Third Party product orders are not eligible for Returns/Refunds or exchanges and is indicated at time of purchase. We wish we could be of more help but given Marketplace's policy, we are unable to assist further on this order. | G42: 41 | H42: 46209.626 | I42: 46209.627 | J42: ssha6767@sysco.com | K42: Sarah Shafer | L42: =OfficeForms.Table[[#This Row],[Email]] -> ssha6767@sysco.com | M42: M0918c7978e6b | N42: 2. Cancel an Order (Marketplace Third Party product orders are not eligible for Returns/Refunds or exchanges and is indicated at time of purchase) | X42: We Can only cancel an order if its in "awaiting acceptance" state and has not been accepted by the Seller. Once the order is accepted, it will no longer be cancellable and rejecting delivery will still hold the customer liable thus please confirm prior to placing any marketplace order. Also note that Sysco Shop does not have the ability to place orders automatically on behalf of customers.
A43: Kashif | C43: Sent | D43: We apologize for the inconvenience. A support ticket has been opened with the supplier. Please feel free to reach out if you do not see an activity on your account by next week. | E43: https://syscous-prod.mirakl.net/mmp/operator/order/M1117cc952795-A/message?sort=date%2CDESC&limit=25 | G43: 42 | H43: 46209.684 | I43: 46209.686 | J43: jmul6830@gc.sysco.com | K43: Josh Mullins | L43: =OfficeForms.Table[[#This Row],[Email]] -> jmul6830@gc.sysco.com | M43: M1117cc952795 | N43: 4. Report an Order not Delivered ( Please note that customer rejecting delivery will suffice as a delivery issue) | S43: 6048752; 1cs
A44: Kashif | C44: Sent | E44: Please see attached export | G44: 43 | H44: 46209.685 | I44: 46209.686 | J44: mguz0871@ctx.sysco.com | K44: Mark Guzman | L44: =OfficeForms.Table[[#This Row],[Email]] -> mguz0871@ctx.sysco.com | M44: 013-708301 | N44: 7. Other (Do NOT use for Order/Product Related Issues) | W44: requesting a statement or summary of Market Place order for May and June 2026 for customer 013-708301
A45: Kashif | C45: Sent | D45: Marketplace orders have a 5-7 Business Day lead time and currently there is not an option to expedite delivery. | E45: ups.com/track?tracknum=1Z2XJ4490325109134 | G45: 44 | H45: 46209.703 | I45: 46209.705 | J45: bfre2137@chi.sysco.com | K45: Benjamin Freedland | L45: =OfficeForms.Table[[#This Row],[Email]] -> bfre2137@chi.sysco.com | M45: M3e2405e7b36a | N45: 1. Receive ETA on Delivery (Marketplace orders have a 5-7 Business Day lead time and currently there is not an option to expedite deliver) | Y45: Marketplace orders have a 5-7 Business Day lead time and currently there is not an option to expedite deliver. Customer is liable for retrieving package if the business is closed or the address is incorrect. Please ensure Delivery address is updated in Salesforce prior to ordering.
A46: Kashif | C46: Sent | E46: It apears that the order was cancelled and could be due to low inteventory or other reasons. | G46: 45 | H46: 46209.706 | I46: 46209.715 | J46: shar8486@rs.sysco.com | K46: Sophia Harvey | L46: =OfficeForms.Table[[#This Row],[Email]] -> shar8486@rs.sysco.com | M46: M61128091b209 | N46: 7. Other (Do NOT use for Order/Product Related Issues) | W46: This order is noted as cancelled on SHOP. Did the supplier cancel on their end or was the product actually delivered to the customer? Thank you for the help !
A47: Kashif | C47: Sent | D47: Thank you for sharing. We have reached out to the seller and have created a support ticket. Please feel free to reach out to us next week if you do not see any activity on this order. | E47: https://syscous-prod.mirakl.net/mmp/operator/order/M1d393dd1f7d8-A/message?sort=date%2CDESC&limit=25 | G47: 46 | H47: 46210.382 | I47: 46210.383 | J47: jmat3941@int.sysco.com | K47: Jeremy Matthews | L47: =OfficeForms.Table[[#This Row],[Email]] -> jmat3941@int.sysco.com | M47: M1d393dd1f7d8 | N47: 4. Report an Order not Delivered ( Please note that customer rejecting delivery will suffice as a delivery issue) | S47: 6042166
A48: Kashif | C48: Sent | E48: https://syscous-prod.mirakl.net/mmp/operator/order/Mee63e533470c-A/message/bbe15d84-7a18-42d9-9c11-f515ad5be06f/details | G48: 47 | H48: 46210.476 | I48: 46210.49 | J48: pgra9460@sd.sysco.com | K48: Peter Grap | L48: =OfficeForms.Table[[#This Row],[Email]] -> pgra9460@sd.sysco.com | M48: Please provide tracking confirmation for customer 036-501692 for 120cs of SUPC 6071576 - invoice date 5/6/2026 (invoice #136A4288M) | N48: 1. Receive ETA on Delivery (Marketplace orders have a 5-7 Business Day lead time and currently there is not an option to expedite deliver) | Y48: Marketplace orders have a 5-7 Business Day lead time and currently there is not an option to expedite deliver. Customer is liable for retrieving package if the business is closed or the address is incorrect. Please ensure Delivery address is updated in Salesforce prior to ordering.
A49: Kashif | C49: Sent | E49: This was signed by K Keller. Please confirm with them and see attachment | G49: 48 | H49: 46210.499 | I49: 46210.501 | J49: pgra9460@sd.sysco.com | K49: Peter Grap | L49: =OfficeForms.Table[[#This Row],[Email]] -> pgra9460@sd.sysco.com | M49: East Mesa Central #23 (036-501692) DOT Foods order: Mee63e533470c SUPC 6022496 Dove Chocolate (2cs) *order was placed on 6/3/26. Tracking shows that this was delivered to Illinois (customer is in San Diego, Ca), can we please have these cases refunded to the customer? | N49: 4. Report an Order not Delivered ( Please note that customer rejecting delivery will suffice as a delivery issue) | S49: SUPC 6022496 (2cs) not delivered
A50: Kashif | C50: Sent | E50: This is not a marketplace order | G50: 49 | H50: 46210.554 | I50: 46210.555 | J50: jhen6452@ctx.sysco.com | K50: Jacob Henderson | L50: =OfficeForms.Table[[#This Row],[Email]] -> jhen6452@ctx.sysco.com | M50: 30157410 | N50: 1. Receive ETA on Delivery (Marketplace orders have a 5-7 Business Day lead time and currently there is not an option to expedite deliver) | Y50: Marketplace orders have a 5-7 Business Day lead time and currently there is not an option to expedite deliver. Customer is liable for retrieving package if the business is closed or the address is incorrect. Please ensure Delivery address is updated in Salesforce prior to ordering.
A51: Kashif | C51: Sent | D51: Thank you for sharing. We have reached out to the seller and have created a support ticket. Please feel free to reach out to us next week if you do not see any activity on this order. | E51: https://syscous-prod.mirakl.net/mmp/operator/order/M9c685221779d-A/message/542f8f57-a2d8-45e8-89cc-db4d19338fa5/details | G51: 50 | H51: 46210.576 | I51: 46210.58 | J51: dpid5039@det.sysco.com | K51: David Pidek | L51: =OfficeForms.Table[[#This Row],[Email]] -> dpid5039@det.sysco.com | M51: M9c685221779d | N51: 3. Report an Issue with an Order Received (All Issues MUST be reported within 14 days of order and submitted with Images and Description of Issue) | O51: https://sysco-my.sharepoint.com/personal/kkhu6683_sysco_com/Documents/Apps/Microsoft%20Forms/Untitled%20form/Question/cake%20damage_David%20Pidek.jpg; https://sysco-my.sharepoint.com/personal/kkhu6683_sysco_com/Documents/Apps/Microsoft%20Forms/Untitled%20form/Question/cake%20damage2_David%20Pidek.jpg; https://sysco-my.sharepoint.com/personal/kkhu6683_sysco_com/Documents/Apps/Microsoft%20Forms/Untitled%20form/Question/cake%20damage3_David%20Pidek.jpg | R51: Customer 058- 338731, Market Square Bloomfield ordered one case each of 6048365, 6048364 and product was delivered damaged and broken up, customer could not use. We are requesting credit for these. Please confirm and advise if you need anything else to process the credit, thank you.
A52: Kashif | C52: New | D52: We have routed your request to the seller. Please feel free to reach out next week if you do not see an update by then. | E52: • BWKHOTBL1020 - Black Lid • BWKDEERHLIDW - White Lid | G52: 51 | H52: 46210.665 | I52: 46210.668 | J52: sriz5487@shr.sysco.com | K52: Stefanie Rizzo-Zahn | L52: =OfficeForms.Table[[#This Row],[Email]] -> sriz5487@shr.sysco.com | M52: Eggheads Diner 073-482950 | N52: 7. Other (Do NOT use for Order/Product Related Issues) | W52: Cup Hot Boardwalk BWKDW12HCUP 12 oz Double-Walled Paper Hot Cups - White (500 Count) for Coffee and Tea 500/12 FOZ 6057583 what is the lid that fits this cup?
A53: Kashif | C53: Sent | D53: Unfortunately, this order has been processed, and the Seller is unable to cancel. Please note, Marketplace Third Party product orders are not eligible for Returns/Refunds or exchanges and is indicated at time of purchase. We wish we could be of more help but given Marketplace's policy, we are unable to assist further on this order. | G53: 52 | H53: 46210.676 | I53: 46210.677 | J53: gtin4580@emd.sysco.com | K53: Glenn Tindle | L53: =OfficeForms.Table[[#This Row],[Email]] -> gtin4580@emd.sysco.com | M53: Mdf7dd4e3a496 | N53: 2. Cancel an Order (Marketplace Third Party product orders are not eligible for Returns/Refunds or exchanges and is indicated at time of purchase) | X53: We Can only cancel an order if its in "awaiting acceptance" state and has not been accepted by the Seller. Once the order is accepted, it will no longer be cancellable and rejecting delivery will still hold the customer liable thus please confirm prior to placing any marketplace order. Also note that Sysco Shop does not have the ability to place orders automatically on behalf of customers.
A54: Kashif | C54: Sent | D54: Unfortunately, this order has been processed, and the Seller is unable to cancel. Please note, Marketplace Third Party product orders are not eligible for Returns/Refunds or exchanges and is indicated at time of purchase. We wish we could be of more help but given Marketplace's policy, we are unable to assist further on this order. | G54: 53 | H54: 46210.683 | I54: 46210.685 | J54: jman2281@ct.sysco.com | K54: John Mantzios | L54: =OfficeForms.Table[[#This Row],[Email]] -> jman2281@ct.sysco.com | M54: Mbcda4a2cf690 | N54: 2. Cancel an Order (Marketplace Third Party product orders are not eligible for Returns/Refunds or exchanges and is indicated at time of purchase) | X54: We Can only cancel an order if its in "awaiting acceptance" state and has not been accepted by the Seller. Once the order is accepted, it will no longer be cancellable and rejecting delivery will still hold the customer liable thus please confirm prior to placing any marketplace order. Also note that Sysco Shop does not have the ability to place orders automatically on behalf of customers.
A55: Brad | C55: Sent | D55: We apologize for the inconvenience. A support ticket has been opened with the supplier. Please feel free to reach out if you do not see an activity on your account by next week. | G55: 54 | H55: 46211.306 | I55: 46211.307 | J55: tspe6155@ok.sysco.com | K55: Tyler Spencer | L55: =OfficeForms.Table[[#This Row],[Email]] -> tspe6155@ok.sysco.com | M55: M4e3fd0028940 | N55: 3. Report an Issue with an Order Received (All Issues MUST be reported within 14 days of order and submitted with Images and Description of Issue) | R55: Customer received 6 cases of this steak finger and was out of temperature and unusable
A56: Brad | C56: Close | G56: 55 | H56: 46211.333 | I56: 46211.334 | J56: chil3771@emd.sysco.com | K56: Candace Lewis | L56: =OfficeForms.Table[[#This Row],[Email]] -> chil3771@emd.sysco.com | M56: N/a | N56: 5. Information on Product/Supplier (Please provide SUPC number that begins with "6xxxxxx" | U56: We are trying to work to source an additional product from supplier, Yello Tomato Ketchup. Can you please advise on how to secure this information? If there is a supplier contact I can reach out to get the necessary information to support sourcing?
A57: Brad | C57: Sent | D57: Marketplace orders have a 5-7 Business Day lead time and currently there is not an option to expedite delivery. | E57: fedex.com/wtrk/track/?trknbr=874004079106 | G57: 56 | H57: 46211.355 | I57: 46211.356 | J57: dcur8328@liny.sysco.com | K57: Daniel Curry | L57: =OfficeForms.Table[[#This Row],[Email]] -> dcur8328@liny.sysco.com | M57: M22f200b31969 | N57: 1. Receive ETA on Delivery (Marketplace orders have a 5-7 Business Day lead time and currently there is not an option to expedite deliver) | Y57: Marketplace orders have a 5-7 Business Day lead time and currently there is not an option to expedite deliver. Customer is liable for retrieving package if the business is closed or the address is incorrect. Please ensure Delivery address is updated in Salesforce prior to ordering.
A58: Brad | C58: Sent | D58: Yes, they appear online and should be available through Sysco Shop. | G58: 57 | H58: 46211.498 | I58: 46211.5 | J58: awal4199@min.sysco.com | K58: Anthony Wall | L58: =OfficeForms.Table[[#This Row],[Email]] -> awal4199@min.sysco.com | M58: Mce6fb214e212 | N58: 7. Other (Do NOT use for Order/Product Related Issues) | W58: I am looking for the lid that goes with the cup on the above order
C59: New | G59: 58 | H59: 46211.542 | I59: 46211.543 | J59: cbel9800@centralpa.sysco.com | K59: Chris Belusko | L59: =OfficeForms.Table[[#This Row],[Email]] -> cbel9800@centralpa.sysco.com | M59: 14399146 | N59: 2. Cancel an Order (Marketplace Third Party product orders are not eligible for Returns/Refunds or exchanges and is indicated at time of purchase) | X59: We Can only cancel an order if its in "awaiting acceptance" state and has not been accepted by the Seller. Once the order is accepted, it will no longer be cancellable and rejecting delivery will still hold the customer liable thus please confirm prior to placing any marketplace order. Also note that Sysco Shop does not have the ability to place orders automatically on behalf of customers.
A60: Brad | C60: Sent | D60: We apologize for the inconvenience. A support ticket has been opened with the supplier. Please feel free to reach out if you do not see an activity on your account by next week. | G60: 59 | H60: 46211.566 | I60: 46211.568 | J60: rhai2211@sysco.com | K60: Robert Haight | L60: =OfficeForms.Table[[#This Row],[Email]] -> rhai2211@sysco.com | M60: M156cc6eb133e | N60: 3. Report an Issue with an Order Received (All Issues MUST be reported within 14 days of order and submitted with Images and Description of Issue) | O60: https://sysco-my.sharepoint.com/personal/kkhu6683_sysco_com/Documents/Apps/Microsoft%20Forms/Untitled%20form/Question/IMG_5215_Robert%20Haight.jpeg; https://sysco-my.sharepoint.com/personal/kkhu6683_sysco_com/Documents/Apps/Microsoft%20Forms/Untitled%20form/Question/IMG_5216_Robert%20Haight.jpeg; https://sysco-my.sharepoint.com/personal/kkhu6683_sysco_com/Documents/Apps/Microsoft%20Forms/Untitled%20form/Question/IMG_5214_Robert%20Haight.jpeg | R60: Item was mispacked with the wrong sized containers in one of the sleeves
A61: Brad | C61: Sent | D61: Unfortunately, this order has been processed, and the Seller is unable to cancel. Please note, Marketplace Third Party product orders are not eligible for Returns/Refunds or exchanges and is indicated at time of purchase. We wish we could be of more help but given Marketplace's policy, we are unable to assist further on this order. | G61: 60 | H61: 46211.582 | I61: 46211.583 | J61: rdim2857@sfo.sysco.com | K61: Rocco DiMaggio | L61: =OfficeForms.Table[[#This Row],[Email]] -> rdim2857@sfo.sysco.com | M61: #M94a2d701f6e6 | N61: 2. Cancel an Order (Marketplace Third Party product orders are not eligible for Returns/Refunds or exchanges and is indicated at time of purchase) | X61: We Can only cancel an order if its in "awaiting acceptance" state and has not been accepted by the Seller. Once the order is accepted, it will no longer be cancellable and rejecting delivery will still hold the customer liable thus please confirm prior to placing any marketplace order. Also note that Sysco Shop does not have the ability to place orders automatically on behalf of customers.
A62: Brad | C62: Sent | D62: We apologize for the inconvenience. A support ticket has been opened with the supplier. Please feel free to reach out if you do not see an activity on your account by next week. | G62: 61 | H62: 46211.601 | I62: 46211.604 | J62: bami2547@sysco.com | K62: Bethany Amilibia | L62: =OfficeForms.Table[[#This Row],[Email]] -> bami2547@sysco.com | M62: Mf1ffad98a494-A | N62: 3. Report an Issue with an Order Received (All Issues MUST be reported within 14 days of order and submitted with Images and Description of Issue) | O62: https://sysco-my.sharepoint.com/personal/kkhu6683_sysco_com/Documents/Apps/Microsoft%20Forms/Untitled%20form/Question/80523057653__D5D36CF0-C803-4F5C-B09A-6A375D9A_Bethany%20Amilibia.jpeg; https://sysco-my.sharepoint.com/personal/kkhu6683_sysco_com/Documents/Apps/Microsoft%20Forms/Untitled%20form/Question/IMG_1823_Bethany%20Amilibia.PNG; https://sysco-my.sharepoint.com/personal/kkhu6683_sysco_com/Documents/Apps/Microsoft%20Forms/Untitled%20form/Question/IMG_1824_Bethany%20Amilibia.PNG | R62: Upon delivery, the item was dropped off in a plastic bag, and the case was covered in oil. The customer reported that 2 of the 7 bags had leaked, resulting in oil throughout the case. Due to the condition of the product, the customer considers the item unusable.
C63: New | G63: 62 | H63: 46211.605 | I63: 46211.606 | J63: jgla2956@metrony.sysco.com | K63: Justin Glasser | L63: =OfficeForms.Table[[#This Row],[Email]] -> jgla2956@metrony.sysco.com | M63: NA | N63: 7. Other (Do NOT use for Order/Product Related Issues) | W63: Customer needs access to marketplace 019897 Black Tap
C64: New | G64: 63 | H64: 46211.606 | I64: 46211.607 | J64: jgla2956@metrony.sysco.com | K64: Justin Glasser | L64: =OfficeForms.Table[[#This Row],[Email]] -> jgla2956@metrony.sysco.com | M64: 036333 | N64: 7. Other (Do NOT use for Order/Product Related Issues) | W64: Customer needs access to order marketplace items- 076 036333
A65: Omar | C65: Sent | G65: 64 | H65: 46211.65 | I65: 46211.65 | J65: khau4953@sfo.sysco.com | K65: Kailey Haught Larson | L65: =OfficeForms.Table[[#This Row],[Email]] -> khau4953@sfo.sysco.com | M65: cid#s attached on form to enable. NAID: ATGR site: 031 | N65: 6. Enable/Disable Customer for Marketplace Products (All TRS customers are enabled by default, LCC and CMU may have restrictions, please confirm prior to requesting) | V65: https://sysco-my.sharepoint.com/personal/kkhu6683_sysco_com/_layouts/15/Doc.aspx?sourcedoc=%7BED013FC2-F245-4A50-A367-2BE70BED1B97%7D&file=Sysco%20Market%20cid%23s%20to%20enable_Kailey%20Haught%20Larson.xlsx&action=default&mobileredirect=true
A66: Brad | C66: Sent | D66: We have routed your request to the seller for product availability. Please feel free to reach out next week if you do not see an update by then. | G66: 65 | H66: 46211.661 | I66: 46211.663 | J66: pnun9955@cfl.sysco.com | K66: Priscila Nunes | L66: =OfficeForms.Table[[#This Row],[Email]] -> pnun9955@cfl.sysco.com | M66: SODIE DOCES | N66: 5. Information on Product/Supplier (Please provide SUPC number that begins with "6xxxxxx" | U66: 6028728 Spread Caramel Bakeable, Dulce de Leche. 11lb pail im looking to get a sample of this item, can i get the company info?
A67: Brad | C67: Sent | D67: It appears to have been delivered. The seller has completed the order from their end and wish we could assist further. I would encourage the seller to connect directly with the delivery provider. | G67: 66 | H67: 46211.736 | I67: 46211.737 | J67: wcla4950@grr.sysco.com | K67: Thomas Clark | L67: =OfficeForms.Table[[#This Row],[Email]] -> wcla4950@grr.sysco.com | M67: M4a66a5bfc55e | N67: 4. Report an Order not Delivered ( Please note that customer rejecting delivery will suffice as a delivery issue) | S67: 6078509 two each
A68: Kashif | C68: Sent | E68: https://syscous-prod.mirakl.net/mmp/operator/order/Ma07af18d4038-A/message?sort=date%2CDESC&limit=25 | G68: 67 | H68: 46212.387 | I68: 46212.391 | J68: hher4631@sysco.com | K68: Holly Herring | L68: =OfficeForms.Table[[#This Row],[Email]] -> hher4631@sysco.com | M68: Ma07af18d4038 | N68: 3. Report an Issue with an Order Received (All Issues MUST be reported within 14 days of order and submitted with Images and Description of Issue) | O68: https://sysco-my.sharepoint.com/personal/kkhu6683_sysco_com/Documents/Apps/Microsoft%20Forms/Untitled%20form/Question/6071_Holly%20Herring.jpg; https://sysco-my.sharepoint.com/personal/kkhu6683_sysco_com/Documents/Apps/Microsoft%20Forms/Untitled%20form/Question/6072_Holly%20Herring.jpg; https://sysco-my.sharepoint.com/personal/kkhu6683_sysco_com/Documents/Apps/Microsoft%20Forms/Untitled%20form/Question/Wolfe%20City%201_Holly%20Herring.jpg
A69: Brad | C69: Sent | D69: It appears to have been delivered. The seller has completed the order from their end and wish we could assist further. I would encourage the seller to connect directly with the delivery provider. | G69: 68 | H69: 46212.469 | I69: 46212.471 | J69: pgra9460@sd.sysco.com | K69: Peter Grap | L69: =OfficeForms.Table[[#This Row],[Email]] -> pgra9460@sd.sysco.com | M69: Customer 036-501692 | Invoice date 5/6/26 - SUPC 6071576 for 120cs Kize bar brownie batter | N69: 1. Receive ETA on Delivery (Marketplace orders have a 5-7 Business Day lead time and currently there is not an option to expedite deliver) | Y69: Marketplace orders have a 5-7 Business Day lead time and currently there is not an option to expedite deliver. Customer is liable for retrieving package if the business is closed or the address is incorrect. Please ensure Delivery address is updated in Salesforce prior to ordering.
C70: New | G70: 69 | H70: 46212.503 | I70: 46212.507 | J70: jmad6864@iowa.sysco.com | K70: Jennifer Warburton | L70: =OfficeForms.Table[[#This Row],[Email]] -> jmad6864@iowa.sysco.com | M70: Lagomacinos Confectionary ML 039-563190, need to order 1 case of item TR-SCL140PET by Karat | N70: 5. Information on Product/Supplier (Please provide SUPC number that begins with "6xxxxxx" | U70: I need to order one case of item TR-SCL140PET but cannot find the right support area to get the item ordered. Customer care, purchasing, and category specialist are all unable to help place order.
A71: Brad | C71: Sent | D71: We have routed your request to the seller. Please feel free to reach out next week if you do not see an update by then. | G71: 70 | H71: 46212.515 | I71: 46212.518 | J71: jvel5786@shr.sysco.com | K71: Jose Velasquez | L71: =OfficeForms.Table[[#This Row],[Email]] -> jvel5786@shr.sysco.com | M71: Mb3371c027ebf | N71: 3. Report an Issue with an Order Received (All Issues MUST be reported within 14 days of order and submitted with Images and Description of Issue) | O71: https://sysco-my.sharepoint.com/personal/kkhu6683_sysco_com/Documents/Apps/Microsoft%20Forms/Untitled%20form/Question/broken%20jarr%20pickled%20onion%20brunch%20company_Jose%20Velasquez.jpeg | R71: customer received packaged damaged during transportation 3 broken jars and product arrive full of liquid from broken jars
A72: Brad | C72: Sent | D72: Unfortunately, this order has been processed, and the Seller is unable to cancel. Please note, Marketplace Third Party product orders are not eligible for Returns/Refunds or exchanges and is indicated at time of purchase. We wish we could be of more help but given Marketplace's policy, we are unable to assist further on this order. | G72: 71 | H72: 46212.552 | I72: 46212.552 | J72: twhi6823@cle.sysco.com | K72: Todd Whited | L72: =OfficeForms.Table[[#This Row],[Email]] -> twhi6823@cle.sysco.com | M72: Mecbced6fde2e and Md824ded63f61 | N72: 2. Cancel an Order (Marketplace Third Party product orders are not eligible for Returns/Refunds or exchanges and is indicated at time of purchase) | X72: We Can only cancel an order if its in "awaiting acceptance" state and has not been accepted by the Seller. Once the order is accepted, it will no longer be cancellable and rejecting delivery will still hold the customer liable thus please confirm prior to placing any marketplace order. Also note that Sysco Shop does not have the ability to place orders automatically on behalf of customers.
A73: Kashif | C73: Sent | E73: the email address that placed the order was erinchef@yahoo.com. Please Note that only autorized user can make purchases and there is no automation in the system thus someone from this account did place the order | G73: 72 | H73: 46212.634 | I73: 46212.638 | J73: dfet2145@cha.sysco.com | K73: Del Fetters | L73: =OfficeForms.Table[[#This Row],[Email]] -> dfet2145@cha.sysco.com | M73: M7ee8f246a7f0 | N73: 3. Report an Issue with an Order Received (All Issues MUST be reported within 14 days of order and submitted with Images and Description of Issue) | R73: Customer did not order this item. Can you tell who did. Customer will refuse invoice.
A74: Brad | C74: Sent | D74: Unfortunately, this order has been processed, and the Seller is unable to cancel. Please note, Marketplace Third Party product orders are not eligible for Returns/Refunds or exchanges and is indicated at time of purchase. We wish we could be of more help but given Marketplace's policy, we are unable to assist further on this order. | G74: 73 | H74: 46212.647 | I74: 46212.649 | J74: dlen6100@sfo.sysco.com | K74: David Lengvarsky | L74: =OfficeForms.Table[[#This Row],[Email]] -> dlen6100@sfo.sysco.com | M74: Mb1dcdbb9c0d3 | N74: 2. Cancel an Order (Marketplace Third Party product orders are not eligible for Returns/Refunds or exchanges and is indicated at time of purchase) | X74: We Can only cancel an order if its in "awaiting acceptance" state and has not been accepted by the Seller. Once the order is accepted, it will no longer be cancellable and rejecting delivery will still hold the customer liable thus please confirm prior to placing any marketplace order. Also note that Sysco Shop does not have the ability to place orders automatically on behalf of customers.
C75: New | E75: this order has been cancelled | G75: 74 | H75: 46212.951 | I75: 46212.951 | J75: klav2850@wtx.sysco.com | K75: Kara Vaughn | L75: =OfficeForms.Table[[#This Row],[Email]] -> klav2850@wtx.sysco.com | M75: Mcccb9ad25f83 | N75: 1. Receive ETA on Delivery (Marketplace orders have a 5-7 Business Day lead time and currently there is not an option to expedite deliver)
A76: Brad | C76: Close | D76: This item is currently out of stock and the seller does not have an ETA on its availability yet. If you do not see this back on after 2 weeks, please feel free to reach out to us. | G76: 75 | H76: 46213.391 | I76: 46213.394 | J76: fbel8389@philly.sysco.com | K76: Frank Bellace | L76: =OfficeForms.Table[[#This Row],[Email]] -> fbel8389@philly.sysco.com | M76: there is no order # since code disapeared | N76: 7. Other (Do NOT use for Order/Product Related Issues) | W76: the code for buffalo ranch sauce for code 6026774 – 6/16 oz bottles went away for a 3rd party order and need to get code back in shop
A77: Omar | C77: Sent | G77: 76 | H77: 46213.449 | I77: 46213.453 | J77: ayep4668@centralca.sysco.com | K77: Alma Leon | L77: =OfficeForms.Table[[#This Row],[Email]] -> ayep4668@centralca.sysco.com | M77: 004-693703;052897698;052897363 | N77: 6. Enable/Disable Customer for Marketplace Products (All TRS customers are enabled by default, LCC and CMU may have restrictions, please confirm prior to requesting) | V77: https://sysco-my.sharepoint.com/personal/kkhu6683_sysco_com/_layouts/15/Doc.aspx?sourcedoc=%7B1CB3BA3F-1AD6-4D64-90A2-819B335088A8%7D&file=SCOPP_3P_Template%20(9)_Alma%20Leon.xlsx&action=default&mobileredirect=true
A78: Brad | C78: Close | D78: We have routed your request to the seller for product availability. Please feel free to reach out next week if you do not see an update by then. | G78: 77 | H78: 46213.549 | I78: 46213.561 | J78: acow7570@wtx.sysco.com | K78: Amy Cowley | L78: =OfficeForms.Table[[#This Row],[Email]] -> acow7570@wtx.sysco.com | M78: there is no order number in shop or on the invoice delivered 7/1 per invoice ordered 6/30 all other details in below message | N78: 7. Other (Do NOT use for Order/Product Related Issues) | W78: 1.my customer ordered lid 6055590 it is non returnable. I need supc for all deli containers that will fit the lid. 2. my customer ordered cup 6044114, I need supc for a lid that will fit the cup. I also need a list of all matching cup sizes that will match the lid
A79: Brad | C79: Sent | D79: We apologize for the inconvenience. A support ticket has been opened with the supplier. Please feel free to reach out if you do not see an activity on your account by next week. | G79: 78 | H79: 46213.937 | I79: 46213.942 | J79: ehar9736@balt.sysco.com | K79: Emily Harris | L79: =OfficeForms.Table[[#This Row],[Email]] -> ehar9736@balt.sysco.com | M79: Me979a1ffb3e4 | N79: 3. Report an Issue with an Order Received (All Issues MUST be reported within 14 days of order and submitted with Images and Description of Issue) | O79: https://sysco-my.sharepoint.com/personal/kkhu6683_sysco_com/Documents/Apps/Microsoft%20Forms/Untitled%20form/Question/Dented%20Celsius%20Cans_Emily%20Harris.jpeg; https://sysco-my.sharepoint.com/personal/kkhu6683_sysco_com/Documents/Apps/Microsoft%20Forms/Untitled%20form/Question/Damaged%20Cans_Emily%20Harris.jpeg; https://sysco-my.sharepoint.com/personal/kkhu6683_sysco_com/Documents/Apps/Microsoft%20Forms/Untitled%20form/Question/Dented%20Cans%20pt.4_Emily%20Harris.jpeg; https://sysco-my.sharepoint.com/personal/kkhu6683_sysco_com/Documents/Apps/Microsoft%20Forms/Untitled%20form/Question/Dented%20Celsius%20Cans%20with%20Labels_Emily%20Harris.jpeg | P79: https://sysco-my.sharepoint.com/personal/kkhu6683_sysco_com/Documents/Apps/Microsoft%20Forms/Untitled%20form/Report%20an%20Issue%20with%20Item%20Received%20Please%20Insert%203%201/Dented%20Cans%20pt.2_Emily%20Harris.jpeg | Q79: https://sysco-my.sharepoint.com/personal/kkhu6683_sysco_com/Documents/Apps/Microsoft%20Forms/Untitled%20form/Report%20an%20Issue%20with%20Item%20Received%20Please%20Insert%203/Dented%20Cans%20pt.3_Emily%20Harris.jpeg | R79: I would like to request a credit for customer Sweetbites (012-213124) for a case of Celsius energy drinks that arrived damaged. Account #012-213124 Item Name: Celsius Drink Energy Peach Mango Green Tea SUPC 6037664 All but two of the cans received were damaged & the customer is requesting credit for the item. Attached are photos of the damaged cans. Thank you.
A80: Brad | C80: Sent | D80: We apologize for the inconvenience. A support ticket has been opened with the supplier. Please feel free to reach out if you do not see an activity on your account by next week. | G80: 79 | H80: 46216.33 | I80: 46216.369 | J80: jgla2956@metrony.sysco.com | K80: Justin Glasser | L80: =OfficeForms.Table[[#This Row],[Email]] -> jgla2956@metrony.sysco.com | M80: M23ac7388318d | N80: 3. Report an Issue with an Order Received (All Issues MUST be reported within 14 days of order and submitted with Images and Description of Issue) | O80: https://sysco-my.sharepoint.com/personal/kkhu6683_sysco_com/Documents/Apps/Microsoft%20Forms/Untitled%20form/Question/ICe%20Cream%20Cookie%20Credit_Justin%20Glasser.pdf | R80: Shop says packed 324 ct but customer only received 18 in total. Product is missing.
C81: New | G81: 80 | H81: 46216.376 | I81: 46216.38 | J81: khau4953@sfo.sysco.com | K81: Kailey Haught Larson | L81: =OfficeForms.Table[[#This Row],[Email]] -> khau4953@sfo.sysco.com | M81: Mfaa2e8e4689d, 031-622997 7/11/26 supc 6083021. M4f7fbb6fbfb2 031-6229660 7/11/26 supc 6083021. Both orders show as no ship, but all of these orders placed same day for same customer group appear to have processed: all supc 6083021, 031-622974 Mf54259bf24c3, 031-622928 M2c6e9c1d8c4d. as of 7/13 supc 6083021 doesn't show in SHOP | N81: 7. Other (Do NOT use for Order/Product Related Issues) | W81: supc not showing in sysco 2 days after initial orders placed and orders are showing as no ship in SHOP even though customer isn't on hold.
A82: Brad | C82: Sent | D82: We apologize for the inconvenience. A support ticket has been opened with the supplier. Please feel free to reach out if you do not see an activity on your account by next week. | G82: 81 | H82: 46216.408 | I82: 46216.409 | J82: jale3447@knox.sysco.com | K82: Javier Alfredo Aleman Martinez | L82: =OfficeForms.Table[[#This Row],[Email]] -> jale3447@knox.sysco.com | M82: M7b6eae5d5a13 | N82: 4. Report an Order not Delivered ( Please note that customer rejecting delivery will suffice as a delivery issue) | S82: Product not shipped yet to customer.
A83: Brad | C83: Close | G83: 82 | H83: 46216.43 | I83: 46216.432 | J83: bnet8174@shr.sysco.com | K83: Brandee Nettles | L83: =OfficeForms.Table[[#This Row],[Email]] -> bnet8174@shr.sysco.com | M83: 620504, Item code 6064310 Spoon soup karat 1,000ct med-heavy weight asian soup spoon, black | N83: 7. Other (Do NOT use for Order/Product Related Issues) | W83: customer needs proof of delivery to pay invoice.
A84: Omar | C84: Sent | G84: 83 | H84: 46216.439 | I84: 46216.448 | J84: ddes4323@hou.sysco.com | K84: Darlene Deslatte | L84: =OfficeForms.Table[[#This Row],[Email]] -> ddes4323@hou.sysco.com | M84: see file attached | N84: 6. Enable/Disable Customer for Marketplace Products (All TRS customers are enabled by default, LCC and CMU may have restrictions, please confirm prior to requesting) | V84: https://sysco-my.sharepoint.com/personal/kkhu6683_sysco_com/_layouts/15/Doc.aspx?sourcedoc=%7B87CD90B3-C22A-4638-915C-23EFBF298D3D%7D&file=Account%20Listing%20Darlene%20Marketplace-Disable-A_Darlene%20Deslatte.xlsx&action=default&mobileredirect=true
A85: Brad | C85: Sent | D85: Marketplace orders have a 5-7 Business Day lead time and currently there is not an option to expedite delivery. | G85: 84 | H85: 46216.447 | I85: 46216.448 | J85: sdem2154@emd.sysco.com | K85: Stefanie Demas | L85: =OfficeForms.Table[[#This Row],[Email]] -> sdem2154@emd.sysco.com | M85: Me50b6e6a1903 | N85: 1. Receive ETA on Delivery (Marketplace orders have a 5-7 Business Day lead time and currently there is not an option to expedite deliver) | Y85: Marketplace orders have a 5-7 Business Day lead time and currently there is not an option to expedite deliver. Customer is liable for retrieving package if the business is closed or the address is incorrect. Please ensure Delivery address is updated in Salesforce prior to ordering.
C86: New | D86: Unfortunately, this order has been processed, and the Seller is unable to cancel. Please note, Marketplace Third Party product orders are not eligible for Returns/Refunds or exchanges and is indicated at time of purchase. We wish we could be of more help but given Marketplace's policy, we are unable to assist further on this order. | G86: 85 | H86: 46216.456 | I86: 46216.458 | J86: kric8807@indy.sysco.com | K86: Kaleigh Richardson | L86: =OfficeForms.Table[[#This Row],[Email]] -> kric8807@indy.sysco.com | M86: M91ae7e3de31b | N86: 3. Report an Issue with an Order Received (All Issues MUST be reported within 14 days of order and submitted with Images and Description of Issue) | R86: This item should not have been ordered. An SC that was covering me while I was on vacation ordered the incorrect item.
A87: Kashif | C87: Sent | D87: We apologize for the inconvenience. A support ticket has been opened with the supplier. Please feel free to reach out if you do not see an activity on your account by next week. | E87: https://syscous-prod.mirakl.net/mmp/operator/order/Mb9b0e14c9650-A/message?sort=date%2CDESC&limit=25 | G87: 86 | H87: 46216.463 | I87: 46216.464 | J87: tlew3091@sysco.com | K87: Taylor Lewis | L87: =OfficeForms.Table[[#This Row],[Email]] -> tlew3091@sysco.com | M87: Mb9b0e14c9650 | N87: 4. Report an Order not Delivered ( Please note that customer rejecting delivery will suffice as a delivery issue) | S87: 6036247 1CS
A88: Brad | C88: Sent | G88: 87 | H88: 46216.467 | I88: 46216.468 | J88: dlon7838@sysco.com | K88: Diana Carolina Londono Trujillo | L88: =OfficeForms.Table[[#This Row],[Email]] -> dlon7838@sysco.com | M88: MILWAUKEE GRILL SUPPLIES (018-180349) | N88: 7. Other (Do NOT use for Order/Product Related Issues) | W88: do we stock this item: Filtrox F-40 SuperSorb Fryer Filter Pad 12.5X15 IN Carbon 30/Case SKU# FILCF40 Mfr# FILCF-40
A89: Brad | C89: Closed | D89: This item is currently out of stock and the seller does not have an ETA on its availability yet. If you do not see this back on after 2 weeks, please feel free to reach out to us. | G89: 88 | H89: 46216.472 | I89: 46216.475 | J89: evan5497@lincoln.sysco.com | K89: Emily Vandrey | L89: =OfficeForms.Table[[#This Row],[Email]] -> evan5497@lincoln.sysco.com | M89: there is not an order number. I need an update on availability | N89: 5. Information on Product/Supplier (Please provide SUPC number that begins with "6xxxxxx" | U89: 6045427.. I would like an update on the availability of this SUPC. It is showing as unavailable for the last 60+ days Container Food 4-Pack Compostable PLA 2.75" Cupcake & Muffin Containers | Good Natured Products | 216 count 6045427 216/4 Good Natured Products Unavailable
A90: Brad | C90: Sent | G90: 89 | H90: 46216.48 | I90: 46216.484 | J90: whon8322@wtx.sysco.com | K90: Wendy Honaker | L90: =OfficeForms.Table[[#This Row],[Email]] -> whon8322@wtx.sysco.com | M90: Trying to find a large party. 3 compartment black bottom, clear top 14x14 tray. | N90: 7. Other (Do NOT use for Order/Product Related Issues) | W90: Trying to find a large party. 3 compartment black bottom, clear top 14x14 tray.
A91: Brad | C91: Close | D91: This item is currently out of stock and the seller does not have an ETA on its availability yet. If you do not see this back on after 2 weeks, please feel free to reach out to us. | G91: 90 | H91: 46216.493 | I91: 46216.498 | J91: jhar0408@nd.sysco.com | K91: Jon Harrison | L91: =OfficeForms.Table[[#This Row],[Email]] -> jhar0408@nd.sysco.com | M91: #M3f60aac7d654 | N91: 5. Information on Product/Supplier (Please provide SUPC number that begins with "6xxxxxx" | U91: I ordered item # 6056882 and 6056466 thinking they would fit each other. They did not. Could you please tell me the correct pairing for these?
A92: Kashif | C92: Sent | E92: This is now complete and refunded | G92: 91 | H92: 46216.5 | I92: 46216.504 | J92: jjac0949@nola.sysco.com | K92: Jonathan Jacques | L92: =OfficeForms.Table[[#This Row],[Email]] -> jjac0949@nola.sysco.com | M92: M562014ba0d18 | N92: 3. Report an Issue with an Order Received (All Issues MUST be reported within 14 days of order and submitted with Images and Description of Issue) | R92: Item received by the customer was fresh/thawed out upon delivery with no dry ice to keep the product from spoiling. We have made numerous attempts to issue credit for this customer but we are going on over a month with no resolution. I have customer withholding payment on this invoice causing disruption with their account. Manufacturer has already approved credit now we are waiting on on Sysco. Please help us resolve this matter ASAP. Thanks
A93: Brad | C93: Sent | D93: This item is currently out of stock and the seller does not have an ETA on its availability yet. If you do not see this back on after 2 weeks, please feel free to reach out to us. | G93: 92 | H93: 46216.547 | I93: 46216.548 | J93: hped1119@sd.sysco.com | K93: Heather Pedigo | L93: =OfficeForms.Table[[#This Row],[Email]] -> hped1119@sd.sysco.com | M93: 036-733159 | N93: 5. Information on Product/Supplier (Please provide SUPC number that begins with "6xxxxxx" | U93: Container Paper SCT 1593 White Paper Bakery Boxes - 14x14x6 Inches - 50 Count Durable and Secure Packaging for Baked Goods 6057220 50/1 SCT Unavailable
A94: Brad | C94: Sent | D94: We have enabled these customer account to view and order Marketplace Third Party Products. Please note it will take about 24 hours to take effect. | G94: 93 | H94: 46216.616 | I94: 46216.633 | J94: ktoy2427@sfo.sysco.com | K94: Katherine Young | L94: =OfficeForms.Table[[#This Row],[Email]] -> ktoy2427@sfo.sysco.com | M94: 050-975482 Little Chihuahua Noe Vally 3, 050-156135 Little Chihuahua Polk St | N94: 6. Enable/Disable Customer for Marketplace Products (All TRS customers are enabled by default, LCC and CMU may have restrictions, please confirm prior to requesting) | V94: https://sysco-my.sharepoint.com/personal/kkhu6683_sysco_com/_layouts/15/Doc.aspx?sourcedoc=%7B7C821E64-ED56-45AA-99AD-7410D7692A57%7D&file=SCOPP_3P_Template%20(9)_Katherine%20Young.xlsx&action=default&mobileredirect=true
C95: New | G95: 94 | H95: 46216.703 | I95: 46216.709 | J95: kada2513@ctx.sysco.com | K95: Karrie Adams-Johansson | L95: =OfficeForms.Table[[#This Row],[Email]] -> kada2513@ctx.sysco.com | M95: 14401514 customer 415059 date: 7/10/26 is it this?? | N95: 1. Receive ETA on Delivery (Marketplace orders have a 5-7 Business Day lead time and currently there is not an option to expedite deliver) | Y95: Marketplace orders have a 5-7 Business Day lead time and currently there is not an option to expedite deliver. Customer is liable for retrieving package if the business is closed or the address is incorrect. Please ensure Delivery address is updated in Salesforce prior to ordering.
A96: Brad | C96: Sent | D96: This item is currently out of stock and the seller does not have an ETA on its availability yet. If you do not see this back on after 2 weeks, please feel free to reach out to us. | G96: 95 | H96: 46216.714 | I96: 46216.715 | J96: klav2850@wtx.sysco.com | K96: Kara Vaughn | L96: =OfficeForms.Table[[#This Row],[Email]] -> klav2850@wtx.sysco.com | M96: Mfe9f857d1344 | N96: 3. Report an Issue with an Order Received (All Issues MUST be reported within 14 days of order and submitted with Images and Description of Issue) | R96: Customer ordered cups and lids, but they do not match. I am needing help finding the lid to this cup and see if they can return the lids on this order.
A97: Brad | C97: Sent | D97: We have routed your request to the seller. Please feel free to reach out next week if you do not see an update by then. | G97: 96 | H97: 46216.81 | I97: 46216.812 | J97: lstc4806@cil.sysco.com | K97: Laura St Clair | L97: =OfficeForms.Table[[#This Row],[Email]] -> lstc4806@cil.sysco.com | M97: M30acc27037ac | N97: 3. Report an Issue with an Order Received (All Issues MUST be reported within 14 days of order and submitted with Images and Description of Issue) | R97: This is not what my customer thought it was. I know that it said no returns but can they return it?
A98: Brad | C98: Sent | D98: Unfortunately, this order has been processed, and the Seller is unable to cancel. Please note, Marketplace Third Party product orders are not eligible for Returns/Refunds or exchanges and is indicated at time of purchase. We wish we could be of more help but given Marketplace's policy, we are unable to assist further on this order. | G98: 97 | H98: 46216.827 | I98: 46216.828 | J98: aleb5719@int.sysco.com | K98: Aaron LeBoeuf | L98: =OfficeForms.Table[[#This Row],[Email]] -> aleb5719@int.sysco.com | M98: Med7c9ec650f5 | N98: 2. Cancel an Order (Marketplace Third Party product orders are not eligible for Returns/Refunds or exchanges and is indicated at time of purchase) | X98: We Can only cancel an order if its in "awaiting acceptance" state and has not been accepted by the Seller. Once the order is accepted, it will no longer be cancellable and rejecting delivery will still hold the customer liable thus please confirm prior to placing any marketplace order. Also note that Sysco Shop does not have the ability to place orders automatically on behalf of customers.
A99: Brad | C99: Sent | D99: Unfortunately, this order has been processed, and the Seller is unable to cancel. Please note, Marketplace Third Party product orders are not eligible for Returns/Refunds or exchanges and is indicated at time of purchase. We wish we could be of more help but given Marketplace's policy, we are unable to assist further on this order. | G99: 98 | H99: 46217.307 | I99: 46217.307 | J99: jgla2956@metrony.sysco.com | K99: Justin Glasser | L99: =OfficeForms.Table[[#This Row],[Email]] -> jgla2956@metrony.sysco.com | M99: M844a1754b8ca | N99: 2. Cancel an Order (Marketplace Third Party product orders are not eligible for Returns/Refunds or exchanges and is indicated at time of purchase) | X99: We Can only cancel an order if its in "awaiting acceptance" state and has not been accepted by the Seller. Once the order is accepted, it will no longer be cancellable and rejecting delivery will still hold the customer liable thus please confirm prior to placing any marketplace order. Also note that Sysco Shop does not have the ability to place orders automatically on behalf of customers.
A100: Brad | C100: Sent | D100: Unfortunately, this order has been processed, and the Seller is unable to cancel. Please note, Marketplace Third Party product orders are not eligible for Returns/Refunds or exchanges and is indicated at time of purchase. We wish we could be of more help but given Marketplace's policy, we are unable to assist further on this order. | G100: 99 | H100: 46217.339 | I100: 46217.341 | J100: kgor4562@sysco.com | K100: Kelly Gorgas McCormac | L100: =OfficeForms.Table[[#This Row],[Email]] -> kgor4562@sysco.com | M100: M55e408c1b73d | N100: 2. Cancel an Order (Marketplace Third Party product orders are not eligible for Returns/Refunds or exchanges and is indicated at time of purchase) | X100: We Can only cancel an order if its in "awaiting acceptance" state and has not been accepted by the Seller. Once the order is accepted, it will no longer be cancellable and rejecting delivery will still hold the customer liable thus please confirm prior to placing any marketplace order. Also note that Sysco Shop does not have the ability to place orders automatically on behalf of customers.
...

Sheet Standard Responses
A3: Category | B3: Message response
A4: General | B4: We have routed your request to the seller. Please feel free to reach out next week if you do not see an update by then.
A5: General | B5: Thank you for sharing, If you do not see activity on your account by next week, please reach back out.
A6: Incident | B6: We apologize for the inconvenience. A support ticket has been opened with the supplier. Please feel free to reach out if you do not see an activity on your account by next week.
A7: Availability | B7: This item is currently out of stock and the seller does not have an ETA on its availability yet. If you do not see this back on after 2 weeks, please feel free to reach out to us.
A8: Availability | B8: Yes, they appear online and should be available through Sysco Shop.
A9: Availability | B9: We have routed your request to the seller for product availability. Please feel free to reach out next week if you do not see an update by then.
A10: Availability | B10: It does appear to have inventory. Please ensure the account being used is located in united states and has access to marketplace products. There are times where Suppliers limit the geos they serve which may impact what customers can see and purchase.
A11: Seller Info | B11: We typically don’t share seller contact info and prefer a single tone when engaging with the seller. That said, is there anything you like us to communicate with the seller.
A12: Product Inquiry | B12: Can you please advise what info/support is needed regarding these products below? We typically do not give out supplier information, but are able to communicate with them on your behalf.
A13: Cancel | B13: Unfortunately, this order has been processed, and the Seller is unable to cancel. Please note, Marketplace Third Party product orders are not eligible for Returns/Refunds or exchanges and is indicated at time of purchase. We wish we could be of more help but given Marketplace's policy, we are unable to assist further on this order.
A14: Incident | B14: Thank you for sharing. We have reached out to the seller and have created a support ticket. Please feel free to reach out to us next week if you do not see any activity on this order.
... A26: Incomplete Info | B26: It appears that the ticket is incomplete, Please fill it out again and be sure to complete all information required for us to Process.
A50: Status
A51: Delete
A52: New
A53: Ready
A54: Sent
A55: Escalate
A56: Close

Sheet EmailDrafts
A1: Status | B1: Incident # | C1: Send To | D1: Subject | E1: Body
A2: Sent | B2: =Tickets!G6 -> 5 | D2: =CONCATENATE("Incident Regarding ", Tickets!M6) -> Incident Regarding M85a82b1b7b9c | E2: =CONCATENATE("Hi, ",Tickets!D6," Additional Detail (if Any:) ",Tickets!E6,"."," Thanks, Marketplace Support Team") -> Hi, We apologize for the inconvenience. A support ticket has been opened with the supplier. Please feel free to reach out if you do not see an activity on your account by next week. Additional Detail (if Any:) created in Mirakle. Thanks, Marketplace Support Team
A3: Sent | B3: =Tickets!G7 -> 6 | C3: =Tickets!L7 | D3: =CONCATENATE("Incident Regarding ", Tickets!M7) -> Incident Regarding Mf685c21465c4 | E3: =CONCATENATE("Hi, ",Tickets!D7," Additional Detail (if Any:) ",Tickets!E7,"."," Thanks, Marketplace Support Team") -> Hi, We apologize for the inconvenience. A support ticket has been opened with the supplier. Please feel free to reach out if you do not see an activity on your account by next week. Additional Detail (if Any:) https://syscous-prod.mirakl.net/mmp/operator/order/Mf685c21465c4-A/message?sort=date%2CDESC&limit=25. Thanks, Marketplace Support Team
A4: Sent | B4: =Tickets!G8 -> 7 | C4: =Tickets!L8 -> pgra9460@sd.sysco.com | D4: =CONCATENATE("Incident Regarding ", Tickets!M8) -> Incident Regarding Mee63e533470c | E4: =CONCATENATE("Hi, ",Tickets!D8," Additional Detail (if Any:) ",Tickets!E8,"."," Thanks, Marketplace Support Team") -> Hi, We apologize for the inconvenience. A support ticket has been opened with the supplier. Please feel free to reach out if you do not see an activity on your account by next week. Additional Detail (if Any:) https://syscous-prod.mirakl.net/mmp/operator/order/Mee63e533470c-A/message/bbe15d84-7a18-42d9-9c11-f515ad5be06f/details. Thanks, Marketplace Support Team
A5: Sent | B5: =Tickets!G9 -> 8 | C5: =Tickets!L9 -> nfon6129@emd.sysco.com | D5: =CONCATENATE("Incident Regarding ", Tickets!M9) -> Incident Regarding Mb5a6fa6ccf65 | E5: =CONCATENATE("Hi, ",Tickets!D9," Additional Detail (if Any:) ",Tickets!E9,"."," Thanks, Marketplace Support Team") -> Hi, Unfortunately, this order has been processed, and the Seller is unable to cancel. Please note, Marketplace Third Party product orders are not eligible for Returns/Refunds or exchanges and is indicated at time of purchase. We wish we could be of more help but given Marketplace's policy, we are unable to assist further on this order. Additional Detail (if Any:) . Thanks, Marketplace Support Team
A6: Sent | B6: =Tickets!G10 -> 9 | C6: =Tickets!L10 -> jmat3941@int.sysco.com | D6: =CONCATENATE("Incident Regarding ", Tickets!M10) -> Incident Regarding M4e8180f441d4 | E6: =CONCATENATE("Hi, ",Tickets!D10," Additional Detail (if Any:) ",Tickets!E10,"."," Thanks, Marketplace Support Team") -> Hi, We apologize for the inconvenience. A support ticket has been opened with the supplier. Please feel free to reach out if you do not see an activity on your account by next week. Additional Detail (if Any:) https://syscous-prod.mirakl.net/mmp/operator/order/M4e8180f441d4-A/message/1d20a812-1f34-4962-acc3-7261aeb2e93f/details. Thanks, Marketplace Support Team
A7: Sent | B7: =Tickets!G11 -> 10 | C7: =Tickets!L11 -> mcan3533@min.sysco.com | D7: =CONCATENATE("Incident Regarding ", Tickets!M11) -> Incident Regarding Mc0f2cf114a79 | E7: =CONCATENATE("Hi, ",Tickets!D11," Additional Detail (if Any:) ",Tickets!E11,"."," Thanks, Marketplace Support Team") -> Hi, Unfortunately, this order has been processed, and the Seller is unable to cancel. Please note, Marketplace Third Party product orders are not eligible for Returns/Refunds or exchanges and is indicated at time of purchase. We wish we could be of more help but given Marketplace's policy, we are unable to assist further on this order. Additional Detail (if Any:) . Thanks, Marketplace Support Team
A8: Sent | B8: =Tickets!G12 -> 11 | C8: =Tickets!L12 -> jsca2787@philly.sysco.com | D8: =CONCATENATE("Incident Regarding ", Tickets!M12) -> Incident Regarding Mffc98f09d1a7 | E8: =CONCATENATE("Hi, ",Tickets!D12," Additional Detail (if Any:) ",Tickets!E12,"."," Thanks, Marketplace Support Team") -> Hi, We have routed your request to the seller. Please feel free to reach out next week if you do not see an update by then. Additional Detail (if Any:) https://syscous-prod.mirakl.net/mmp/operator/order/Mffc98f09d1a7-A/message?sort=date%2CDESC&limit=25. Thanks, Marketplace Support Team
A9: Sent | B9: =Tickets!G13 -> 12 | C9: =Tickets!L13 -> jswe4549@boston.sysco.com | D9: =CONCATENATE("Incident Regarding ", Tickets!M13) -> Incident Regarding Ma825a338a0f6 | E9: =CONCATENATE("Hi, ",Tickets!D13," Additional Detail (if Any:) ",Tickets!E13,"."," Thanks, Marketplace Support Team") -> Hi, Thank you for sharing. Please fill out the form again and select option #3 "issue with order received" and complete the additional details before we can proceed with a ticket Additional Detail (if Any:) . Thanks, Marketplace Support Team
A10: Sent | B10: =Tickets!G14 -> 13 | C10: =Tickets!L14 -> acro7701@sysco.com | D10: =CONCATENATE("Incident Regarding ", Tickets!M14) -> Incident Regarding M9f8b6d10da2e | E10: =CONCATENATE("Hi, ",Tickets!D14," Additional Detail (if Any:) ",Tickets!E14,"."," Thanks, Marketplace Support Team") -> Hi, We apologize for the inconvenience. A support ticket has been opened with the supplier. Please feel free to reach out if you do not see an activity on your account by next week. Additional Detail (if Any:) https://syscous-prod.mirakl.net/mmp/operator/order/M9f8b6d10da2e-A/message?sort=date%2CDESC&limit=25. Thanks, Marketplace Support Team
A11: Sent | B11: =Tickets!G15 -> 14 | C11: =Tickets!L15 -> sriz5487@shr.sysco.com | D11: =CONCATENATE("Incident Regarding ", Tickets!M15) -> Incident Regarding #M827c03c17592 | E11: =CONCATENATE("Hi, ",Tickets!D15," Additional Detail (if Any:) ",Tickets!E15,"."," Thanks, Marketplace Support Team") -> Hi, We have routed your request to the seller. Please feel free to reach out next week if you do not see an update by then. Additional Detail (if Any:) . Thanks, Marketplace Support Team
A12: Sent | B12: =Tickets!G16 -> 15 | C12: =Tickets!L16 -> blin7890@ntx.sysco.com | D12: =CONCATENATE("Incident Regarding ", Tickets!M16) -> Incident Regarding Mbc51e08c2606-A | E12: =CONCATENATE("Hi, ",Tickets!D16," Additional Detail (if Any:) ",Tickets!E16,"."," Thanks, Marketplace Support Team") -> Hi, We apologize for the inconvenience. A support ticket has been opened with the supplier. Please feel free to reach out if you do not see an activity on your account by next week. Additional Detail (if Any:) https://syscous-prod.mirakl.net/mmp/operator/order/Mbc51e08c2606-A/message?sort=date%2CDESC&limit=25. Thanks, Marketplace Support Team
A13: Sent | B13: =Tickets!G17 -> 16 | C13: =Tickets!L17 -> jswe4549@boston.sysco.com | D13: =CONCATENATE("Incident Regarding ", Tickets!M17) -> Incident Regarding Me1135712a256 | E13: =CONCATENATE("Hi, ",Tickets!D17," Additional Detail (if Any:) ",Tickets!E17,"."," Thanks, Marketplace Support Team") -> Hi, Unfortunately, this order has been processed, and the Seller is unable to cancel. Please note, Marketplace Third Party product orders are not eligible for Returns/Refunds or exchanges and is indicated at time of purchase. We wish we could be of more help but given Marketplace's policy, we are unable to assist further on this order. Additional Detail (if Any:) . Thanks, Marketplace Support Team
A14: Sent | B14: =Tickets!G18 -> 17 | C14: =Tickets!j6 | D14: =CONCATENATE("Incident Regarding ", Tickets!M18) -> Incident Regarding Mad6533fba6f2 | E14: =CONCATENATE("Hi, ",Tickets!D18," Additional Detail (if Any:) ",Tickets!E18,"."," Thanks, Marketplace Support Team") -> Hi, We have routed your request to the seller. Please feel free to reach out next week if you do not see an update by then. Additional Detail (if Any:) https://syscous-prod.mirakl.net/mmp/operator/order/Mad6533fba6f2-A/message?sort=date%2CDESC&limit=25. Thanks, Marketplace Support Team
A15: Sent | B15: =Tickets!G19 -> 18 | C15: =Tickets!L19 -> pste6327@mt.sysco.com | D15: =CONCATENATE("Incident Regarding ", Tickets!M19) -> Incident Regarding M346b5eb63018 | E15: =CONCATENATE("Hi, ",Tickets!D19," Additional Detail (if Any:) ",Tickets!E19,"."," Thanks, Marketplace Support Team") -> Hi, Unfortunately, this order has been processed, and the Seller is unable to cancel. Please note, Marketplace Third Party product orders are not eligible for Returns/Refunds or exchanges and is indicated at time of purchase. We wish we could be of more help but given Marketplace's policy, we are unable to assist further on this order. Additional Detail (if Any:) . Thanks, Marketplace Support Team
A16: Sent | B16: =Tickets!G20 -> 19 | C16: =Tickets!L20 -> ggal6788@rs.sysco.com | D16: =CONCATENATE("Incident Regarding ", Tickets!M20) -> Incident Regarding Mf21fe5c2517b | E16: =CONCATENATE("Hi, ",Tickets!D20," Additional Detail (if Any:) ",Tickets!E20,"."," Thanks, Marketplace Support Team") -> Hi, Thank you for sharing, If you do not see activity on your account by next week, please reach back out. Additional Detail (if Any:) https://syscous-prod.mirakl.net/mmp/operator/order/Mf21fe5c2517b-A/message/e5b4c079-e8cd-43fb-8c45-a9747ba2dd33/details. Thanks, Marketplace Support Team
A17: Sent | B17: =Tickets!G21 -> 20 | C17: =Tickets!L21 -> acar1081@rnc.sysco.com | D17: =CONCATENATE("Incident Regarding ", Tickets!M21) -> Incident Regarding na | E17: =CONCATENATE("Hi, ",Tickets!D21," Additional Detail (if Any:) ",Tickets!E21,"."," Thanks, Marketplace Support Team") -> Hi, We have routed your request to the seller. Please feel free to reach out next week if you do not see an update by then. Additional Detail (if Any:) . Thanks, Marketplace Support Team
A18: Sent | B18: =Tickets!G22 -> 21 | C18: =Tickets!L22 -> fmem6919@corp.sysco.com | D18: =CONCATENATE("Incident Regarding ", Tickets!M22) -> Incident Regarding M4c5def9f971d | E18: =CONCATENATE("Hi, ",Tickets!D22," Additional Detail (if Any:) ",Tickets!E22,"."," Thanks, Marketplace Support Team") -> Hi, It appears to have been delivered. The seller has completed the order from their end and wish we could assist further. I would encourage the seller to connect directly with the delivery provider. Additional Detail (if Any:) . Thanks, Marketplace Support Team
A19: Sent | B19: =Tickets!G23 -> 22 | C19: =Tickets!L23 -> smoo5472@wmn.sysco.com | D19: =CONCATENATE("Incident Regarding ", Tickets!M23) -> Incident Regarding 047-933682 Cru Restaurant (enable) | E19: =CONCATENATE("Hi, ",Tickets!D23," Additional Detail (if Any:) ",Tickets!E23,"."," Thanks, Marketplace Support Team") -> Hi, We have enabled these customer account to view and order Marketplace Third Party Products. Please note it will take about 24 hours to take effect. Additional Detail (if Any:) . Thanks, Marketplace Support Team
A20: Sent | B20: =Tickets!G24 -> 23 | C20: =Tickets!L24 -> kgwa2062@balt.sysco.com | D20: =CONCATENATE("Incident Regarding ", Tickets!M24) -> Incident Regarding 012-241715 | E20: =CONCATENATE("Hi, ",Tickets!D24," Additional Detail (if Any:) ",Tickets!E24,"."," Thanks, Marketplace Support Team") -> Hi, Unfortunately this Marketplace sellers does not offer samples at this time. Additional Detail (if Any:) . Thanks, Marketplace Support Team
A21: Sent | B21: =Tickets!G25 -> 24 | C21: =Tickets!L25 -> kelt9557@la.sysco.com | D21: =CONCATENATE("Incident Regarding ", Tickets!M25) -> Incident Regarding MD832AFB41047 | E21: =CONCATENATE("Hi, ",Tickets!D25," Additional Detail (if Any:) ",Tickets!E25,"."," Thanks, Marketplace Support Team") -> Hi, It appears to have been delivered. The seller has completed the order from their end and wish we could assist further. I would encourage the seller to connect directly with the delivery provider. Additional Detail (if Any:) . Thanks, Marketplace Support Team
A22: Sent | B22: =Tickets!G26 -> 25 | C22: =Tickets!L26 -> pgra9460@sd.sysco.com | D22: =CONCATENATE("Incident Regarding ", Tickets!M26) -> Incident Regarding n/a | E22: =CONCATENATE("Hi, ",Tickets!D26," Additional Detail (if Any:) ",Tickets!E26,"."," Thanks, Marketplace Support Team") -> Hi, We have routed your request to the seller. Please feel free to reach out next week if you do not see an update by then. Additional Detail (if Any:) . Thanks, Marketplace Support Team
A23: Sent | B23: =Tickets!G27 -> 26 | C23: =Tickets!L27 -> gner8973@sfl.sysco.com | D23: =CONCATENATE("Incident Regarding ", Tickets!M27) -> Incident Regarding Mc8050f9d386e | E23: =CONCATENATE("Hi, ",Tickets!D27," Additional Detail (if Any:) ",Tickets!E27,"."," Thanks, Marketplace Support Team") -> Hi, Unfortunately, this order has been processed, and the Seller is unable to cancel. Please note, Marketplace Third Party product orders are not eligible for Returns/Refunds or exchanges and is indicated at time of purchase. We wish we could be of more help but given Marketplace's policy, we are unable to assist further on this order. Additional Detail (if Any:) . Thanks, Marketplace Support Team
A24: Sent | B24: =Tickets!G28 -> 27 | C24: =Tickets!L28 -> kkuz3544@sd.sysco.com | D24: =CONCATENATE("Incident Regarding ", Tickets!M28, " and Ticket #",Tickets!G28) -> Incident Regarding 036-744930 - not an order inquiry and Ticket #27 | E24: =CONCATENATE("Hi, ",Tickets!D28," Additional Detail (if Any:) ",Tickets!E28,"."," Thanks, Marketplace Support Team") -> Hi, We have routed your request to the seller. Please feel free to reach out next week if you do not see an update by then. Additional Detail (if Any:) . Thanks, Marketplace Support Team
A25: Sent | B25: =Tickets!G29 -> 28 | C25: =Tickets!L29 -> jgla2956@metrony.sysco.com | D25: =CONCATENATE("Incident Regarding ", Tickets!M29, " and Ticket #",Tickets!G29) -> Incident Regarding M59c6fe193ab, M439221894fd4, M44c96521c56c, Mb59b4691f145, M659c3273e591. This customer is fraud and we need to cancel orders immediately and halt shipping. and Ticket #28 | E25: =CONCATENATE("Hi, ",Tickets!D29," Additional Detail (if Any:) ",Tickets!E29,"."," Thanks, Marketplace Support Team") -> Hi, We have routed your request to the seller. Please feel free to reach out next week if you do not see an update by then. Additional Detail (if Any:) . Thanks, Marketplace Support Team
A26: Sent | B26: =Tickets!#REF! -> #REF! | C26: =Tickets!L30 -> jswe4549@boston.sysco.com | D26: =CONCATENATE("Incident Regarding ", Tickets!M30, " and Ticket #",Tickets!G30) -> Incident Regarding M43dee9a2bcff and Ticket #29 | E26: =CONCATENATE("Hi, ",Tickets!D30," Additional Detail (if Any:) ",Tickets!E30,"."," Thanks, Marketplace Support Team") -> Hi, We apologize for the inconvenience. A support ticket has been opened with the supplier. Please feel free to reach out if you do not see an activity on your account by next week. Additional Detail (if Any:) https://syscous-prod.mirakl.net/mmp/operator/order/M43dee9a2bcff-A/message?sort=date%2CDESC&limit=25. Thanks, Marketplace Support Team
A27: Sent | B27: =Tickets!#REF! -> #REF! | C27: =Tickets!L31 -> pgra9460@sd.sysco.com | D27: =CONCATENATE("Incident Regarding ", Tickets!M31, " and Ticket #",Tickets!G31) -> Incident Regarding Customer 036-501692 (east mesa central #23) | invoice 136A4288M (120cs Kize brownie) and Ticket #30 | E27: =CONCATENATE("Hi, ",Tickets!D31," Additional Detail (if Any:) ",Tickets!E31,"."," Thanks, Marketplace Support Team") -> Hi, It appears that the ticket is incomplete, Please fill it out again and be sure to complete all information required for us to Process. Additional Detail (if Any:) . Thanks, Marketplace Support Team
A28: Sent | B28: =Tickets!#REF! -> #REF! | C28: =Tickets!L32 -> tbru0701@rnc.sysco.com | D28: =CONCATENATE("Incident Regarding ", Tickets!M32, " and Ticket #",Tickets!G32) -> Incident Regarding 137-695638 and Ticket #31 | E28: =CONCATENATE("Hi, ",Tickets!D32," Additional Detail (if Any:) ",Tickets!E32,"."," Thanks, Marketplace Support Team") -> Hi, Additional Detail (if Any:) . Thanks, Marketplace Support Team
A29: Sent | B29: =Tickets!#REF! -> #REF! | C29: =Tickets!L33 -> afeo2641@wcf.sysco.com | D29: =CONCATENATE("Incident Regarding ", Tickets!M33, " and Ticket #",Tickets!G33) -> Incident Regarding . and Ticket #32 | E29: =CONCATENATE("Hi, ",Tickets!D33," Additional Detail (if Any:) ",Tickets!E33,"."," Thanks, Marketplace Support Team") -> Hi, This item is currently out of stock and the seller does not have an ETA on its availability yet. If you do not see this back on after 2 weeks, please feel free to reach out to us. Additional Detail (if Any:) . Thanks, Marketplace Support Team
A30: Sent | B30: =Tickets!#REF! -> #REF! | C30: =Tickets!L34 -> mmor7615@lv.sysco.com | D30: =CONCATENATE("Incident Regarding ", Tickets!M34, " and Ticket #",Tickets!G34) -> Incident Regarding M1e95df72e263 and Ticket #33 | E30: =CONCATENATE("Hi, ",Tickets!D34," Additional Detail (if Any:) ",Tickets!E34,"."," Thanks, Marketplace Support Team") -> Hi, We apologize for the inconvenience. A support ticket has been opened with the supplier. Please feel free to reach out if you do not see an activity on your account by next week. Additional Detail (if Any:) https://syscous-prod.mirakl.net/mmp/operator/order/M1e95df72e263-A/message?sort=date%2CDESC&limit=25. Thanks, Marketplace Support Team
A31: Sent | B31: =Tickets!#REF! -> #REF! | C31: =Tickets!L35 -> emar1379@va.sysco.com | D31: =CONCATENATE("Incident Regarding ", Tickets!M35, " and Ticket #",Tickets!G35) -> Incident Regarding M692433f9aa33 and Ticket #34 | E31: =CONCATENATE("Hi, ",Tickets!D35," Additional Detail (if Any:) ",Tickets!E35,"."," Thanks, Marketplace Support Team") -> Hi, Unfortunately, this order has been processed, and the Seller is unable to cancel. Please note, Marketplace Third Party product orders are not eligible for Returns/Refunds or exchanges and is indicated at time of purchase. We wish we could be of more help but given Marketplace's policy, we are unable to assist further on this order. Additional Detail (if Any:) . Thanks, Marketplace Support Team
A32: Sent | B32: =Tickets!#REF! -> #REF! | C32: =Tickets!L36 -> cmcc9289@int.sysco.com | D32: =CONCATENATE("Incident Regarding ", Tickets!M36, " and Ticket #",Tickets!G36) -> Incident Regarding M1fcbf9ab2aa5 and Ticket #35 | E32: =CONCATENATE("Hi, ",Tickets!D36," Additional Detail (if Any:) ",Tickets!E36,"."," Thanks, Marketplace Support Team") -> Hi, We have routed your request to the seller. Please feel free to reach out next week if you do not see an update by then. Additional Detail (if Any:) It Appears the item was damaged in Transit. We have reached out to the Seller to proceed with a refund. https://www.fedex.com/fedextrack/?trknbr=510032640802&trkqual=12030~510032640802~FDEG. Thanks, Marketplace Support Team
A33: Sent | B33: =Tickets!#REF! -> #REF! | C33: =Tickets!L37 -> sriz5487@shr.sysco.com | D33: =CONCATENATE("Incident Regarding ", Tickets!M37, " and Ticket #",Tickets!G37) -> Incident Regarding #M827c03c17592 and Ticket #36 | E33: =CONCATENATE("Hi, ",Tickets!D37," Additional Detail (if Any:) ",Tickets!E37,"."," Thanks, Marketplace Support Team") -> Hi, It does appear to have inventory. Please ensure the account being used is located in united states and has access to marketplace products. There are times where Suppliers limit the geos they serve which may impact what customers can see and purchase. Additional Detail (if Any:) GTIN 10815812014131 Alternate Product ID 10815812014131 Manufacturer Product Code 815812014134. Thanks, Marketplace Support Team
A34: Sent | B34: =Tickets!#REF! -> #REF! | C34: =Tickets!L38 -> ckne2908@boston.sysco.com | D34: =CONCATENATE("Incident Regarding ", Tickets!M38, " and Ticket #",Tickets!G38) -> Incident Regarding M3f64100d26ca and Ticket #37 | E34: =CONCATENATE("Hi, ",Tickets!D38," Additional Detail (if Any:) ",Tickets!E38,"."," Thanks, Marketplace Support Team") -> Hi, Thank you for sharing. We have reached out to the seller and have created a support ticket. Please feel free to reach out to us next week if you do not see any activity on this order. Additional Detail (if Any:) https://syscous-prod.mirakl.net/mmp/operator/order/M3f64100d26ca-A/message/03d9c98f-56e4-4887-a3a1-31b4724f22ac/details. Thanks, Marketplace Support Team
A35: Sent | B35: =Tickets!#REF! -> #REF! | C35: =Tickets!L39 -> tmey5037@indy.sysco.com | D35: =CONCATENATE("Incident Regarding ", Tickets!M39, " and Ticket #",Tickets!G39) -> Incident Regarding M98fe533adb93 and Ticket #38 | E35: =CONCATENATE("Hi, ",Tickets!D39," Additional Detail (if Any:) ",Tickets!E39,"."," Thanks, Marketplace Support Team") -> Hi, Marketplace has a policy for reporting any incidents to the seller within the first 14 days of delivery. Any incidents such as these should be reported within that timeframe so that we may open a support ticket with the seller. Unfortunately, this falls outside of the allotted time and thus we are unable to assist further. Additional Detail (if Any:) https://tools.usps.com/tracking/9434636106196334818968. Thanks, Marketplace Support Team
A36: Sent | B36: =Tickets!#REF! -> #REF! | C36: =Tickets!L40 -> jswe4549@boston.sysco.com | D36: =CONCATENATE("Incident Regarding ", Tickets!M40, " and Ticket #",Tickets!G40) -> Incident Regarding 156B3431M Date: 5/23/26 and Ticket #39 | E36: =CONCATENATE("Hi, ",Tickets!D40," Additional Detail (if Any:) ",Tickets!E40,"."," Thanks, Marketplace Support Team") -> Hi, Unfortunately, this order has been processed, and the Seller is unable to cancel. Please note, Marketplace Third Party product orders are not eligible for Returns/Refunds or exchanges and is indicated at time of purchase. We wish we could be of more help but given Marketplace's policy, we are unable to assist further on this order. Additional Detail (if Any:) . Thanks, Marketplace Support Team
A37: Sent | B37: =Tickets!#REF! -> #REF! | C37: =Tickets!L41 -> fsta4629@boston.sysco.com | D37: =CONCATENATE("Incident Regarding ", Tickets!M41, " and Ticket #",Tickets!G41) -> Incident Regarding 056174743 Wright in my Kitchen and Ticket #40 | E37: =CONCATENATE("Hi, ",Tickets!D41," Additional Detail (if Any:) ",Tickets!E41,"."," Thanks, Marketplace Support Team") -> Hi, It appears that the ticket is incomplete, Please fill it out again and be sure to complete all information required for us to Process. Additional Detail (if Any:) . Thanks, Marketplace Support Team
... A41: Sent | B41: =Tickets!#REF! -> #REF! | C41: =Tickets!L45 -> bfre2137@chi.sysco.com | D41: =CONCATENATE("Incident Regarding ", Tickets!M45, " and Ticket #",Tickets!G45) -> Incident Regarding M3e2405e7b36a and Ticket #44 | E41: =CONCATENATE("Hi, ",Tickets!D45," Additional Detail (if Any:) ",Tickets!E45,"."," Thanks, Marketplace Support Team") -> Hi, Marketplace orders have a 5-7 Business Day lead time and currently there is not an option to expedite delivery. Additional Detail (if Any:) ups.com/track?tracknum=1Z2XJ4490325109134. Thanks, Marketplace Support Team
A42: Sent | C42: =Tickets!L46 -> shar8486@rs.sysco.com | D42: =CONCATENATE("Incident Regarding ", Tickets!M46, " and Ticket #",Tickets!G46) -> Incident Regarding M61128091b209 and Ticket #45 | E42: =CONCATENATE("Hi, ",Tickets!D46," Additional Detail (if Any:) ",Tickets!E46,"."," Thanks, Marketplace Support Team") -> Hi, Additional Detail (if Any:) It apears that the order was cancelled and could be due to low inteventory or other reasons.. Thanks, Marketplace Support Team
A43: Sent | C43: =Tickets!L47 -> jmat3941@int.sysco.com | D43: =CONCATENATE("Incident Regarding ", Tickets!M47, " and Ticket #",Tickets!G47) -> Incident Regarding M1d393dd1f7d8 and Ticket #46 | E43: =CONCATENATE("Hi, ",Tickets!D47," Additional Detail (if Any:) ",Tickets!E47,"."," Thanks, Marketplace Support Team") -> Hi, Thank you for sharing. We have reached out to the seller and have created a support ticket. Please feel free to reach out to us next week if you do not see any activity on this order. Additional Detail (if Any:) https://syscous-prod.mirakl.net/mmp/operator/order/M1d393dd1f7d8-A/message?sort=date%2CDESC&limit=25. Thanks, Marketplace Support Team
A44: Sent | C44: =Tickets!L48 -> pgra9460@sd.sysco.com | D44: =CONCATENATE("Incident Regarding ", Tickets!M48, " and Ticket #",Tickets!G48) -> Incident Regarding Please provide tracking confirmation for customer 036-501692 for 120cs of SUPC 6071576 - invoice date 5/6/2026 (invoice #136A4288M) and Ticket #47 | E44: =CONCATENATE("Hi, ",Tickets!D48," Additional Detail (if Any:) ",Tickets!E48,"."," Thanks, Marketplace Support Team") -> Hi, Additional Detail (if Any:) https://syscous-prod.mirakl.net/mmp/operator/order/Mee63e533470c-A/message/bbe15d84-7a18-42d9-9c11-f515ad5be06f/details. Thanks, Marketplace Support Team
A45: Sent | C45: =Tickets!L49 -> pgra9460@sd.sysco.com | D45: =CONCATENATE("Incident Regarding ", Tickets!M49, " and Ticket #",Tickets!G49) -> Incident Regarding East Mesa Central #23 (036-501692) DOT Foods order: Mee63e533470c SUPC 6022496 Dove Chocolate (2cs) *order was placed on 6/3/26. Tracking shows that this was delivered to Illinois (customer is in San Diego, Ca), can we please have these cases refunded to the customer? and Ticket #48 | E45: =CONCATENATE("Hi, ",Tickets!D49," Additional Detail (if Any:) ",Tickets!E49,"."," Thanks, Marketplace Support Team") -> Hi, Additional Detail (if Any:) This was signed by K Keller. Please confirm with them and see attachment. Thanks, Marketplace Support Team
A46: Sent | C46: =Tickets!L50 -> jhen6452@ctx.sysco.com | D46: =CONCATENATE("Incident Regarding ", Tickets!M50, " and Ticket #",Tickets!G50) -> Incident Regarding 30157410 and Ticket #49 | E46: =CONCATENATE("Hi, ",Tickets!D50," Additional Detail (if Any:) ",Tickets!E50,"."," Thanks, Marketplace Support Team") -> Hi, Additional Detail (if Any:) This is not a marketplace order. Thanks, Marketplace Support Team
A47: Sent | C47: =Tickets!L51 -> dpid5039@det.sysco.com | D47: =CONCATENATE("Incident Regarding ", Tickets!M51, " and Ticket #",Tickets!G51) -> Incident Regarding M9c685221779d and Ticket #50 | E47: =CONCATENATE("Hi, ",Tickets!D51," Additional Detail (if Any:) ",Tickets!E51,"."," Thanks, Marketplace Support Team") -> Hi, Thank you for sharing. We have reached out to the seller and have created a support ticket. Please feel free to reach out to us next week if you do not see any activity on this order. Additional Detail (if Any:) https://syscous-prod.mirakl.net/mmp/operator/order/M9c685221779d-A/message/542f8f57-a2d8-45e8-89cc-db4d19338fa5/details. Thanks, Marketplace Support Team
A48: New | C48: =Tickets!L52 -> sriz5487@shr.sysco.com | D48: =CONCATENATE("Incident Regarding ", Tickets!M52, " and Ticket #",Tickets!G52) -> Incident Regarding Eggheads Diner 073-482950 and Ticket #51 | E48: =CONCATENATE("Hi, ",Tickets!D52," Additional Detail (if Any:) ",Tickets!E52,"."," Thanks, Marketplace Support Team") -> Hi, We have routed your request to the seller. Please feel free to reach out next week if you do not see an update by then. Additional Detail (if Any:) • BWKHOTBL1020 - Black Lid • BWKDEERHLIDW - White Lid. Thanks, Marketplace Support Team
A49: Sent | C49: =Tickets!L53 -> gtin4580@emd.sysco.com | D49: =CONCATENATE("Incident Regarding ", Tickets!M53, " and Ticket #",Tickets!G53) -> Incident Regarding Mdf7dd4e3a496 and Ticket #52 | E49: =CONCATENATE("Hi, ",Tickets!D53," Additional Detail (if Any:) ",Tickets!E53,"."," Thanks, Marketplace Support Team") -> Hi, Unfortunately, this order has been processed, and the Seller is unable to cancel. Please note, Marketplace Third Party product orders are not eligible for Returns/Refunds or exchanges and is indicated at time of purchase. We wish we could be of more help but given Marketplace's policy, we are unable to assist further on this order. Additional Detail (if Any:) . Thanks, Marketplace Support Team
A50: Sent | C50: =Tickets!L54 -> jman2281@ct.sysco.com | D50: =CONCATENATE("Incident Regarding ", Tickets!M54, " and Ticket #",Tickets!G54) -> Incident Regarding Mbcda4a2cf690 and Ticket #53 | E50: =CONCATENATE("Hi, ",Tickets!D54," Additional Detail (if Any:) ",Tickets!E54,"."," Thanks, Marketplace Support Team") -> Hi, Unfortunately, this order has been processed, and the Seller is unable to cancel. Please note, Marketplace Third Party product orders are not eligible for Returns/Refunds or exchanges and is indicated at time of purchase. We wish we could be of more help but given Marketplace's policy, we are unable to assist further on this order. Additional Detail (if Any:) . Thanks, Marketplace Support Team
A51: New | C51: =Tickets!L55 -> tspe6155@ok.sysco.com | D51: =CONCATENATE("Incident Regarding ", Tickets!M55, " and Ticket #",Tickets!G55) -> Incident Regarding M4e3fd0028940 and Ticket #54 | E51: =CONCATENATE("Hi, ",Tickets!D55," Additional Detail (if Any:) ",Tickets!E55,"."," Thanks, Marketplace Support Team") -> Hi, We apologize for the inconvenience. A support ticket has been opened with the supplier. Please feel free to reach out if you do not see an activity on your account by next week. Additional Detail (if Any:) . Thanks, Marketplace Support Team
A52: New | C52: =Tickets!L56 -> chil3771@emd.sysco.com | D52: =CONCATENATE("Incident Regarding ", Tickets!M56, " and Ticket #",Tickets!G56) -> Incident Regarding N/a and Ticket #55 | E52: =CONCATENATE("Hi, ",Tickets!D56," Additional Detail (if Any:) ",Tickets!E56,"."," Thanks, Marketplace Support Team") -> Hi, Additional Detail (if Any:) . Thanks, Marketplace Support Team
A53: New | C53: =Tickets!L57 -> dcur8328@liny.sysco.com | D53: =CONCATENATE("Incident Regarding ", Tickets!M57, " and Ticket #",Tickets!G57) -> Incident Regarding M22f200b31969 and Ticket #56 | E53: =CONCATENATE("Hi, ",Tickets!D57," Additional Detail (if Any:) ",Tickets!E57,"."," Thanks, Marketplace Support Team") -> Hi, Marketplace orders have a 5-7 Business Day lead time and currently there is not an option to expedite delivery. Additional Detail (if Any:) fedex.com/wtrk/track/?trknbr=874004079106. Thanks, Marketplace Support Team
A54: =Tickets!C58 | C54: =Tickets!L58 -> awal4199@min.sysco.com | D54: =CONCATENATE("Incident Regarding ", Tickets!M58, " and Ticket #",Tickets!G58) -> Incident Regarding Mce6fb214e212 and Ticket #57 | E54: =CONCATENATE("Hi, ",Tickets!D58," Additional Detail (if Any:) ",Tickets!E58,"."," Thanks, Marketplace Support Team") -> Hi, Yes, they appear online and should be available through Sysco Shop. Additional Detail (if Any:) . Thanks, Marketplace Support Team
A55: =Tickets!C59 -> New | C55: =Tickets!L59 -> cbel9800@centralpa.sysco.com | D55: =CONCATENATE("Incident Regarding ", Tickets!M59, " and Ticket #",Tickets!G59) -> Incident Regarding 14399146 and Ticket #58 | E55: =CONCATENATE("Hi, ",Tickets!D59," Additional Detail (if Any:) ",Tickets!E59,"."," Thanks, Marketplace Support Team") -> Hi, Additional Detail (if Any:) . Thanks, Marketplace Support Team
A56: =Tickets!C60 -> Sent | C56: =Tickets!L60 -> rhai2211@sysco.com | D56: =CONCATENATE("Incident Regarding ", Tickets!M60, " and Ticket #",Tickets!G60) -> Incident Regarding M156cc6eb133e and Ticket #59 | E56: =CONCATENATE("Hi, ",Tickets!D60," Additional Detail (if Any:) ",Tickets!E60,"."," Thanks, Marketplace Support Team") -> Hi, We apologize for the inconvenience. A support ticket has been opened with the supplier. Please feel free to reach out if you do not see an activity on your account by next week. Additional Detail (if Any:) . Thanks, Marketplace Support Team
A57: =Tickets!C61 -> Sent | C57: =Tickets!L61 -> rdim2857@sfo.sysco.com | D57: =CONCATENATE("Incident Regarding ", Tickets!M61, " and Ticket #",Tickets!G61) -> Incident Regarding #M94a2d701f6e6 and Ticket #60 | E57: =CONCATENATE("Hi, ",Tickets!D61," Additional Detail (if Any:) ",Tickets!E61,"."," Thanks, Marketplace Support Team") -> Hi, Unfortunately, this order has been processed, and the Seller is unable to cancel. Please note, Marketplace Third Party product orders are not eligible for Returns/Refunds or exchanges and is indicated at time of purchase. We wish we could be of more help but given Marketplace's policy, we are unable to assist further on this order. Additional Detail (if Any:) . Thanks, Marketplace Support Team
A58: =Tickets!C62 -> Sent | C58: =Tickets!L62 -> bami2547@sysco.com | D58: =CONCATENATE("Incident Regarding ", Tickets!M62, " and Ticket #",Tickets!G62) -> Incident Regarding Mf1ffad98a494-A and Ticket #61 | E58: =CONCATENATE("Hi, ",Tickets!D62," Additional Detail (if Any:) ",Tickets!E62,"."," Thanks, Marketplace Support Team") -> Hi, We apologize for the inconvenience. A support ticket has been opened with the supplier. Please feel free to reach out if you do not see an activity on your account by next week. Additional Detail (if Any:) . Thanks, Marketplace Support Team
A59: =Tickets!C63 -> New | C59: =Tickets!L63 -> jgla2956@metrony.sysco.com | D59: =CONCATENATE("Incident Regarding ", Tickets!M63, " and Ticket #",Tickets!G63) -> Incident Regarding NA and Ticket #62 | E59: =CONCATENATE("Hi, ",Tickets!D63," Additional Detail (if Any:) ",Tickets!E63,"."," Thanks, Marketplace Support Team") -> Hi, Additional Detail (if Any:) . Thanks, Marketplace Support Team
A60: =Tickets!C64 -> New | C60: =Tickets!L64 -> jgla2956@metrony.sysco.com | D60: =CONCATENATE("Incident Regarding ", Tickets!M64, " and Ticket #",Tickets!G64) -> Incident Regarding 036333 and Ticket #63 | E60: =CONCATENATE("Hi, ",Tickets!D64," Additional Detail (if Any:) ",Tickets!E64,"."," Thanks, Marketplace Support Team") -> Hi, Additional Detail (if Any:) . Thanks, Marketplace Support Team
A61: =Tickets!C65 -> Sent | C61: =Tickets!L65 -> khau4953@sfo.sysco.com | D61: =CONCATENATE("Incident Regarding ", Tickets!M65, " and Ticket #",Tickets!G65) -> Incident Regarding cid#s attached on form to enable. NAID: ATGR site: 031 and Ticket #64 | E61: =CONCATENATE("Hi, ",Tickets!D65," Additional Detail (if Any:) ",Tickets!E65,"."," Thanks, Marketplace Support Team") -> Hi, Additional Detail (if Any:) . Thanks, Marketplace Support Team
A62: =Tickets!C66 -> Sent | C62: =Tickets!L66 -> pnun9955@cfl.sysco.com | D62: =CONCATENATE("Incident Regarding ", Tickets!M66, " and Ticket #",Tickets!G66) -> Incident Regarding SODIE DOCES and Ticket #65 | E62: =CONCATENATE("Hi, ",Tickets!D66," Additional Detail (if Any:) ",Tickets!E66,"."," Thanks, Marketplace Support Team") -> Hi, We have routed your request to the seller for product availability. Please feel free to reach out next week if you do not see an update by then. Additional Detail (if Any:) . Thanks, Marketplace Support Team
A63: =Tickets!C67 -> Sent | C63: =Tickets!L67 -> wcla4950@grr.sysco.com | D63: =CONCATENATE("Incident Regarding ", Tickets!M67, " and Ticket #",Tickets!G67) -> Incident Regarding M4a66a5bfc55e and Ticket #66 | E63: =CONCATENATE("Hi, ",Tickets!D67," Additional Detail (if Any:) ",Tickets!E67,"."," Thanks, Marketplace Support Team") -> Hi, It appears to have been delivered. The seller has completed the order from their end and wish we could assist further. I would encourage the seller to connect directly with the delivery provider. Additional Detail (if Any:) . Thanks, Marketplace Support Team
A64: =Tickets!C68 -> Sent | B64: sent | C64: =Tickets!L68 -> hher4631@sysco.com | D64: =CONCATENATE("Incident Regarding ", Tickets!M68, " and Ticket #",Tickets!G68) -> Incident Regarding Ma07af18d4038 and Ticket #67 | E64: =CONCATENATE("Hi, ",Tickets!D68," Additional Detail (if Any:) ",Tickets!E68,"."," Thanks, Marketplace Support Team") -> Hi, Additional Detail (if Any:) https://syscous-prod.mirakl.net/mmp/operator/order/Ma07af18d4038-A/message?sort=date%2CDESC&limit=25. Thanks, Marketplace Support Team
A65: =Tickets!C69 -> Sent | C65: =Tickets!L69 -> pgra9460@sd.sysco.com | D65: =CONCATENATE("Incident Regarding ", Tickets!M69, " and Ticket #",Tickets!G69) -> Incident Regarding Customer 036-501692 | Invoice date 5/6/26 - SUPC 6071576 for 120cs Kize bar brownie batter and Ticket #68 | E65: =CONCATENATE("Hi, ",Tickets!D69," Additional Detail (if Any:) ",Tickets!E69,"."," Thanks, Marketplace Support Team") -> Hi, It appears to have been delivered. The seller has completed the order from their end and wish we could assist further. I would encourage the seller to connect directly with the delivery provider. Additional Detail (if Any:) . Thanks, Marketplace Support Team
A66: =Tickets!C70 -> New | C66: =Tickets!L70 -> jmad6864@iowa.sysco.com | D66: =CONCATENATE("Incident Regarding ", Tickets!M70, " and Ticket #",Tickets!G70) -> Incident Regarding Lagomacinos Confectionary ML 039-563190, need to order 1 case of item TR-SCL140PET by Karat and Ticket #69 | E66: =CONCATENATE("Hi, ",Tickets!D70," Additional Detail (if Any:) ",Tickets!E70,"."," Thanks, Marketplace Support Team") -> Hi, Additional Detail (if Any:) . Thanks, Marketplace Support Team
A67: =Tickets!C71 -> Sent | C67: =Tickets!L71 -> jvel5786@shr.sysco.com | D67: =CONCATENATE("Incident Regarding ", Tickets!M71, " and Ticket #",Tickets!G71) -> Incident Regarding Mb3371c027ebf and Ticket #70 | E67: =CONCATENATE("Hi, ",Tickets!D71," Additional Detail (if Any:) ",Tickets!E71,"."," Thanks, Marketplace Support Team") -> Hi, We have routed your request to the seller. Please feel free to reach out next week if you do not see an update by then. Additional Detail (if Any:) . Thanks, Marketplace Support Team
A68: =Tickets!C72 -> Sent | C68: =Tickets!L72 -> twhi6823@cle.sysco.com | D68: =CONCATENATE("Incident Regarding ", Tickets!M72, " and Ticket #",Tickets!G72) -> Incident Regarding Mecbced6fde2e and Md824ded63f61 and Ticket #71 | E68: =CONCATENATE("Hi, ",Tickets!D72," Additional Detail (if Any:) ",Tickets!E72,"."," Thanks, Marketplace Support Team") -> Hi, Unfortunately, this order has been processed, and the Seller is unable to cancel. Please note, Marketplace Third Party product orders are not eligible for Returns/Refunds or exchanges and is indicated at time of purchase. We wish we could be of more help but given Marketplace's policy, we are unable to assist further on this order. Additional Detail (if Any:) . Thanks, Marketplace Support Team
A69: =Tickets!C73 -> Sent | B69: sent | C69: =Tickets!L73 -> dfet2145@cha.sysco.com | D69: =CONCATENATE("Incident Regarding ", Tickets!M73, " and Ticket #",Tickets!G73) -> Incident Regarding M7ee8f246a7f0 and Ticket #72 | E69: =CONCATENATE("Hi, ",Tickets!D73," Additional Detail (if Any:) ",Tickets!E73,"."," Thanks, Marketplace Support Team") -> Hi, Additional Detail (if Any:) the email address that placed the order was erinchef@yahoo.com. Please Note that only autorized user can make purchases and there is no automation in the system thus someone from this account did place the order. Thanks, Marketplace Support Team
A70: =Tickets!C74 -> Sent | C70: =Tickets!L74 -> dlen6100@sfo.sysco.com | D70: =CONCATENATE("Incident Regarding ", Tickets!M74, " and Ticket #",Tickets!G74) -> Incident Regarding Mb1dcdbb9c0d3 and Ticket #73 | E70: =CONCATENATE("Hi, ",Tickets!D74," Additional Detail (if Any:) ",Tickets!E74,"."," Thanks, Marketplace Support Team") -> Hi, Unfortunately, this order has been processed, and the Seller is unable to cancel. Please note, Marketplace Third Party product orders are not eligible for Returns/Refunds or exchanges and is indicated at time of purchase. We wish we could be of more help but given Marketplace's policy, we are unable to assist further on this order. Additional Detail (if Any:) . Thanks, Marketplace Support Team
A71: =Tickets!C75 -> New | C71: =Tickets!L75 -> klav2850@wtx.sysco.com | D71: =CONCATENATE("Incident Regarding ", Tickets!M75, " and Ticket #",Tickets!G75) -> Incident Regarding Mcccb9ad25f83 and Ticket #74 | E71: =CONCATENATE("Hi, ",Tickets!D75," Additional Detail (if Any:) ",Tickets!E75,"."," Thanks, Marketplace Support Team") -> Hi, Additional Detail (if Any:) this order has been cancelled. Thanks, Marketplace Support Team
A72: =Tickets!C76 -> Close | C72: =Tickets!L76 -> fbel8389@philly.sysco.com | D72: =CONCATENATE("Incident Regarding ", Tickets!M76, " and Ticket #",Tickets!G76) -> Incident Regarding there is no order # since code disapeared and Ticket #75 | E72: =CONCATENATE("Hi, ",Tickets!D76," Additional Detail (if Any:) ",Tickets!E76,"."," Thanks, Marketplace Support Team") -> Hi, This item is currently out of stock and the seller does not have an ETA on its availability yet. If you do not see this back on after 2 weeks, please feel free to reach out to us. Additional Detail (if Any:) . Thanks, Marketplace Support Team
A73: =Tickets!C77 -> Sent | C73: =Tickets!L77 -> ayep4668@centralca.sysco.com | D73: =CONCATENATE("Incident Regarding ", Tickets!M77, " and Ticket #",Tickets!G77) -> Incident Regarding 004-693703;052897698;052897363 and Ticket #76 | E73: =CONCATENATE("Hi, ",Tickets!D77," Additional Detail (if Any:) ",Tickets!E77,"."," Thanks, Marketplace Support Team") -> Hi, Additional Detail (if Any:) . Thanks, Marketplace Support Team
A74: =Tickets!C78 -> Close | C74: =Tickets!L78 -> acow7570@wtx.sysco.com | D74: =CONCATENATE("Incident Regarding ", Tickets!M78, " and Ticket #",Tickets!G78) -> Incident Regarding there is no order number in shop or on the invoice delivered 7/1 per invoice ordered 6/30 all other details in below message and Ticket #77 | E74: =CONCATENATE("Hi, ",Tickets!D78," Additional Detail (if Any:) ",Tickets!E78,"."," Thanks, Marketplace Support Team") -> Hi, We have routed your request to the seller for product availability. Please feel free to reach out next week if you do not see an update by then. Additional Detail (if Any:) . Thanks, Marketplace Support Team
A75: =Tickets!C79 -> Sent | C75: =Tickets!L79 -> ehar9736@balt.sysco.com | D75: =CONCATENATE("Incident Regarding ", Tickets!M79, " and Ticket #",Tickets!G79) -> Incident Regarding Me979a1ffb3e4 and Ticket #78 | E75: =CONCATENATE("Hi, ",Tickets!D79," Additional Detail (if Any:) ",Tickets!E79,"."," Thanks, Marketplace Support Team") -> Hi, We apologize for the inconvenience. A support ticket has been opened with the supplier. Please feel free to reach out if you do not see an activity on your account by next week. Additional Detail (if Any:) . Thanks, Marketplace Support Team
A76: =Tickets!C80 -> Sent | C76: =Tickets!L80 -> jgla2956@metrony.sysco.com | D76: =CONCATENATE("Incident Regarding ", Tickets!M80, " and Ticket #",Tickets!G80) -> Incident Regarding M23ac7388318d and Ticket #79 | E76: =CONCATENATE("Hi, ",Tickets!D80," Additional Detail (if Any:) ",Tickets!E80,"."," Thanks, Marketplace Support Team") -> Hi, We apologize for the inconvenience. A support ticket has been opened with the supplier. Please feel free to reach out if you do not see an activity on your account by next week. Additional Detail (if Any:) . Thanks, Marketplace Support Team
A77: =Tickets!C81 -> New | C77: =Tickets!L81 -> khau4953@sfo.sysco.com | D77: =CONCATENATE("Incident Regarding ", Tickets!M81, " and Ticket #",Tickets!G81) -> Incident Regarding Mfaa2e8e4689d, 031-622997 7/11/26 supc 6083021. M4f7fbb6fbfb2 031-6229660 7/11/26 supc 6083021. Both orders show as no ship, but all of these orders placed same day for same customer group appear to have processed: all supc 6083021, 031-622974 Mf54259bf24c3, 031-622928 M2c6e9c1d8c4d. as of 7/13 supc 6083021 doesn't show in SHOP and Ticket #80 | E77: =CONCATENATE("Hi, ",Tickets!D81," Additional Detail (if Any:) ",Tickets!E81,"."," Thanks, Marketplace Support Team") -> Hi, Additional Detail (if Any:) . Thanks, Marketplace Support Team
A78: =Tickets!C82 -> Sent | C78: =Tickets!L82 -> jale3447@knox.sysco.com | D78: =CONCATENATE("Incident Regarding ", Tickets!M82, " and Ticket #",Tickets!G82) -> Incident Regarding M7b6eae5d5a13 and Ticket #81 | E78: =CONCATENATE("Hi, ",Tickets!D82," Additional Detail (if Any:) ",Tickets!E82,"."," Thanks, Marketplace Support Team") -> Hi, We apologize for the inconvenience. A support ticket has been opened with the supplier. Please feel free to reach out if you do not see an activity on your account by next week. Additional Detail (if Any:) . Thanks, Marketplace Support Team
A79: =Tickets!C83 -> Close | C79: =Tickets!L83 -> bnet8174@shr.sysco.com | D79: =CONCATENATE("Incident Regarding ", Tickets!M83, " and Ticket #",Tickets!G83) -> Incident Regarding 620504, Item code 6064310 Spoon soup karat 1,000ct med-heavy weight asian soup spoon, black and Ticket #82 | E79: =CONCATENATE("Hi, ",Tickets!D83," Additional Detail (if Any:) ",Tickets!E83,"."," Thanks, Marketplace Support Team") -> Hi, Additional Detail (if Any:) . Thanks, Marketplace Support Team
A80: =Tickets!C84 -> Sent | C80: =Tickets!L84 -> ddes4323@hou.sysco.com | D80: =CONCATENATE("Incident Regarding ", Tickets!M84, " and Ticket #",Tickets!G84) -> Incident Regarding see file attached and Ticket #83 | E80: =CONCATENATE("Hi, ",Tickets!D84," Additional Detail (if Any:) ",Tickets!E84,"."," Thanks, Marketplace Support Team") -> Hi, Additional Detail (if Any:) . Thanks, Marketplace Support Team
A81: =Tickets!C85 -> Sent | C81: =Tickets!L85 -> sdem2154@emd.sysco.com | D81: =CONCATENATE("Incident Regarding ", Tickets!M85, " and Ticket #",Tickets!G85) -> Incident Regarding Me50b6e6a1903 and Ticket #84 | E81: =CONCATENATE("Hi, ",Tickets!D85," Additional Detail (if Any:) ",Tickets!E85,"."," Thanks, Marketplace Support Team") -> Hi, Marketplace orders have a 5-7 Business Day lead time and currently there is not an option to expedite delivery. Additional Detail (if Any:) . Thanks, Marketplace Support Team
A82: =Tickets!C86 -> New | C82: =Tickets!L86 -> kric8807@indy.sysco.com | D82: =CONCATENATE("Incident Regarding ", Tickets!M86, " and Ticket #",Tickets!G86) -> Incident Regarding M91ae7e3de31b and Ticket #85 | E82: =CONCATENATE("Hi, ",Tickets!D86," Additional Detail (if Any:) ",Tickets!E86,"."," Thanks, Marketplace Support Team") -> Hi, Unfortunately, this order has been processed, and the Seller is unable to cancel. Please note, Marketplace Third Party product orders are not eligible for Returns/Refunds or exchanges and is indicated at time of purchase. We wish we could be of more help but given Marketplace's policy, we are unable to assist further on this order. Additional Detail (if Any:) . Thanks, Marketplace Support Team
A83: =Tickets!C87 -> Sent | B83: sent | C83: =Tickets!L87 -> tlew3091@sysco.com | D83: =CONCATENATE("Incident Regarding ", Tickets!M87, " and Ticket #",Tickets!G87) -> Incident Regarding Mb9b0e14c9650 and Ticket #86 | E83: =CONCATENATE("Hi, ",Tickets!D87," Additional Detail (if Any:) ",Tickets!E87,"."," Thanks, Marketplace Support Team") -> Hi, We apologize for the inconvenience. A support ticket has been opened with the supplier. Please feel free to reach out if you do not see an activity on your account by next week. Additional Detail (if Any:) https://syscous-prod.mirakl.net/mmp/operator/order/Mb9b0e14c9650-A/message?sort=date%2CDESC&limit=25. Thanks, Marketplace Support Team
A84: =Tickets!C88 -> Sent | C84: =Tickets!L88 -> dlon7838@sysco.com | D84: =CONCATENATE("Incident Regarding ", Tickets!M88, " and Ticket #",Tickets!G88) -> Incident Regarding MILWAUKEE GRILL SUPPLIES (018-180349) and Ticket #87 | E84: =CONCATENATE("Hi, ",Tickets!D88," Additional Detail (if Any:) ",Tickets!E88,"."," Thanks, Marketplace Support Team") -> Hi, Additional Detail (if Any:) . Thanks, Marketplace Support Team
A85: =Tickets!C89 -> Closed | C85: =Tickets!L89 -> evan5497@lincoln.sysco.com | D85: =CONCATENATE("Incident Regarding ", Tickets!M89, " and Ticket #",Tickets!G89) -> Incident Regarding there is not an order number. I need an update on availability and Ticket #88 | E85: =CONCATENATE("Hi, ",Tickets!D89," Additional Detail (if Any:) ",Tickets!E89,"."," Thanks, Marketplace Support Team") -> Hi, This item is currently out of stock and the seller does not have an ETA on its availability yet. If you do not see this back on after 2 weeks, please feel free to reach out to us. Additional Detail (if Any:) . Thanks, Marketplace Support Team
A86: =Tickets!C90 -> Sent | C86: =Tickets!L90 -> whon8322@wtx.sysco.com | D86: =CONCATENATE("Incident Regarding ", Tickets!M90, " and Ticket #",Tickets!G90) -> Incident Regarding Trying to find a large party. 3 compartment black bottom, clear top 14x14 tray. and Ticket #89 | E86: =CONCATENATE("Hi, ",Tickets!D90," Additional Detail (if Any:) ",Tickets!E90,"."," Thanks, Marketplace Support Team") -> Hi, Additional Detail (if Any:) . Thanks, Marketplace Support Team
A87: =Tickets!C91 -> Close | C87: =Tickets!L91 -> jhar0408@nd.sysco.com | D87: =CONCATENATE("Incident Regarding ", Tickets!M91, " and Ticket #",Tickets!G91) -> Incident Regarding #M3f60aac7d654 and Ticket #90 | E87: =CONCATENATE("Hi, ",Tickets!D91," Additional Detail (if Any:) ",Tickets!E91,"."," Thanks, Marketplace Support Team") -> Hi, This item is currently out of stock and the seller does not have an ETA on its availability yet. If you do not see this back on after 2 weeks, please feel free to reach out to us. Additional Detail (if Any:) . Thanks, Marketplace Support Team
A88: =Tickets!C92 -> Sent | B88: sent | C88: =Tickets!L92 -> jjac0949@nola.sysco.com | D88: =CONCATENATE("Incident Regarding ", Tickets!M92, " and Ticket #",Tickets!G92) -> Incident Regarding M562014ba0d18 and Ticket #91 | E88: =CONCATENATE("Hi, ",Tickets!D92," Additional Detail (if Any:) ",Tickets!E92,"."," Thanks, Marketplace Support Team") -> Hi, Additional Detail (if Any:) This is now complete and refunded. Thanks, Marketplace Support Team
A89: =Tickets!C93 -> Sent | C89: =Tickets!L93 -> hped1119@sd.sysco.com | D89: =CONCATENATE("Incident Regarding ", Tickets!M93, " and Ticket #",Tickets!G93) -> Incident Regarding 036-733159 and Ticket #92 | E89: =CONCATENATE("Hi, ",Tickets!D93," Additional Detail (if Any:) ",Tickets!E93,"."," Thanks, Marketplace Support Team") -> Hi, This item is currently out of stock and the seller does not have an ETA on its availability yet. If you do not see this back on after 2 weeks, please feel free to reach out to us. Additional Detail (if Any:) . Thanks, Marketplace Support Team
A90: =Tickets!C94 -> Sent | C90: =Tickets!L94 -> ktoy2427@sfo.sysco.com | D90: =CONCATENATE("Incident Regarding ", Tickets!M94, " and Ticket #",Tickets!G94) -> Incident Regarding 050-975482 Little Chihuahua Noe Vally 3, 050-156135 Little Chihuahua Polk St and Ticket #93 | E90: =CONCATENATE("Hi, ",Tickets!D94," Additional Detail (if Any:) ",Tickets!E94,"."," Thanks, Marketplace Support Team") -> Hi, We have enabled these customer account to view and order Marketplace Third Party Products. Please note it will take about 24 hours to take effect. Additional Detail (if Any:) . Thanks, Marketplace Support Team
A91: =Tickets!C95 -> New | C91: =Tickets!L95 -> kada2513@ctx.sysco.com | D91: =CONCATENATE("Incident Regarding ", Tickets!M95, " and Ticket #",Tickets!G95) -> Incident Regarding 14401514 customer 415059 date: 7/10/26 is it this?? and Ticket #94 | E91: =CONCATENATE("Hi, ",Tickets!D95," Additional Detail (if Any:) ",Tickets!E95,"."," Thanks, Marketplace Support Team") -> Hi, Additional Detail (if Any:) . Thanks, Marketplace Support Team
A92: =Tickets!C96 -> Sent | C92: =Tickets!L96 -> klav2850@wtx.sysco.com | D92: =CONCATENATE("Incident Regarding ", Tickets!M96, " and Ticket #",Tickets!G96) -> Incident Regarding Mfe9f857d1344 and Ticket #95 | E92: =CONCATENATE("Hi, ",Tickets!D96," Additional Detail (if Any:) ",Tickets!E96,"."," Thanks, Marketplace Support Team") -> Hi, This item is currently out of stock and the seller does not have an ETA on its availability yet. If you do not see this back on after 2 weeks, please feel free to reach out to us. Additional Detail (if Any:) . Thanks, Marketplace Support Team
A93: =Tickets!C97 -> Sent | C93: =Tickets!L97 -> lstc4806@cil.sysco.com | D93: =CONCATENATE("Incident Regarding ", Tickets!M97, " and Ticket #",Tickets!G97) -> Incident Regarding M30acc27037ac and Ticket #96 | E93: =CONCATENATE("Hi, ",Tickets!D97," Additional Detail (if Any:) ",Tickets!E97,"."," Thanks, Marketplace Support Team") -> Hi, We have routed your request to the seller. Please feel free to reach out next week if you do not see an update by then. Additional Detail (if Any:) . Thanks, Marketplace Support Team
A94: =Tickets!C98 -> Sent | C94: =Tickets!L98 -> aleb5719@int.sysco.com | D94: =CONCATENATE("Incident Regarding ", Tickets!M98, " and Ticket #",Tickets!G98) -> Incident Regarding Med7c9ec650f5 and Ticket #97 | E94: =CONCATENATE("Hi, ",Tickets!D98," Additional Detail (if Any:) ",Tickets!E98,"."," Thanks, Marketplace Support Team") -> Hi, Unfortunately, this order has been processed, and the Seller is unable to cancel. Please note, Marketplace Third Party product orders are not eligible for Returns/Refunds or exchanges and is indicated at time of purchase. We wish we could be of more help but given Marketplace's policy, we are unable to assist further on this order. Additional Detail (if Any:) . Thanks, Marketplace Support Team
A95: =Tickets!C99 -> Sent | C95: =Tickets!L99 -> jgla2956@metrony.sysco.com | D95: =CONCATENATE("Incident Regarding ", Tickets!M99, " and Ticket #",Tickets!G99) -> Incident Regarding M844a1754b8ca and Ticket #98 | E95: =CONCATENATE("Hi, ",Tickets!D99," Additional Detail (if Any:) ",Tickets!E99,"."," Thanks, Marketplace Support Team") -> Hi, Unfortunately, this order has been processed, and the Seller is unable to cancel. Please note, Marketplace Third Party product orders are not eligible for Returns/Refunds or exchanges and is indicated at time of purchase. We wish we could be of more help but given Marketplace's policy, we are unable to assist further on this order. Additional Detail (if Any:) . Thanks, Marketplace Support Team
A96: =Tickets!C100 -> Sent | C96: =Tickets!L100 -> kgor4562@sysco.com | D96: =CONCATENATE("Incident Regarding ", Tickets!M100, " and Ticket #",Tickets!G100) -> Incident Regarding M55e408c1b73d and Ticket #99 | E96: =CONCATENATE("Hi, ",Tickets!D100," Additional Detail (if Any:) ",Tickets!E100,"."," Thanks, Marketplace Support Team") -> Hi, Unfortunately, this order has been processed, and the Seller is unable to cancel. Please note, Marketplace Third Party product orders are not eligible for Returns/Refunds or exchanges and is indicated at time of purchase. We wish we could be of more help but given Marketplace's policy, we are unable to assist further on this order. Additional Detail (if Any:) . Thanks, Marketplace Support Team
A97: =Tickets!C101 -> Close | C97: =Tickets!L101 -> kgor4562@sysco.com | D97: =CONCATENATE("Incident Regarding ", Tickets!M101, " and Ticket #",Tickets!G101) -> Incident Regarding NA and Ticket #100 | E97: =CONCATENATE("Hi, ",Tickets!D101," Additional Detail (if Any:) ",Tickets!E101,"."," Thanks, Marketplace Support Team") -> Hi, Additional Detail (if Any:) . Thanks, Marketplace Support Team
A98: =Tickets!C102 -> Close | C98: =Tickets!L102 -> bfli9049@sfl.sysco.com | D98: =CONCATENATE("Incident Regarding ", Tickets!M102, " and Ticket #",Tickets!G102) -> Incident Regarding n/a and Ticket #101 | E98: =CONCATENATE("Hi, ",Tickets!D102," Additional Detail (if Any:) ",Tickets!E102,"."," Thanks, Marketplace Support Team") -> Hi, Additional Detail (if Any:) . Thanks, Marketplace Support Team
A99: =Tickets!C103 -> Sent | B99: sent | C99: =Tickets!L103 -> kgor4562@sysco.com | D99: =CONCATENATE("Incident Regarding ", Tickets!M103, " and Ticket #",Tickets!G103) -> Incident Regarding Mc6de48dfe69f and Ticket #102 | E99: =CONCATENATE("Hi, ",Tickets!D103," Additional Detail (if Any:) ",Tickets!E103,"."," Thanks, Marketplace Support Team") -> Hi, We have routed your request to the seller. Please feel free to reach out next week if you do not see an update by then. Additional Detail (if Any:) . Thanks, Marketplace Support Team
A100: =Tickets!C104 -> Close | C100: =Tickets!L104 -> erib5541@cfl.sysco.com | D100: =CONCATENATE("Incident Regarding ", Tickets!M104, " and Ticket #",Tickets!G104) -> Incident Regarding M79a46b2eecaf and Ticket #103 | E100: =CONCATENATE("Hi, ",Tickets!D104," Additional Detail (if Any:) ",Tickets!E104,"."," Thanks, Marketplace Support Team") -> Hi, Additional Detail (if Any:) refunded. Thanks, Marketplace Support Team
A101: =Tickets!C105 -> New | C101: =Tickets!L105 -> jlan8369@ctx.sysco.com | D101: =CONCATENATE("Incident Regarding ", Tickets!M105, " and Ticket #",Tickets!G105) -> Incident Regarding 113B0498M and Ticket #104 | E101: =CONCATENATE("Hi, ",Tickets!D105," Additional Detail (if Any:) ",Tickets!E105,"."," Thanks, Marketplace Support Team") -> Hi, Additional Detail (if Any:) . Thanks, Marketplace Support Team
A102: =Tickets!C106 -> Sent | C102: =Tickets!L106 -> wcla4950@grr.sysco.com | D102: =CONCATENATE("Incident Regarding ", Tickets!M106, " and Ticket #",Tickets!G106) -> Incident Regarding Me23e1ca06fd9 and Ticket #105 | E102: =CONCATENATE("Hi, ",Tickets!D106," Additional Detail (if Any:) ",Tickets!E106,"."," Thanks, Marketplace Support Team") -> Hi, We apologize for the inconvenience. A support ticket has been opened with the supplier. Please feel free to reach out if you do not see an activity on your account by next week. Additional Detail (if Any:) . Thanks, Marketplace Support Team
A103: =Tickets!C107 -> Sent | C103: =Tickets!L107 -> jbur0912@stl.sysco.com | D103: =CONCATENATE("Incident Regarding ", Tickets!M107, " and Ticket #",Tickets!G107) -> Incident Regarding Mefb47626fac5 and Ticket #106 | E103: =CONCATENATE("Hi, ",Tickets!D107," Additional Detail (if Any:) ",Tickets!E107,"."," Thanks, Marketplace Support Team") -> Hi, We apologize for the inconvenience. A support ticket has been opened with the supplier. Please feel free to reach out if you do not see an activity on your account by next week. Additional Detail (if Any:) . Thanks, Marketplace Support Team
...

Sheet shop_users (1)
A1: Date created | B1: Id | C1: Seller | D1: Status | E1: Premium rules | F1: Premium | G1: Currency | H1: Email | I1: Payment blocked | J1: Pending balance | K1: Payable balance | L1: Paid balance | M1: Total offers | N1: Total consecutive refused orders | O1: Total consecutive auto-refused orders | P1: Domains | Q1: Billing cycle | R1: KYC status | S1: KYC failure reason | T1: Total revenue | U1: Total revenue (last 1 month) | V1: Total revenue (last 3 months) | W1: Total revenue (last 6 months) | X1: Total revenue (last 1 year) | Y1: Average order value incl. shipping charges | Z1: Average order value incl. shipping charges (last 1 month) | AA1: Average order value incl. shipping charges (last 3 months) | AB1: Average order value incl. shipping charges (last 6 months) | AC1: Average order value incl. shipping charges (last 1 year) | AD1: Evaluation | AE1: Evaluation (last 1 month) | AF1: Evaluation (last 3 months) | AG1: Evaluation (last 6 months) | AH1: Evaluation (last 1 year) | AI1: Processed orders | AJ1: Processed orders (last 1 month) | AK1: Processed orders (last 3 months) | AL1: Processed orders (last 6 months) | AM1: Processed orders (last 1 year) | AN1: Acceptance rate | AO1: Acceptance rate (last 1 month) | AP1: Acceptance rate (last 3 months) | AQ1: Acceptance rate (last 6 months) | AR1: Acceptance rate (last 1 year) | AS1: Incident rate | AT1: Incident rate (last 1 month) | AU1: Incident rate (last 3 months) | AV1: Incident rate (last 6 months) | AW1: Incident rate (last 1 year) | AX1: Refund rate | AY1: Refund rate (last 1 month) | AZ1: Refund rate (last 3 months) | BA1: Refund rate (last 6 months) | BB1: Refund rate (last 1 year) | BC1: Auto-refused rate | BD1: Auto-refused rate (last 1 month) | BE1: Auto-refused rate (last 3 months) | BF1: Auto-refused rate (last 6 months) | BG1: Auto-refused rate (last 1 year) | BH1: Late shipment rate | BI1: Late shipment rate (last 1 month) | BJ1: Late shipment rate (last 3 months) | BK1: Late shipment rate (last 6 months) | BL1: Late shipment rate (last 1 year) | BM1: Acceptance time | BN1: Acceptance time (last 1 month) | BO1: Acceptance time (last 3 months) | BP1: Acceptance time (last 6 months) | BQ1: Acceptance time (last 1 year) | BR1: Time to ship | BS1: Time to ship (last 1 month) | BT1: Time to ship (last 3 months) | BU1: Time to ship (last 6 months) | BV1: Time to ship (last 1 year) | BW1: Response time to order-related messages | BX1: Response time to order-related messages (last 1 month) | BY1: Response time to order-related messages (last 3 months) | BZ1: Response time to order-related messages (last 6 months) | CA1: Response time to order-related messages (last 1 year) | CB1: Total orders | CC1: Total orders (last 1 month) | CD1: Total orders (last 3 months) | CE1: Total orders (last 6 months) | CF1: Total orders (last 1 year) | CG1: Suspension date | CH1: Suspension type | CI1: Suspension reason | CJ1: Low quality since | CK1: Low quality | CL1: Operator internal ID | CM1: Immunity granted until | CN1: Closed from | CO1: Closed until | CP1: Shipping country | CQ1: Professional | CR1: Company name | CS1: Company registration number | CT1: VAT number | CU1: Civility | CV1: First name | CW1: Last name | CX1: Phone | CY1: Secondary phone | CZ1: Fax | DA1: Address | DB1: Address (continued) | DC1: Zip code | DD1: City | DE1: State | DF1: Country | DG1: Website | DH1: Invoiced subscription | DI1: Subscription type | DJ1: Monthly fee | DK1: Invoiced only if orders exist | DL1: Free months | DM1: Free from | DN1: Free until | DO1: Commission grid | DP1: Payment terms | DQ1: Refund limit | DR1: Tier | DS1: Tracking rate | DT1: Tracking rate (last 1 month) | DU1: Tracking rate (last 3 months) | DV1: Tracking rate (last 6 months) | DW1: Tracking rate (last year) | DX1: Cancelation rate | DY1: Cancelation rate (last 1 month) | DZ1: Cancelation rate (last 3 months) | EA1: Cancelation rate (last 6 months) | EB1: Cancelation rate (last year) | EC1: Account manager | ED1: Electronic address | EE1: Phone number | EF1: Diverse Supplier | EG1: Diverse Classification | EH1: Certification | EI1: Vendor Attributes | EJ1: Federal Status | EK1: Small Business | EL1: HHA Signed and Completed? | EM1: HHA Expiration Date | EN1: General Liability Expiration Date | EO1: Excess Liability Expiration Date | EP1: Auto Liability Expiration Date | EQ1: Worker's Compensation and Employer's Liability Expiration Date | ER1: COI General Liability Amount | ES1: Date of Incorporation | ET1: ID Type | EU1: Tax Number (EIN/GST/HST) | EV1: Doing Business As | EW1: Are you a Redistributor? | EX1: Do you use SPS Commerce or True Commerce EDI Software Partners? | EY1: What is EDI being used for specifically? | EZ1: SUVC (Vendor Number) | FA1: Mirakl Invoicing Seller Type | FB1: connect-onboarded-seller | FC1: Ship From Name | FD1: Ship From Street | FE1: Suite, Floor, Building | FF1: Street 3 | FG1: Street 4 | FH1: Street 5 | FI1: City_1 | FJ1: Country_2 | FK1: Region/State | FL1: Postal Code | FM1: Daily Cut-off Time (Central Time) | FN1: Daily Pickup Needed | FO1: Delivery Time During Day | FP1: Preferred Shipping Carrier
A2: 45243.481 | B2: 2000 | C2: Natural Commerce | D2: Open | E2: 2000 | F2: no | G2: USD | H2: chandler@naturalcommerce.com | I2: no | J2: 115824.32 | K2: 1063.89 | L2: 5710252.2 | M2: 7543 | N2: 0 | O2: 0 | P2: Products | Q2: Every 21st of the month | R2: KYC passed | T2: 6855085 | U2: 291181.23 | V2: 864404.78 | W2: 1652026 | X2: 3236166.3 | Y2: 95.06 | Z2: 106.43 | AA2: 105.85 | AB2: 104.3 | AC2: 99.17 | AI2: 72503 | AJ2: 2740 | AK2: 8190 | AL2: 15916 | AM2: 32835 | AN2: 99.97 | AO2: 100 | AP2: 100 | AQ2: 100 | AR2: 99.99 | AS2: 0.26 | AT2: 0.19 | AU2: 0.26 | AV2: 0.25 | AW2: 0.25 | AX2: 0.24 | AY2: 0.16 | AZ2: 0.18 | BA2: 0.23 | BB2: 0.25 | BC2: 0.02 | BD2: 0 | BE2: 0 | BF2: 0 | BG2: 0 | BH2: 4.87 | BI2: 4.84 | BJ2: 6.64 | BK2: 4.63 | BL2: 3.45 | BM2: 5602 | BN2: 2847 | BO2: 2977 | BP2: 2978 | BQ2: 3926 | BR2: 35841 | BS2: 41601 | BT2: 41212 | BU2: 39339 | BV2: 37195 | BW2: 57600 | CB2: 72560 | CC2: 2746 | CD2: 8196 | CE2: 15923 | CF2: 32852 | CJ2: 46206 | CK2: Late shipment rate (since 3 months) ≥ 3% | CP2: USA | CQ2: yes | CR2: Natural Commerce Inc | CT2: 47-2127787 | CU2: Mrs | CV2: Chandler | CW2: Dearth | DA2: 520 Folly Rd | DB2: Suite 25-309 | DC2: 29412 | DD2: Charleston | DE2: SC | DF2: USA | DH2: yes | DI2: By default | DJ2: 0 | DK2: no | DL2: 0 | DO2: Default grid | DP2: 30 days, net | DQ2: 0 | DR2: Tier 3 | DS2: 99.92 | DT2: 99.75 | DU2: 99.91 | DV2: 99.92 | DW2: 99.92 | DX2: 1.72 | DY2: 1.69 | DZ2: 2.28 | EA2: 2.49 | EB2: 2.03 | EC2: kkhu6683@sysco.com | EF2: No | EI2: Not_Declared | EJ2: I_choose_not_to_disclose | EK2: No | EL2: TRUE | EM2: 73050 | EN2: 46595 | EO2: 46589 | EP2: 46589 | EQ2: 46589 | ER2: $2,000,000 | ES2: 42552 | ET2: Employer_Identification_Number | EU2: 47-2127787 | EV2: Natural Commerce | EW2: TRUE | EX2: FALSE | EY2: Inventory,Order,PO_Ack,Invoicing | FA2: External-Seller | FC2: Natural Commerce | FD2: 655 Commerce Pkwy E Dr | FI2: Greenwood | FJ2: USA | FK2: IN | FL2: 46143 | FM2: 4:00 AM | FN2: TRUE | FO2: Afternoon | FP2: UPS
A3: 45266.582 | B3: 2001 | C3: Specialty Food Partners | D3: Open | E3: 2001 | F3: yes | G3: USD | H3: hannah@specialtyfoodpartners.com | I3: no | J3: 32983.25 | K3: 0 | L3: 2051237.9 | M3: 3952 | N3: 0 | O3: 0 | P3: Products | Q3: Every 21st of the month | R3: KYC passed | T3: 2368393.4 | U3: 84632.84 | V3: 302273.89 | W3: 665755.26 | X3: 1281255.3 | Y3: 111.08 | Z3: 115.56 | AA3: 121.75 | AB3: 123 | AC3: 122.26 | AI3: 21474 | AJ3: 735 | AK3: 2494 | AL3: 5447 | AM3: 10554 | AN3: 99.99 | AO3: 100 | AP3: 100 | AQ3: 100 | AR3: 100 | AS3: 0.2 | AT3: 0.12 | AU3: 0.34 | AV3: 0.26 | AW3: 0.22 | AX3: 0.78 | AY3: 0.46 | AZ3: 0.78 | BA3: 0.96 | BB3: 0.84 | BC3: 0 | BD3: 0 | BE3: 0 | BF3: 0 | BG3: 0 | BH3: 0.68 | BI3: 0 | BJ3: 0.2 | BK3: 0.55 | BL3: 0.67 | BM3: 239 | BN3: 186 | BO3: 184 | BP3: 245 | BQ3: 259 | BR3: 65962 | BS3: 66089 | BT3: 69953 | BU3: 69018 | BV3: 67296 | BW3: 878 | BX3: 184 | BY3: 228 | BZ3: 320 | CA3: 565 | CB3: 21479 | CC3: 735 | CD3: 2494 | CE3: 5448 | CF3: 10556 | CP3: USA | CQ3: yes | CR3: Specialty Food Partners LLC | CS3: 080747413-001 | CT3: 84-4131469 | CU3: Neutral | CV3: Hannah | CW3: Pullman | CX3: 203-517-0041 x 203 | DA3: 68 Southfield Ave | DB3: Ste 100 | DC3: 06902 | DD3: Stamford | DE3: CT | DF3: USA | DG3: https://specialtyfoodpartners.com/ | DH3: yes | DI3: By default | DJ3: 0 | DK3: no | DL3: 0 | DO3: Commission grid 12 | DP3: 30 days, net | DQ3: 0 | DR3: Tier 3 | DS3: 99.74 | DT3: 100 | DU3: 99.96 | DV3: 99.74 | DW3: 99.74 | DX3: 1.24 | DY3: 0.81 | DZ3: 1.28 | EA3: 1.16 | EB3: 1.15 | EC3: kkhu6683@sysco.com | EF3: No | EI3: Not_Declared | EJ3: I_choose_not_to_disclose | EK3: No | EL3: TRUE | EM3: 73050 | EN3: 46130 | EO3: 46130 | EP3: 46130 | EQ3: 46130 | ER3: $2,000,000 | ES3: 43832 | ET3: Tax_Payer_Identification_Number | EU3: 84-4131469 | EW3: FALSE | EX3: TRUE | EY3: Inventory,Product_Content_and_Pricing,Order,Invoicing | FA3: External-Seller | FC3: Specialty Food Parnters | FD3: 30 Old Kings Highway S | FE3: 303 | FI3: Darien | FJ3: United States | FK3: CT | FL3: 06820 | FM3: 3 pm | FN3: FALSE | FO3: UPS - Morning, Afternoon and Evening | FP3: UPS
A4: 45280.51 | B4: 2002 | C4: Barista Joe’s | D4: Terminated | E4: 2002 | F4: no | G4: USD | H4: chris@dcamcoffee.com | I4: no | J4: 0 | K4: 0 | L4: 7449.77 | M4: 0 | N4: 0 | O4: 1 | P4: Products | Q4: Every 21st of the month | R4: KYC passed | T4: 8465.65 | U4: 0 | V4: 0 | W4: 0 | X4: 0 | Y4: 282.19 | AI4: 30 | AJ4: 0 | AK4: 0 | AL4: 0 | AM4: 0 | AN4: 94.74 | AS4: 2.78 | AX4: 0 | BC4: 5.26 | BH4: 12.5 | BM4: 76164 | BR4: 3808 | CB4: 32 | CC4: 0 | CD4: 0 | CE4: 0 | CF4: 0 | CG4: 45680 | CH4: Manual suspension | CN4: 45688.849 | CP4: USA | CQ4: yes | CR4: DCAM Group | CS4: M19000003887 | CT4: 834161696 | CU4: Mr | CV4: Chris | CW4: Miano | CX4: 8004416339 | CY4: 9542499296 | DA4: 4710 NW 15TH AVE 5C | DC4: 33309 | DD4: Fort Lauderdale | DE4: FL | DF4: USA | DG4: https://www.dcamcoffee.com | DH4: no | DO4: Commission grid 12 | DP4: 30 days, net | DQ4: 0 | DR4: Tier 3 | DX4: 0 | EC4: kkhu6683@sysco.com | EF4: No | EI4: I_choose_not_to_disclose | EJ4: I_choose_not_to_disclose | EK4: Yes | EL4: TRUE | EM4: 73050 | EN4: 45670 | EO4: 45670 | EP4: 45670 | EQ4: 45404 | ER4: $2,000,000 | ES4: 43566 | ET4: Employer_Identification_Number | EU4: 834161696 | EW4: FALSE | EX4: FALSE | FA4: External-Seller | FC4: DCAM GROUP / BARISTA JOE'S | FD4: 4710 NW 15TH AVE | FE4: 5C | FI4: Fort Lauderdale | FJ4: United States | FK4: FL | FL4: 33309 | FM4: 4pm | FN4: FALSE | FO4: Afternoon | FP4: FEDEX
A5: 45289.486 | B5: 2003 | C5: Yo Mama's Foods | D5: Open | E5: 2003 | F5: yes | G5: USD | H5: accounting@yomamasfoods.com | I5: no | J5: 472.97 | K5: 0 | L5: 62520.55 | M5: 16 | N5: 0 | O5: 0 | P5: Products | Q5: Every 21st of the month | R5: KYC passed | T5: 71547.4 | U5: 1179.78 | V5: 5616.3 | W5: 10970.67 | X5: 43940.79 | Y5: 62.21 | Z5: 40.68 | AA5: 46.04 | AB5: 47.7 | AC5: 94.96 | AI5: 1158 | AJ5: 29 | AK5: 122 | AL5: 230 | AM5: 466 | AN5: 100 | AO5: 100 | AP5: 100 | AQ5: 100 | AR5: 100 | AS5: 0.8 | AT5: 0 | AU5: 0 | AV5: 0 | AW5: 0.83 | AX5: 0.8 | AY5: 0 | AZ5: 0 | BA5: 0 | BB5: 0.83 | BC5: 0 | BD5: 0 | BE5: 0 | BF5: 0 | BG5: 0 | BH5: 0.43 | BI5: 0 | BJ5: 0 | BK5: 0 | BL5: 0 | BM5: 1607 | BN5: 3116 | BO5: 1402 | BP5: 1689 | BQ5: 1378 | BR5: 17786 | BS5: 13259 | BT5: 11419 | BU5: 11851 | BV5: 14903 | BW5: 715 | CB5: 1158 | CC5: 29 | CD5: 122 | CE5: 230 | CF5: 466 | CP5: USA | CQ5: yes | CR5: Yo Mama's Foods | CT5: 83-0561643 | CU5: Mr | CV5: David | CW5: Habib | CX5: 7272664745 | DA5: 1125 Eldridge Street | DC5: 33755 | DD5: Clearwater | DE5: FL | DF5: USA | DG5: https://www.yomamasfoods.com | DH5: yes | DI5: By default | DJ5: 0 | DK5: no | DL5: 0 | DO5: Commission grid 12 | DP5: 30 days, net | DQ5: 0 | DR5: Tier 3 | DS5: 88.1 | DT5: 92.86 | DU5: 88.43 | DV5: 88.1 | DW5: 88.1 | DX5: 0.07 | DY5: 0 | DZ5: 0 | EA5: 0 | EB5: 0 | EC5: kkhu6683@sysco.com | EF5: Yes | EG5: Black_or_African_American | EH5: Third-party | EI5: Not_Declared | EJ5: Small_Business_Enterprise_(SBE)_Certified | EK5: Yes | EL5: TRUE | EM5: 73050 | EN5: 45859 | EO5: 46222 | EP5: 46222 | EQ5: 46222 | ER5: 2 Million | ES5: 43236 | ET5: Employer_Identification_Number | EU5: 83-0561643 | EV5: Yo Mama's Foods | EW5: FALSE | EX5: TRUE | EY5: Order,PO_Ack,Invoicing | FA5: External-Seller | FC5: Yo Mama's Foods | FD5: 1125 Eldridge Street | FI5: Clearwater | FJ5: United States | FK5: Florida | FL5: 33755 | FM5: 6 AM | FN5: TRUE | FO5: Afternoon | FP5: FedEx
A6: 45294.555 | B6: 2004 | C6: Sapna Foods | D6: Open | E6: 2004 | F6: no | G6: USD | H6: ryan@sapnafoods.com | I6: no | J6: 10079.76 | K6: 0 | L6: 570996.23 | M6: 1443 | N6: 0 | O6: 0 | P6: Products | Q6: Every 21st of the month | R6: KYC passed | T6: 683622.94 | U6: 22744.49 | V6: 101899.21 | W6: 214456.14 | X6: 416336.5 | Y6: 134.52 | Z6: 120.34 | AA6: 140.52 | AB6: 142.39 | AC6: 136.94 | AI6: 5121 | AJ6: 189 | AK6: 728 | AL6: 1511 | AM6: 3062 | AN6: 99.96 | AO6: 100 | AP6: 100 | AQ6: 99.94 | AR6: 99.97 | AS6: 0.38 | AT6: 0 | AU6: 0.4 | AV6: 0.39 | AW6: 0.41 | AX6: 0.4 | AY6: 0 | AZ6: 0.54 | BA6: 0.39 | BB6: 0.41 | BC6: 0 | BD6: 0 | BE6: 0 | BF6: 0 | BG6: 0 | BH6: 44.36 | BI6: 45.5 | BJ6: 60.85 | BK6: 72.7 | BL6: 64.89 | BM6: 3831 | BN6: 4645 | BO6: 4016 | BP6: 4684 | BQ6: 4315 | BR6: 74048 | BS6: 85277 | BT6: 90374 | BU6: 95931 | BV6: 85741 | BW6: 5680 | BZ6: 1989 | CA6: 8520 | CB6: 5127 | CC6: 189 | CD6: 728 | CE6: 1513 | CF6: 3065 | CJ6: 45604 | CK6: Late shipment rate (since 3 months) ≥ 3% | CP6: USA | CQ6: yes | CR6: Sapna Foods, Inc | CT6: 582380399 | CU6: Mr | CV6: Cofield | CW6: Ryan | CX6: 4045890977 | CZ6: 4045899711 | DA6: 2280 Mountain Industrial Blvd | DC6: 30084 | DD6: Tucker | DE6: GA | DF6: USA | DG6: https://essentialspice.com/ | DH6: yes | DI6: By default | DJ6: 0 | DK6: no | DL6: 0 | DO6: Commission grid 15 | DP6: 30 days, net | DQ6: 0 | DR6: Tier 3 | DS6: 99.48 | DT6: 98.78 | DU6: 99.43 | DV6: 99.48 | DW6: 99.48 | DX6: 0.71 | DY6: 0 | DZ6: 0 | EA6: 0.06 | EB6: 0.45 | EC6: kkhu6683@sysco.com | EF6: I_choose_not_to_disclose | EG6: Other | EI6: Not_Declared | EJ6: I_choose_not_to_disclose | EK6: Yes | EL6: TRUE | EM6: 73050 | EN6: 45548 | EO6: 45548 | EP6: 45436 | EQ6: 45504 | ER6: 2000000 | ES6: 35821 | ET6: Employer_Identification_Number | EU6: 582380399 | EV6: Essential Spice | EW6: FALSE | EX6: TRUE | EY6: Inventory,Order,PO_Ack,Invoicing | FA6: External-Seller | FC6: Essential Spice | FD6: 2280 Mountain Industrial Blvd | FI6: Tucker | FJ6: United States | FK6: Georgia | FL6: 30084 | FM6: 2:00pm | FN6: TRUE | FO6: Morning, Afternnon, Evening | FP6: UPS
A7: 45301.284 | B7: 2005 | C7: Mavuno Harvest | D7: Open | E7: 2005 | F7: yes | G7: USD | H7: orders@mavunoharvest.com | I7: no | J7: 223.81 | K7: 0 | L7: 20372.6 | M7: 26 | N7: 0 | O7: 0 | P7: Products | Q7: Every 21st of the month | R7: KYC passed | T7: 25117.68 | U7: 992.83 | V7: 7531.64 | W7: 9270.39 | X7: 12614.99 | Y7: 80.2 | Z7: 66.19 | AA7: 70.39 | AB7: 72.42 | AC7: 83.54 | AI7: 314 | AJ7: 15 | AK7: 107 | AL7: 128 | AM7: 151 | AN7: 98.51 | AO7: 100 | AP7: 100 | AQ7: 99.26 | AR7: 97.56 | AS7: 0.3 | AT7: 0 | AU7: 0.88 | AV7: 0.74 | AW7: 0.63 | AX7: 0.3 | AY7: 0 | AZ7: 0 | BA7: 0 | BB7: 0 | BC7: 1.19 | BD7: 0 | BE7: 0 | BF7: 0 | BG7: 1.83 | BH7: 4.08 | BI7: 6.67 | BJ7: 1.87 | BK7: 2.33 | BL7: 4.52 | BM7: 10972 | BN7: 218 | BO7: 6543 | BP7: 8222 | BQ7: 11117 | BR7: 3604 | BS7: 30478 | BT7: 5119 | BU7: 4271 | BV7: 3860 | CB7: 319 | CC7: 15 | CD7: 107 | CE7: 129 | CF7: 155 | CP7: USA | CQ7: yes | CR7: Mavuno Harvest | CT7: 45-3325962 | CU7: Mr | CV7: Phil | CW7: Hughes | CX7: 2152598785 | DA7: 4125 Whitaker Avenue | DC7: 19124 | DD7: Philadelphia, PA | DE7: PA | DF7: USA | DG7: https://mavunoharvest.com/ | DH7: yes | DI7: By default | DJ7: 0 | DK7: no | DL7: 0 | DO7: Commission grid 18 | DP7: 30 days, net | DQ7: 0 | DR7: Tier 3 | DS7: 100 | DT7: 100 | DU7: 100 | DV7: 100 | DW7: 100 | DX7: 0.3 | DY7: 0 | DZ7: 0 | EA7: 0 | EB7: 0.63 | EC7: kkhu6683@sysco.com | EF7: I_choose_not_to_disclose | EI7: I_choose_not_to_disclose | EJ7: I_choose_not_to_disclose | EK7: Yes | EL7: TRUE | EM7: 73050 | EN7: 46166 | EO7: 46166 | EP7: 46166 | EQ7: 46098 | ER7: 4,000,000 | ES7: 40800 | ET7: Employer_Identification_Number | EU7: 45-3325962 | EV7: Mavuno Harvest | EW7: FALSE | EX7: TRUE | EY7: Inventory,Order | FA7: External-Seller | FC7: Mavuno LLC | FD7: 4125 Whitaker Avenue | FI7: Philadelphia, PA | FJ7: United States | FK7: PA | FL7: 19124 | FM7: 3pm | FN7: TRUE | FO7: morning, afternoon, and evening | FP7: ups, usps, fedex
A8: 45301.558 | B8: 2006 | C8: Crafted Brand Company | D8: Open | E8: 2006 | F8: no | G8: USD | H8: dylanm@craftedbrandcompany.com | I8: no | J8: 0 | K8: 0 | L8: 13276.15 | M8: 0 | N8: 0 | O8: 0 | P8: Products | Q8: Every 21st of the month | R8: KYC passed | T8: 16390.58 | U8: 0 | V8: 0 | W8: 1103.98 | X8: 6077.48 | Y8: 58.59 | AB8: 73.6 | AC8: 61.09 | AI8: 282 | AJ8: 0 | AK8: 0 | AL8: 15 | AM8: 101 | AN8: 98 | AQ8: 93.75 | AR8: 95.33 | AS8: 0 | AV8: 0 | AW8: 0 | AX8: 1.02 | BA8: 0 | BB8: 1.96 | BC8: 1 | BF8: 0 | BG8: 2.8 | BH8: 22.92 | BK8: 0 | BL8: 16.98 | BM8: 6664 | BP8: 8828 | BQ8: 7499 | BR8: 28389 | BU8: 26095 | BV8: 29476 | CB8: 288 | CC8: 0 | CD8: 0 | CE8: 16 | CF8: 106 | CP8: USA | CQ8: yes | CR8: Crafted Brand Company | CS8: 201407810635 | CT8: 47-3417606 | CU8: Mr | CV8: Dylan | CW8: Milne | CX8: 8583955789 | DA8: 5348 Vegas Dr | DB8: #532 | DC8: 89108 | DD8: Las Vegas | DE8: NV | DF8: USA | DG8: https://craftedcocktails.com/ | DH8: yes | DI8: By default | DJ8: 0 | DK8: no | DL8: 0 | DO8: Commission grid 19 | DP8: 30 days, net | DQ8: 0 | DR8: Tier 3 | DX8: 1.36 | EA8: 0 | EB8: 0 | EC8: kkhu6683@sysco.com | EF8: Yes | EG8: Hispanic_or_Latino | EH8: Third-party | EI8: Woman_Supplier | EJ8: I_choose_not_to_disclose | EK8: I_choose_not_to_disclose | EL8: TRUE | EM8: 73050 | EN8: 46280 | EO8: 46280 | EP8: 46280 | EQ8: 46280 | ER8: 4000000 | ES8: 41712 | ET8: Tax_Payer_Identification_Number | EU8: 47-3417606 | EV8: Crafted Cocktails | EW8: FALSE | EX8: FALSE | FA8: External-Seller | FC8: Crafted Brand Company- IL | FD8: 14908 South Gougar Road | FI8: Lockport | FJ8: United States | FK8: IL | FL8: 60441 | FM8: 12:00 PM | FN8: FALSE | FO8: Afternoon/Evening | FP8: UPS and FedEx
A9: 45308.49 | B9: 2007 | C9: AB American Boy | D9: Terminated | E9: 2007 | F9: no | G9: USD | H9: abamerican@americantowellinen.com | I9: yes | J9: 0 | K9: 0 | L9: 0 | M9: 0 | N9: 0 | O9: 0 | P9: Products | Q9: Every 21st of the month | R9: Pending KYC submission | S9: <html lang="en"> <body> Create your account with Payoneer, Mirakl Payout’s partner, to submit your KYC information and receive payments to your wallet. <br/> <br/> <a href="https://payouts.payoneer.com/partners/lp.aspx?token=1ae4f3f4109a447a8566e5e415e21e715C4915E75D" class="btn btn-outline btn-outline-default"> <span>Create account</span> </a> </body> </html> | T9: 0 | U9: 0 | V9: 0 | W9: 0 | X9: 0 | AI9: 0 | AJ9: 0 | AK9: 0 | AL9: 0 | AM9: 0 | CB9: 0 | CC9: 0 | CD9: 0 | CE9: 0 | CF9: 0 | CN9: 45434.654 | CQ9: yes | CR9: AB American Boy Inc | CS9: 802625009 | CT9: 453171959 | CU9: Mr | CV9: abdul | CW9: Bheda | CX9: 2147251995 | DA9: 4108 Los Altos Drive | DC9: 75024 | DD9: Plano | DE9: Texas | DF9: USA | DG9: https://www.americanlinentowel.com | DH9: no | DO9: Default grid | DP9: 30 days, net | DQ9: 0 | DR9: Tier 3 | EC9: kkhu6683@sysco.com | EF9: Yes | EG9: OTHER | EH9: Third-party | EI9: No | EJ9: Small_Business_Enterprise_(SBE) | EK9: Yes | EL9: FALSE | EM9: 45322 | EN9: 45395 | EO9: 45395 | EP9: 45395 | EQ9: 45395 | ER9: 2000000 | ES9: 42748 | ET9: Employer_Identification_Number | EU9: 45-3171959 | EV9: AB American Boy Inc | EW9: TRUE | EX9: FALSE | EY9: Inventory,Product_Content_and_Pricing,Order,Invoicing | FA9: External-Seller | FC9: Calderon Textile | FD9: 4108 Los Altos Drive | FI9: Plano | FJ9: USA | FK9: Texas | FL9: 75024 | FM9: 3:pm CT | FN9: TRUE | FO9: 8-5pm CT | FP9: UPS. Fedex , DHL, other LTL
A10: 45309.583 | B10: 2008 | C10: Go Mouthwash | D10: Open | E10: 2008 | F10: yes | G10: USD | H10: austin@gomouthwash.com | I10: no | J10: 73.8 | K10: 0 | L10: 7559.86 | M10: 7 | N10: 0 | O10: 0 | P10: Products | Q10: Every 21st of the month | R10: KYC passed | T10: 9309.42 | U10: 270 | V10: 2459.99 | W10: 4139.97 | X10: 7319.84 | Y10: 125.8 | Z10: 135 | AA10: 223.64 | AB10: 172.5 | AC10: 159.13 | AI10: 74 | AJ10: 2 | AK10: 11 | AL10: 24 | AM10: 46 | AN10: 97.37 | AO10: 100 | AP10: 100 | AQ10: 100 | AR10: 95.83 | AS10: 0 | AT10: 0 | AU10: 0 | AV10: 0 | AW10: 0 | AX10: 0 | AY10: 0 | AZ10: 0 | BA10: 0 | BB10: 0 | BC10: 0 | BD10: 0 | BE10: 0 | BF10: 0 | BG10: 0 | BH10: 5.41 | BI10: 0 | BJ10: 0 | BK10: 4.17 | BL10: 4.35 | BM10: 5178 | BN10: 16706 | BO10: 8648 | BP10: 5403 | BQ10: 5729 | BR10: 32268 | BS10: 10590 | BT10: 12781 | BU10: 19526 | BV10: 23801 | CB10: 74 | CC10: 2 | CD10: 11 | CE10: 24 | CF10: 46 | CP10: USA | CQ10: yes | CR10: Go Mouthwash | CT10: 83-0621227 | CU10: Mr | CV10: Austin | CW10: Loper | CX10: 8106268695 | CY10: 8106268695 | DA10: 40 Pearl St. Suite 200 | DC10: 49503 | DD10: Grand Rapids | DE10: MI | DF10: USA | DG10: http://gomouthwash.com | DH10: yes | DI10: By default | DJ10: 0 | DK10: no | DL10: 0 | DO10: Commission grid 18 | DP10: 30 days, net | DQ10: 0 | DR10: Tier 3 | DS10: 100 | DT10: 100 | DU10: 100 | DV10: 100 | DW10: 100 | DX10: 1.35 | DY10: 0 | DZ10: 0 | EA10: 4.17 | EB10: 2.17 | EC10: kkhu6683@sysco.com | EF10: Yes | EH10: Third-party | EI10: Woman_Supplier | EJ10: Women's_Business_Enterprise_(WBE)_Certified | EK10: Yes | EL10: FALSE | EM10: 73050 | EN10: 46043 | EO10: 46043 | EP10: 46043 | EQ10: 46043 | ER10: 2000000 | ES10: 43328 | ET10: Employer_Identification_Number | EU10: 83-0621227 | EV10: Go Mouthwash | EW10: FALSE | EX10: FALSE | FA10: External-Seller | FC10: Go Mouthwash | FD10: 2350 Port Lansing Rd. | FE10: Suite 5 | FI10: Lansing | FJ10: United States | FK10: MI | FL10: 48906 | FM10: 9 | FN10: FALSE | FO10: Afternoon | FP10: UPS
A11: 45324.527 | B11: 2009 | C11: WATCHAREE'S Thai Sauces | D11: Open | E11: 2009 | F11: no | G11: USD | H11: watcharee@thaiculinaryarts.com | I11: no | J11: 0 | K11: 0 | L11: 5633.13 | M11: 15 | N11: 0 | O11: 0 | P11: Products | Q11: Every 21st of the month | R11: KYC passed | T11: 6869.8 | U11: 0 | V11: 251.92 | W11: 1712.39 | X11: 2818.69 | Y11: 64.81 | Z11: 0 | AA11: 62.98 | AB11: 90.13 | AC11: 80.53 | AI11: 106 | AJ11: 1 | AK11: 4 | AL11: 19 | AM11: 35 | AN11: 100 | AO11: 100 | AP11: 100 | AQ11: 100 | AR11: 100 | AS11: 0 | AT11: 0 | AU11: 0 | AV11: 0 | AW11: 0 | AX11: 0 | AY11: 0 | AZ11: 0 | BA11: 0 | BB11: 0 | BC11: 0 | BD11: 0 | BE11: 0 | BF11: 0 | BG11: 0 | BH11: 14.02 | BI11: 0 | BJ11: 0 | BK11: 10.53 | BL11: 17.14 | BM11: 11105 | BN11: 22808 | BO11: 13979 | BP11: 19351 | BQ11: 18152 | BR11: 74561 | BT11: 69779 | BU11: 76389 | BV11: 78423 | BW11: 29406 | BZ11: 29406 | CA11: 29406 | CB11: 107 | CC11: 1 | CD11: 4 | CE11: 19 | CF11: 35 | CP11: USA | CQ11: yes | CR11: Thai Culinary Arts Studio LLC | CS11: Thai Culinary Arts Studio LLC | CT11: 46-5326243 | CU11: Miss | CV11: Watcharee | CW11: Limanon | CX11: 8009312970 | DA11: PO Box 595 | DC11: 04096 | DD11: Yarmouth | DE11: ME | DF11: USA | DG11: https://www.watcharees.com | DH11: yes | DI11: By default | DJ11: 0 | DK11: no | DL11: 0 | DO11: Commission grid 18 | DP11: 30 days, net | DQ11: 0 | DR11: Tier 3 | DS11: 100 | DU11: 100 | DV11: 100 | DW11: 100 | DX11: 0 | DY11: 0 | DZ11: 0 | EA11: 0 | EB11: 0 | EC11: kkhu6683@sysco.com | EF11: Yes | EG11: Asian | EH11: Self-selected | EI11: Woman_Supplier | EJ11: Small_Business_Enterprise_(SBE)_Certified | EK11: Yes | EL11: TRUE | EM11: 73050 | EN11: 45762 | EO11: 45762 | EP11: 45762 | EQ11: 45762 | ER11: 5,000,000 | ES11: 41698 | ET11: Employer_Identification_Number | EU11: 465326243 | EV11: Thai Culinary Arts Studio LLC | EW11: FALSE | EX11: TRUE | EY11: PO_Ack | FA11: External-Seller | FC11: 3G Warehouse | FD11: 320 Mill Road | FI11: Edison | FJ11: USA | FK11: NJ | FL11: 08817 | FM11: 12 PM | FN11: FALSE | FO11: Afternoon | FP11: UPS, USPS
A12: 45342.555 | B12: 2010 | C12: Gourmet Foodservice Group | D12: Open | E12: 2010 | F12: no | G12: USD | H12: amorelli@foodinno.com | I12: no | J12: 60802.04 | K12: 627.98 | L12: 3175977.2 | M12: 1639 | N12: 0 | O12: 0 | P12: Products | Q12: Every 21st of the month | R12: KYC passed | T12: 3808255.1 | U12: 128846.82 | V12: 413107.53 | W12: 806428.35 | X12: 1712092.8 | Y12: 160.97 | Z12: 163.98 | AA12: 177.64 | AB12: 176.93 | AC12: 179.47 | AI12: 23825 | AJ12: 799 | AK12: 2353 | AL12: 4598 | AM12: 9632 | AN12: 99.99 | AO12: 100 | AP12: 100 | AQ12: 100 | AR12: 99.99 | AS12: 0.4 | AT12: 0.37 | AU12: 0.37 | AV12: 0.4 | AW12: 0.58 | AX12: 0.39 | AY12: 0.61 | AZ12: 0.49 | BA12: 0.46 | BB12: 0.51 | BC12: 0 | BD12: 0 | BE12: 0 | BF12: 0 | BG12: 0 | BH12: 3.77 | BI12: 3.13 | BJ12: 2.68 | BK12: 2.8 | BL12: 3.8 | BM12: 1778 | BN12: 1016 | BO12: 1346 | BP12: 1221 | BQ12: 1173 | BR12: 39428 | BS12: 38563 | BT12: 38568 | BU12: 39562 | BV12: 39753 | BW12: 9743 | BX12: 3308 | BY12: 4065 | BZ12: 3704 | CA12: 4838 | CB12: 23834 | CC12: 799 | CD12: 2353 | CE12: 4599 | CF12: 9638 | CP12: USA | CQ12: yes | CR12: Gourmet Foodservice Group | CS12: 4616488 | CT12: 26-3780857 | CU12: Mrs | CV12: Anita | CW12: Morelli | CX12: 239-449-3238 | CY12: 1-888-352-3663 | CZ12: 866-258-8108 | DA12: 9696 Bonita Beach Rd. | DB12: Ste. 208 | DC12: 34135 | DD12: Bonita Springs | DE12: FL | DF12: USA | DG12: https://ivfh.com | DH12: yes | DI12: By default | DJ12: 0 | DK12: no | DL12: 0 | DO12: Commission grid 15 | DP12: 30 days, net | DQ12: 0 | DR12: Tier 3 | DS12: 100 | DT12: 100 | DU12: 100 | DV12: 100 | DW12: 100 | DX12: 2.74 | DY12: 2.92 | DZ12: 2.27 | EA12: 2.44 | EB12: 2.65 | EC12: kkhu6683@sysco.com | EF12: I_choose_not_to_disclose | EI12: I_choose_not_to_disclose | EJ12: I_choose_not_to_disclose | EK12: I_choose_not_to_disclose | EL12: TRUE | EM12: 73050 | EN12: 45627 | EO12: 45627 | EP12: 45627 | EQ12: 45474 | ER12: 6,305,000 | ES12: 40004 | ET12: Employer_Identification_Number | EU12: 26-3780857 | EV12: Gourmet Foodservice Group | EW12: TRUE | EX12: FALSE | EY12: Order,PO_Ack,Invoicing | FA12: External-Seller | FC12: Artisan Specialty Foods | FD12: 2528 S 27th Ave | FI12: Broadview | FJ12: USA | FK12: IL | FL12: 60155 | FM12: 3 pm | FN12: TRUE | FO12: Morning, Afternoon, Evening | FP12: FedEx
A13: 45344.612 | B13: 2011 | C13: Dot Foods | D13: Open | E13: 2011 | F13: no | G13: USD | H13: steve.ramlet@dotfoods.com | I13: no | J13: 365916.29 | K13: 7642.49 | L13: 10168726 | M13: 8300 | N13: 0 | O13: 0 | P13: Products | Q13: Every 21st of the month | R13: KYC passed | T13: 11979855 | U13: 832185.25 | V13: 2925248.6 | W13: 5875164.4 | X13: 9026704.5 | Y13: 145.16 | Z13: 140.8 | AA13: 151.33 | AB13: 153.25 | AC13: 152.12 | AI13: 83176 | AJ13: 5939 | AK13: 19443 | AL13: 38609 | AM13: 59836 | AN13: 100 | AO13: 100 | AP13: 100 | AQ13: 100 | AR13: 100 | AS13: 0.36 | AT13: 0.29 | AU13: 0.34 | AV13: 0.38 | AW13: 0.41 | AX13: 0.55 | AY13: 0.3 | AZ13: 0.43 | BA13: 0.51 | BB13: 0.58 | BC13: 0 | BD13: 0 | BE13: 0 | BF13: 0 | BG13: 0 | BH13: 20.93 | BI13: 9.87 | BJ13: 10.83 | BK13: 17.39 | BL13: 17.8 | BM13: 454 | BN13: 390 | BO13: 417 | BP13: 454 | BQ13: 454 | BR13: 158007 | BS13: 127515 | BT13: 129713 | BU13: 145992 | BV13: 150058 | BW13: 171572 | CB13: 83177 | CC13: 5940 | CD13: 19444 | CE13: 38610 | CF13: 59837 | CJ13: 45472 | CK13: Late shipment rate (since 3 months) ≥ 3% | CP13: USA | CQ13: yes | CR13: Dot Foods | CS13: 4270-3409 | CT13: 37-1872672 | CU13: Mr | CV13: Steve | CW13: Ramlet | CX13: 636.449.3622 | DA13: 1 Dot Way | DB13: P.O. Box 192 | DC13: 62353 | DD13: Mt. Sterling | DE13: IL | DF13: USA | DG13: https://www.dotfoods.com/ | DH13: yes | DI13: By default | DJ13: 0 | DK13: no | DL13: 0 | DO13: Commission grid 12 | DP13: 30 days, net | DQ13: 0 | DR13: Tier 3 | DS13: 97.2 | DT13: 99.8 | DU13: 99.9 | DV13: 97.2 | DW13: 97.2 | DX13: 2.14 | DY13: 3.08 | DZ13: 2.55 | EA13: 2.34 | EB13: 2.29 | EC13: kkhu6683@sysco.com | EF13: No | EI13: Not_Declared | EJ13: I_choose_not_to_disclose | EK13: No | EL13: TRUE | EM13: 73050 | EN13: 45658 | EO13: 45658 | EP13: 45658 | EQ13: 45658 | ER13: 2,000,000 | ES13: 43067 | ET13: Employer_Identification_Number | EU13: 37-1872672 | EW13: TRUE | EX13: FALSE | EY13: Order,PO_Ack | FA13: Internal-Seller | FC13: Dot Foods Inc. | FD13: 1 Dot Way | FI13: Mt. Sterling | FJ13: United States | FK13: IL | FL13: 62353 | FM13: varies by day, time, and distribution location | FN13: TRUE | FO13: Morning, Afternoon, and Evening | FP13: FedEx
A14: 45345.441 | B14: 2012 | C14: RCN Imports | D14: Open | E14: 2012 | F14: no | G14: USD | H14: joel@rcnimports.com | I14: no | J14: 232.88 | K14: 0 | L14: 57618.94 | M14: 4 | N14: 0 | O14: 0 | P14: Products | Q14: Every 21st of the month | R14: KYC passed | T14: 70551 | U14: 816 | V14: 3440 | W14: 9916 | X14: 19939 | Y14: 90.37 | Z14: 90.67 | AA14: 86 | AB14: 91.81 | AC14: 89.41 | AI14: 782 | AJ14: 9 | AK14: 40 | AL14: 108 | AM14: 223 | AN14: 100 | AO14: 100 | AP14: 100 | AQ14: 100 | AR14: 100 | AS14: 0.38 | AT14: 0 | AU14: 0 | AV14: 0 | AW14: 0 | AX14: 0.25 | AY14: 0 | AZ14: 0 | BA14: 0 | BB14: 0 | BC14: 0 | BD14: 0 | BE14: 0 | BF14: 0 | BG14: 0 | BH14: 0.51 | BI14: 11.11 | BJ14: 7.5 | BK14: 2.78 | BL14: 1.79 | BM14: 14819 | BN14: 51788 | BO14: 45363 | BP14: 36446 | BQ14: 33947 | BR14: 10788 | BS14: 25021 | BT14: 111798 | BU14: 45788 | BV14: 27860 | CB14: 782 | CC14: 9 | CD14: 40 | CE14: 108 | CF14: 223 | CJ14: 46284 | CK14: Late shipment rate (since 3 months) ≥ 3% | CP14: USA | CQ14: yes | CR14: RCN Imports | CS14: 0400590960 | CT14: 46-3391207 | CU14: Mr | CV14: Joel | CW14: Goldsmith | CX14: 9732292639 | CY14: 9739749940 | DA14: 299 Hillside Avenue | DC14: 07039 | DD14: Livingston | DE14: NJ | DF14: USA | DG14: https://www.rcnimports.com | DH14: yes | DI14: By default | DJ14: 0 | DK14: no | DL14: 0 | DO14: Commission grid 18 | DP14: 30 days, net | DQ14: 0 | DR14: Tier 3 | DS14: 100 | DT14: 100 | DU14: 100 | DV14: 100 | DW14: 100 | DX14: 0.13 | DY14: 0 | DZ14: 2.5 | EA14: 0.93 | EB14: 0.45 | EC14: kkhu6683@sysco.com | EF14: I_choose_not_to_disclose | EH14: Self-selected | EI14: Woman_Supplier | EJ14: I_choose_not_to_disclose | EK14: Yes | EL14: TRUE | EM14: 73050 | EN14: 45951 | EO14: 45951 | EP14: 45951 | EQ14: 45951 | ER14: 8,000,000 | ES14: 41485 | ET14: Employer_Identification_Number | EU14: 463391207 | EV14: RCN Imports | EW14: FALSE | EX14: FALSE | FA14: External-Seller | FC14: RCN Imports | FD14: 135 Raritan Center PKWY | FE14: Suite 1 | FI14: Edison | FJ14: United States | FK14: New Jersey | FL14: 08837 | FM14: 4 pm | FN14: FALSE | FO14: Afternoon | FP14: Federal Express
A15: 45345.525 | B15: 2013 | C15: Aiva Products | D15: Open | E15: 2013 | F15: yes | G15: USD | H15: info@aivaproducts.com | I15: no | J15: 8753.58 | K15: 0 | L15: 209625.59 | M15: 260 | N15: 0 | O15: 0 | P15: Products | Q15: Every 21st of the month | R15: KYC passed | T15: 266323.52 | U15: 20975.6 | V15: 80462.73 | W15: 120338.6 | X15: 184338.59 | Y15: 55.6 | Z15: 66.96 | AA15: 74.79 | AB15: 70.66 | AC15: 63.95 | AI15: 4825 | AJ15: 315 | AK15: 1088 | AL15: 1722 | AM15: 2906 | AN15: 99.86 | AO15: 100 | AP15: 100 | AQ15: 100 | AR15: 100 | AS15: 0.34 | AT15: 0 | AU15: 0.44 | AV15: 0.44 | AW15: 0.3 | AX15: 0.62 | AY15: 0.63 | AZ15: 0.53 | BA15: 0.99 | BB15: 0.69 | BC15: 0 | BD15: 0 | BE15: 0 | BF15: 0 | BG15: 0 | BH15: 0.27 | BI15: 0.32 | BJ15: 0.28 | BK15: 0.29 | BL15: 0.24 | BM15: 817 | BN15: 409 | BO15: 177 | BP15: 166 | BQ15: 209 | BR15: 8829 | BS15: 7077 | BT15: 7654 | BU15: 8872 | BV15: 8501 | BW15: 4757 | BY15: 4757 | BZ15: 4757 | CA15: 4757 | CB15: 4831 | CC15: 315 | CD15: 1088 | CE15: 1722 | CF15: 2906 | CN15: 45650 | CO15: 45659 | CP15: USA | CQ15: yes | CR15: Vaikunth LLC DBA Aiva Products | CS15: 801916706 | CT15: 464560046 | CU15: Mr | CV15: Vinay | CW15: Patel | CX15: (832) 303-6153 | DA15: 10601 S SAM HOUSTON PKWY W, STE 190 | DC15: 77701 | DD15: HOUSTON | DE15: Texas | DF15: USA | DG15: https://www.aivaproducts.com/ | DH15: yes | DI15: By default | DJ15: 0 | DK15: no | DL15: 0 | DO15: Commission grid 18 | DP15: 30 days, net | DQ15: 0 | DR15: Tier 3 | DS15: 99.39 | DT15: 100 | DU15: 99.54 | DV15: 99.39 | DW15: 99.39 | DX15: 0.12 | DY15: 0 | DZ15: 0.09 | EA15: 0.06 | EB15: 0.13 | EC15: kkhu6683@sysco.com | EF15: I_choose_not_to_disclose | EG15: Asian | EH15: Self-selected | EI15: I_choose_not_to_disclose | EJ15: I_choose_not_to_disclose | EK15: I_choose_not_to_disclose | EL15: TRUE | EM15: 73050 | EN15: 46457 | EO15: 46457 | EP15: 46457 | EQ15: 46457 | ER15: 2000000 | ES15: 41655 | ET15: Employer_Identification_Number | EU15: 464560040 | EV15: Vaikunth LLC DBA Aiva Products | EW15: TRUE | EX15: FALSE | FA15: External-Seller | FC15: Aiva Products | FD15: 10601 S SAM HOUSTON PKWY W | FE15: SUITE 190 | FI15: HOUSTON | FJ15: United States | FK15: Texas | FL15: 77701 | FM15: 8:30 AM | FN15: TRUE | FO15: Morning, Afternoon, Evening | FP15: USPS and UPS
A16: 45348.43 | B16: 2014 | C16: Pure Food by Estee | D16: Suspended | E16: 2014 | F16: no | G16: USD | H16: franco@pure-food.ca | I16: no | J16: 0 | K16: 0 | L16: 11984.72 | M16: 0 | N16: 0 | O16: 0 | P16: Products | Q16: Every 21st of the month | R16: KYC passed | T16: 14615.6 | U16: 0 | V16: 0 | W16: 0 | X16: 294 | Y16: 59.97 | AC16: 13.36 | AI16: 247 | AJ16: 0 | AK16: 0 | AL16: 0 | AM16: 22 | AN16: 99.61 | AR16: 100 | AS16: 1.16 | AW16: 0 | AX16: 0.78 | BB16: 0 | BC16: 0 | BG16: 0 | BH16: 31.45 | BL16: 100 | BM16: 9368 | BQ16: 188 | BR16: 225747 | BV16: 978345 | CB16: 248 | CC16: 0 | CD16: 0 | CE16: 0 | CF16: 22 | CG16: 45944 | CH16: Manual suspension | CP16: CAN | CQ16: yes | CR16: Pure Food by Estee | CS16: 2094328 | CT16: 806048146RP0002 | CU16: Mr | CV16: Franco | CW16: Timpano | CX16: 647 860 2580 | DA16: 10 Wanless Ave | DB16: Suite 201 | DC16: M4N 1V6 | DD16: Toronto | DE16: ON | DF16: CAN | DG16: https://www.pure-food.ca | DH16: yes | DI16: By default | DJ16: 0 | DK16: no | DL16: 0 | DO16: Commission grid 18 | DP16: 30 days, net | DQ16: 0 | DR16: Tier 3 | DX16: 9.3 | EB16: 78.26 | EC16: kkhu6683@sysco.com | EF16: Yes | EH16: Self-selected | EI16: Woman_Supplier | EJ16: Small_Business_Enterprise_(SBE)_Certified | EK16: Yes | EL16: TRUE | EM16: 73050 | EN16: 45716 | EO16: 45716 | EP16: 45716 | EQ16: 45716 | ER16: 2500000 | ES16: 42430 | ET16: Tax_Payer_Identification_Number | EU16: 806048146RP0002 | EV16: Pure Food by Estée | EW16: FALSE | EX16: TRUE | EY16: Product_Content_and_Pricing,Order,Invoicing | FA16: External-Seller | FC16: Pure Food by Estée | FD16: 10 Wanless Ave | FE16: Suite 201 | FI16: Toronto | FJ16: Canada | FK16: ON | FL16: M4N 1V6 | FM16: 3 | FN16: FALSE | FO16: Morning Afternoon Evening | FP16: USPS
A17: 45348.482 | B17: 2015 | C17: Buettner Global Services | D17: Open | E17: 2015 | F17: no | G17: USD | H17: Jenny@bgs-corp.com | I17: no | J17: 0 | K17: 0 | L17: 1895.07 | M17: 10 | N17: 0 | O17: 0 | P17: Products | Q17: Every 21st of the month | R17: KYC passed | T17: 2311.04 | U17: 0 | V17: 32.86 | W17: 32.86 | X17: 755.24 | Y17: 135.94 | AA17: 32.86 | AB17: 32.86 | AC17: 125.87 | AI17: 17 | AJ17: 0 | AK17: 1 | AL17: 1 | AM17: 6 | AN17: 94.74 | AP17: 100 | AQ17: 100 | AR17: 100 | AS17: 0 | AU17: 0 | AV17: 0 | AW17: 0 | AX17: 0 | AZ17: 0 | BA17: 0 | BB17: 0 | BC17: 5.26 | BE17: 0 | BF17: 0 | BG17: 0 | BH17: 50 | BJ17: 0 | BK17: 0 | BL17: 33.33 | BM17: 103537 | BO17: 188322 | BP17: 188322 | BQ17: 169768 | BR17: 232048 | BT17: 306 | BU17: 306 | BV17: 101600 | CB17: 18 | CC17: 0 | CD17: 1 | CE17: 1 | CF17: 6 | CP17: USA | CQ17: yes | CR17: Buettner Global Services Corp | CS17: MUQFL3KUGKR7 | CT17: 851252078 | CU17: Mrs | CV17: Jenny | CW17: Buettner | CX17: 7143697178 | CY17: 7143300231 | DA17: 32 Tatahatso Point St | DC17: 89011 | DD17: Henderson | DE17: Nevada | DF17: USA | DG17: http://www.Bgs-corp.com | DH17: yes | DI17: By default | DJ17: 0 | DK17: no | DL17: 0 | DO17: Commission grid 18 | DP17: 30 days, net | DQ17: 0 | DR17: Tier 3 | DS17: 100 | DU17: 100 | DV17: 100 | DW17: 100 | DX17: 0 | DZ17: 0 | EA17: 0 | EB17: 0 | EC17: kkhu6683@sysco.com | EF17: Yes | EG17: Other | EH17: Third-party | EI17: Woman_Supplier | EJ17: Women's_Business_Enterprise_(WBE)_Certified,Small_Business_Enterprise_(SBE)_Certified,Small_Disadvantaged_Business_(SDB)_Certified | EK17: Yes | EL17: TRUE | EM17: 73050 | EN17: 45797 | EO17: 45848 | EP17: 45708 | EQ17: 45589 | ER17: 4000000 | ES17: 43971 | ET17: Employer_Identification_Number | EU17: 851252078 | EV17: Buettner Global Services | EW17: TRUE | EX17: FALSE | FA17: External-Seller | FC17: Buettner Global Services | FD17: 32 Tatahatso Point St | FI17: Henderson | FJ17: USA | FK17: Nevada | FL17: 89011 | FM17: 3pm | FN17: FALSE | FO17: 9-3 | FP17: UPS, USPS, FEDEX, DHL
A18: 45348.609 | B18: 2016 | C18: Restaurant Furniture Plus | D18: Open | E18: 2016 | F18: no | G18: USD | H18: akessler@kwventuresgroup.com | I18: no | J18: 0 | K18: 0 | L18: 28450.01 | M18: 0 | N18: 0 | O18: 0 | P18: Products | Q18: Every 21st of the month | R18: KYC passed | T18: 32329.56 | U18: 0 | V18: 0 | W18: 0 | X18: 0 | Y18: 2486.89 | AI18: 13 | AJ18: 0 | AK18: 0 | AL18: 0 | AM18: 0 | AN18: 73.53 | AS18: 0 | AX18: 0 | BC18: 0 | BH18: 64.71 | BM18: 7100 | BR18: 91785 | CB18: 17 | CC18: 0 | CD18: 0 | CE18: 0 | CF18: 0 | CP18: USA | CQ18: yes | CR18: Trenzy LLC | CT18: 823488811 | CU18: Mr | CV18: Art | CW18: Kessler | CX18: 773-294-9108 | DA18: 2714 Sheridan Rd | DC18: 60035 | DD18: Highland Park | DE18: Illinois | DF18: USA | DG18: https://www.restaurantfurnitureplus.com/ | DH18: yes | DI18: By default | DJ18: 0 | DK18: no | DL18: 0 | DO18: Commission grid 12 | DP18: 30 days, net | DQ18: 0 | DR18: Tier 3 | DX18: 28 | EC18: kkhu6683@sysco.com | EF18: No | EI18: Not_Declared | EJ18: I_choose_not_to_disclose | EK18: No | EL18: TRUE | EM18: 73050 | EN18: 45708 | EO18: 45708 | EP18: 45708 | EQ18: 45708 | ER18: 2000000 | ES18: 43101 | ET18: Employer_Identification_Number | EU18: 823488811 | EV18: Restaurant Furniture Plus | EW18: FALSE | EX18: TRUE | EY18: Inventory,Product_Content_and_Pricing,Order,PO_Ack,Invoicing | FA18: External-Seller | FC18: Restaurant Furniture Plus | FD18: 2714 Sheridan Rd | FI18: Highland Park | FJ18: United States | FK18: Illinois | FL18: 60035 | FM18: 5:00 PM | FN18: FALSE | FO18: Afternoon | FP18: N/A
A19: 45349.566 | B19: 2017 | C19: New Age Drinks | D19: Suspended | E19: 2017 | F19: no | G19: USD | H19: sierra@newagedrinks.com | I19: no | J19: 0 | K19: 0 | L19: 3099.26 | M19: 0 | N19: 0 | O19: 0 | P19: Products | Q19: Every 21st of the month | R19: KYC passed | T19: 3620.4 | U19: 0 | V19: 0 | W19: 0 | X19: 0 | Y19: 150.51 | AI19: 76 | AJ19: 0 | AK19: 0 | AL19: 0 | AM19: 0 | AN19: 98.82 | AS19: 1.19 | AX19: 2.38 | BC19: 1.18 | BH19: 10.39 | BM19: 46566 | BR19: 81894 | CB19: 77 | CC19: 0 | CD19: 0 | CE19: 0 | CF19: 0 | CG19: 45740 | CH19: Manual suspension | CP19: USA | CQ19: yes | CR19: New Age Drinks LLC | CS19: 0450351004 | CT19: 0450351004 | CU19: Miss | CV19: Sierra | CW19: Hooshiari | DA19: 261 1st st #3W | DC19: 07030 | DD19: Hoboken NJ 07030 | DF19: USA | DH19: yes | DI19: By default | DJ19: 0 | DK19: no | DL19: 0 | DO19: Default grid | DP19: 30 days, net | DQ19: 0 | DR19: Tier 3 | DX19: 0 | EC19: kkhu6683@sysco.com | EF19: Yes | EG19: Other | EH19: Self-selected | EI19: Woman_Supplier | EJ19: Small_Business_Enterprise_(SBE)_Certified | EK19: Yes | EL19: TRUE | EM19: 73050 | EN19: 45734 | EO19: 45734 | EP19: 45734 | EQ19: 45734 | ER19: 2000000 | ES19: 43133 | ET19: Tax_Payer_Identification_Number | EU19: 0450351004 | EW19: FALSE | EX19: FALSE | EY19: Inventory | FA19: External-Seller | FC19: Hello Goods | FD19: 71-10 Beach Channel Drive Queens | FE19: 71-10 | FI19: Queens | FJ19: United States | FK19: New York | FL19: 11692 | FM19: 2PM | FN19: FALSE | FO19: 12pm ET | FP19: UPS
A20: 45351.495 | B20: 2018 | C20: Sunday Morning Coffee | D20: Open | E20: 2018 | F20: no | G20: USD | H20: customerservice@sundaymorningroast.com | I20: no | J20: 73.76 | K20: 0 | L20: 2301.71 | M20: 18 | N20: 0 | O20: 0 | P20: Products | Q20: Every 21st of the month | R20: KYC passed | T20: 2897.09 | U20: 89.95 | V20: 89.95 | W20: 89.95 | X20: 341.91 | Y20: 49.63 | Z20: 31.48 | AA20: 31.48 | AB20: 31.48 | AC20: 47.24 | AI20: 62 | AJ20: 4 | AK20: 4 | AL20: 4 | AM20: 8 | AN20: 100 | AO20: 100 | AP20: 100 | AQ20: 100 | AR20: 100 | AS20: 9.28 | AT20: 0 | AU20: 0 | AV20: 0 | AW20: 0 | AX20: 9.28 | AY20: 25 | AZ20: 25 | BA20: 25 | BB20: 11.11 | BC20: 0 | BD20: 0 | BE20: 0 | BF20: 0 | BG20: 0 | BH20: 22.58 | BI20: 25 | BJ20: 25 | BK20: 25 | BL20: 37.5 | BM20: 30483 | BN20: 28924 | BO20: 28924 | BP20: 28924 | BQ20: 38078 | BR20: 43454 | BS20: 44205 | BT20: 44205 | BU20: 44205 | BV20: 57775 | BW20: 43608 | CB20: 62 | CC20: 4 | CD20: 4 | CE20: 4 | CF20: 8 | CJ20: 46280 | CK20: Refund rate (since 3 months) ≥ 2%, Late shipment rate (since 3 months) ≥ 3% | CP20: USA | CQ20: yes | CR20: Sunday Morning Roasting Company | CT20: 852513000 | CU20: Miss | CV20: Savannah | CW20: Mitchell | CX20: 12405502312 | DA20: 111 S Springdale Avenue | DC20: 21776 | DD20: New Windsor | DE20: MD | DF20: USA | DG20: https://sundaymorningroast.com/ | DH20: yes | DI20: By default | DJ20: 0 | DK20: no | DL20: 0 | DO20: Commission grid 18 | DP20: 30 days, net | DQ20: 0 | DR20: Tier 3 | DS20: 50 | DT20: 50 | DU20: 50 | DV20: 50 | DW20: 50 | DX20: 2.06 | DY20: 50 | DZ20: 50 | EA20: 50 | EB20: 22.22 | EC20: kkhu6683@sysco.com | EF20: Yes | EG20: Black_or_African_American | EH20: Third-party | EI20: Woman_Supplier | EJ20: Disadvantaged_Business_Enterprise_(DBE)_Certified,Women's_Business_Enterprise_(WBE)_Certified,Small_Business_Enterprise_(SBE)_Certified,Small_Disadvantaged_Business_(SDB)_Certified | EK20: Yes | EL20: TRUE | EM20: 73050 | EN20: 45816 | EO20: 45816 | EP20: 45879 | EQ20: 45961 | ER20: $5 million | ES20: 44355 | ET20: Employer_Identification_Number | EU20: 872513000 | EV20: Sunday Morning Roasting Company | EW20: FALSE | EX20: FALSE | FA20: External-Seller | FC20: Sunday Morning Coffee | FD20: 111 South Springdale Avenue | FI20: New Windsor | FJ20: United States | FK20: Maryland | FL20: 21776 | FM20: 12 noon | FN20: FALSE | FO20: Afternoon | FP20: USPS
A21: 45356.623 | B21: 2019 | C21: Tempo Granola | D21: Terminated | E21: 2019 | F21: no | G21: USD | H21: beverly@tempoeats.com | I21: no | J21: 0 | K21: 0 | L21: 0 | M21: 0 | N21: 0 | O21: 0 | P21: Products | Q21: Every 21st of the month | R21: KYC passed | T21: 0 | U21: 0 | V21: 0 | W21: 0 | X21: 0 | AI21: 0 | AJ21: 0 | AK21: 0 | AL21: 0 | AM21: 0 | CB21: 0 | CC21: 0 | CD21: 0 | CE21: 0 | CF21: 0 | CG21: 45552 | CH21: Manual suspension | CP21: USA | CQ21: yes | CR21: CMJ Foods dba Tempo Granola | CS21: 85-2883337 | CT21: 85-2883337 | CU21: Mrs | CV21: Beverly | CW21: Karns | CX21: 303-887-6711 | DA21: 675 Meadowleaf Lane | DC21: 80126 | DD21: Highlands Ranch | DE21: Colorado | DF21: USA | DG21: https://www.tempoeats.com | DH21: no | DO21: Commission grid 18 | DP21: 30 days, net | DQ21: 0 | DR21: Tier 3 | EC21: kkhu6683@sysco.com | EF21: I_choose_not_to_disclose | EG21: OTHER | EH21: Third-party | EI21: Yes | EJ21: Small_Business_Enterprise_(SBE) | EK21: Yes | EL21: TRUE | EM21: 73050 | EN21: 45805 | EO21: 45805 | EP21: 45805 | EQ21: 45805 | ER21: $2,000,000 | ES21: 44070 | ET21: Employer_Identification_Number | EU21: 85-2883337 | EV21: Tempo Granola | EW21: FALSE | EX21: TRUE | EY21: Order,Invoicing | FA21: External-Seller | FC21: Made4U Foods | FD21: 1441 Industry Drive | FI21: Laramie | FJ21: USA | FK21: WY | FL21: 82070 | FM21: 5:00pm | FN21: FALSE | FO21: Afternoon | FP21: UPS
A22: 45356.717 | B22: 2020 | C22: Soultox | D22: Open | E22: 2020 | F22: no | G22: USD | H22: vinnie@luckysoulusa.com | I22: no | J22: 0 | K22: 0 | L22: 0 | M22: 0 | N22: 0 | O22: 0 | P22: Products | Q22: Every 21st of the month | R22: KYC passed | T22: 0 | U22: 0 | V22: 0 | W22: 0 | X22: 0 | AI22: 0 | AJ22: 0 | AK22: 0 | AL22: 0 | AM22: 0 | CB22: 0 | CC22: 0 | CD22: 0 | CE22: 0 | CF22: 0 | CP22: USA | CQ22: yes | CR22: Soultox LLC | CS22: 852349851 | CT22: 852349851 | CU22: Mr | CV22: Vinnie | CW22: Merrill | CX22: 323-834-9211 | DA22: 275 S 3rd Street # 102 | DC22: 91502 | DD22: Burbank | DE22: CA | DF22: USA | DG22: https://www.luckysoulusa.com/ | DH22: yes | DI22: By default | DJ22: 0 | DK22: no | DL22: 0 | DO22: Commission grid 18 | DP22: 30 days, net | DQ22: 0 | DR22: Tier 3 | EC22: kkhu6683@sysco.com | EF22: Yes | EG22: Black_or_African_American | EI22: Not_Declared | EJ22: I_choose_not_to_disclose | EK22: Yes | EL22: FALSE | EM22: 73050 | EN22: 45563 | EO22: 45563 | EP22: 45563 | EQ22: 45563 | ER22: 2,000.000 | ES22: 44197 | ET22: Tax_Payer_Identification_Number | EU22: 852349851 | EW22: FALSE | EX22: FALSE | FA22: External-Seller | FC22: Soultox LLC | FD22: 6901 Marlin Circle | FI22: La Palma | FJ22: USA | FK22: ca | FL22: 90623 | FM22: 5:00 | FN22: TRUE | FO22: 5:00 | FP22: Fed Ex
A23: 45357.407 | B23: 2022 | C23: Hampton Farms | D23: Terminated | E23: 2022 | F23: no | G23: USD | H23: cwatson@hamptonfarms.com | I23: no | J23: 0 | K23: 0 | L23: 0 | M23: 0 | N23: 0 | O23: 0 | P23: Products | Q23: Every 21st of the month | R23: Pending KYC submission | S23: <html lang="en"> <body> Create your account with Payoneer, Mirakl Payout’s partner, to submit your KYC information and receive payments to your wallet. <br/> <br/> <a href="https://payouts.payoneer.com/partners/lp.aspx?token=e32c011780cf47fb82df2fa309694d23CCA3CE683A" class="btn btn-outline btn-outline-default"> <span>Create account</span> </a> </body> </html> | T23: 0 | U23: 0 | V23: 0 | W23: 0 | X23: 0 | AI23: 0 | AJ23: 0 | AK23: 0 | AL23: 0 | AM23: 0 | CB23: 0 | CC23: 0 | CD23: 0 | CE23: 0 | CF23: 0 | CG23: 45357 | CH23: Pending approval | CN23: 45551.531 | CQ23: yes | CR23: Hampton Farms | CS23: 560579564 | CT23: 560579564 | CU23: Mr | CV23: Claire | CW23: Watson | CX23: 9842220786 | DA23: 8060 N CAROLINA 46 | DC23: 27831 | DD23: GARYSBURG | DE23: North Carolina | DF23: USA | DG23: https://www.hamptonfarms.com/ | DH23: no | DO23: Commission grid 18 | DP23: 30 days, net | DQ23: 0 | DR23: Tier 3 | EC23: kkhu6683@sysco.com | EF23: No | EI23: No | EJ23: I_choose_not_to_disclose | EK23: I_choose_not_to_disclose | EL23: TRUE | EM23: 73050 | EN23: 45535 | EO23: 45535 | EP23: 45535 | EQ23: 45535 | ER23: $1,000,000 | ES23: 17838 | ET23: Employer_Identification_Number | EU23: 560579564 | EV23: Hampton Farms | EW23: FALSE | EX23: FALSE | FA23: External-Seller | FC23: Hampton Farms | FD23: 8060 N CAROLINA 46 | FI23: GARYSBURG | FJ23: United States | FK23: North Carolina | FL23: 27831 | FM23: 3:30 pm | FN23: FALSE | FO23: All | FP23: UPS
A24: 45359.661 | B24: 2023 | C24: Wingredient | D24: Open | E24: 2023 | F24: no | G24: USD | H24: wingredient@gmail.com | I24: no | J24: 516.32 | K24: 0 | L24: 16903.28 | M24: 13 | N24: 0 | O24: 0 | P24: Products | Q24: Every 21st of the month | R24: KYC passed | T24: 21243.15 | U24: 1049.49 | V24: 3128.34 | W24: 5472.17 | X24: 10319.5 | Y24: 124.73 | Z24: 104.95 | AA24: 111.73 | AB24: 118.24 | AC24: 119.59 | AI24: 171 | AJ24: 10 | AK24: 28 | AL24: 47 | AM24: 87 | AN24: 99.54 | AO24: 100 | AP24: 100 | AQ24: 100 | AR24: 100 | AS24: 0 | AT24: 0 | AU24: 0 | AV24: 0 | AW24: 0 | AX24: 0.46 | AY24: 0 | AZ24: 0 | BA24: 1.89 | BB24: 0.94 | BC24: 0 | BD24: 0 | BE24: 0 | BF24: 0 | BG24: 0 | BH24: 5.23 | BI24: 10 | BJ24: 3.57 | BK24: 6.38 | BL24: 3.45 | BM24: 16398 | BN24: 11469 | BO24: 11130 | BP24: 11436 | BQ24: 12055 | BR24: 11708 | BS24: 20249 | BT24: 15586 | BU24: 18898 | BV24: 13184 | CB24: 172 | CC24: 10 | CD24: 28 | CE24: 47 | CF24: 87 | CJ24: 46280 | CK24: Late shipment rate (since 3 months) ≥ 3% | CP24: USA | CQ24: yes | CR24: Wingredient LLC | CS24: 473765700 | CT24: 473765700 | CU24: Mr | CV24: Deats | CW24: Bryan | CX24: 406-570-0758 | DA24: 2010 N 7th | DC24: 59718 | DD24: Bozeman | DE24: MT | DF24: USA | DG24: https://www.wingredient.com/ | DH24: yes | DI24: By default | DJ24: 0 | DK24: no | DL24: 0 | DO24: Commission grid 18 | DP24: 30 days, net | DQ24: 0 | DR24: Tier 3 | DS24: 100 | DT24: 100 | DU24: 100 | DV24: 100 | DW24: 100 | DX24: 0.46 | DY24: 0 | DZ24: 0 | EA24: 0 | EB24: 0 | EC24: kkhu6683@sysco.com | EF24: No | EI24: Not_Declared | EJ24: I_choose_not_to_disclose | EK24: Yes | EL24: TRUE | EM24: 73050 | EN24: 46526 | EO24: 46526 | EP24: 46526 | EQ24: 46526 | ER24: 100000/200000 | ES24: 41703 | ET24: Employer_Identification_Number | EU24: 473765700 | EW24: FALSE | EX24: FALSE | FA24: External-Seller | FC24: Wingredient | FD24: 2010 N 7th | FI24: Bozeman | FJ24: United States | FK24: Montana | FL24: 59715 | FM24: 2:00pm | FN24: FALSE | FO24: 11:00am | FP24: UPS
A25: 45364.587 | B25: 2025 | C25: Mikuni Wild Harvest | D25: Open | E25: 2025 | F25: yes | G25: USD | H25: lainew@mikuniwild.com | I25: no | J25: 843.17 | K25: 0 | L25: 41382.07 | M25: 28 | N25: 0 | O25: 0 | P25: Products | Q25: Every 21st of the month | R25: KYC passed | T25: 51493.65 | U25: 2531.1 | V25: 7856.3 | W25: 14701.25 | X25: 25733.45 | Y25: 137.42 | Z25: 194.7 | AA25: 154.05 | AB25: 147.01 | AC25: 146.21 | AI25: 375 | AJ25: 13 | AK25: 51 | AL25: 100 | AM25: 176 | AN25: 99.24 | AO25: 100 | AP25: 100 | AQ25: 100 | AR25: 98.94 | AS25: 0.26 | AT25: 0 | AU25: 0 | AV25: 0 | AW25: 0 | AX25: 0.26 | AY25: 0 | AZ25: 0 | BA25: 0 | BB25: 0 | BC25: 0 | BD25: 0 | BE25: 0 | BF25: 0 | BG25: 0 | BH25: 0 | BI25: 0 | BJ25: 0 | BK25: 0 | BL25: 0 | BM25: 5426 | BN25: 6197 | BO25: 6123 | BP25: 5687 | BQ25: 5782 | BR25: 318 | BS25: 175 | BT25: 121 | BU25: 121 | BV25: 121 | CB25: 379 | CC25: 14 | CD25: 52 | CE25: 101 | CF25: 179 | CP25: USA | CQ25: yes | CR25: Mikuni Wild Harvest Inc | CT25: 20-3476668 | CU25: Mr | CV25: Laine | CW25: Weighill | CX25: 2502651745 | DA25: 6340 McLeod Drive | DB25: Suite 5 | DC25: 89120 | DD25: Las Vegas | DE25: NV | DF25: USA | DG25: https://www.mikuniwildharvest.com | DH25: yes | DI25: By default | DJ25: 0 | DK25: no | DL25: 0 | DO25: Commission grid 18 | DP25: 30 days, net | DQ25: 0 | DR25: Tier 3 | DS25: 100 | DT25: 100 | DU25: 100 | DV25: 100 | DW25: 100 | DX25: 0 | DY25: 0 | DZ25: 0 | EA25: 0 | EB25: 0 | EC25: kkhu6683@sysco.com | EF25: I_choose_not_to_disclose | EI25: Not_Declared | EJ25: I_choose_not_to_disclose | EK25: I_choose_not_to_disclose | EL25: FALSE | EM25: 73050 | EN25: 45646 | EO25: 45646 | EP25: 45646 | EQ25: 45646 | ER25: 5000000 | ES25: 38442 | ET25: Employer_Identification_Number | EU25: 20-3476668 | EW25: FALSE | EX25: FALSE | FA25: External-Seller | FC25: Mikuni Wild Harvest | FD25: 5440 S Proctor St | FI25: Tacoma | FJ25: USA | FK25: WA | FL25: 98409 | FM25: 8AM | FN25: TRUE | FO25: Afternoon | FP25: UPS
A26: 45371.485 | B26: 2026 | C26: Berri Organics | D26: Open | E26: 2026 | F26: no | G26: USD | H26: jerome@berripro.com | I26: no | J26: 159.11 | K26: 0 | L26: 14933.16 | M26: 6 | N26: 0 | O26: 0 | P26: Products | Q26: Every 21st of the month | R26: KYC passed | T26: 18397.22 | U26: 475.57 | V26: 2628.18 | W26: 5017.28 | X26: 9216.8 | Y26: 85.17 | Z26: 118.89 | AA26: 82.13 | AB26: 74.88 | AC26: 81.56 | AI26: 216 | AJ26: 4 | AK26: 32 | AL26: 67 | AM26: 113 | AN26: 100 | AO26: 100 | AP26: 100 | AQ26: 100 | AR26: 100 | AS26: 0 | AT26: 0 | AU26: 0 | AV26: 0 | AW26: 0 | AX26: 0 | AY26: 0 | AZ26: 0 | BA26: 0 | BB26: 0 | BC26: 0 | BD26: 0 | BE26: 0 | BF26: 0 | BG26: 0 | BH26: 12.44 | BI26: 20 | BJ26: 24.24 | BK26: 14.71 | BL26: 17.54 | BM26: 24854 | BN26: 14922 | BO26: 39598 | BP26: 32263 | BQ26: 35562 | BR26: 122954 | BS26: 134504 | BT26: 105944 | BU26: 90064 | BV26: 104973 | CB26: 217 | CC26: 5 | CD26: 33 | CE26: 68 | CF26: 114 | CJ26: 46197 | CK26: Late shipment rate (since 3 months) ≥ 3% | CP26: USA | CQ26: yes | CR26: Berri Pro | CS26: 3778596 | CT26: 47-3685236 | CU26: Mr | CV26: Jerome | CW26: TSE | DA26: 840 Apollo St #100 | DC26: 90245 | DD26: El Segundo | DE26: CA | DF26: USA | DG26: http://www.berriorganics.com | DH26: yes | DI26: By default | DJ26: 0 | DK26: no | DL26: 0 | DO26: Commission grid 18 | DP26: 30 days, net | DQ26: 0 | DR26: Tier 3 | DS26: 38.46 | DT26: 25 | DU26: 37.5 | DV26: 38.46 | DW26: 38.46 | DX26: 0 | DY26: 0 | DZ26: 0 | EA26: 0 | EB26: 0 | EC26: kkhu6683@sysco.com | EF26: Yes | EG26: Asian | EI26: Not_Declared | EJ26: Small_Business_Enterprise_(SBE)_Certified | EK26: Yes | EL26: FALSE | EM26: 73050 | EN26: 45777 | EO26: 45777 | EP26: 45777 | EQ26: 45777 | ER26: 3,000,000 | ES26: 42103 | ET26: Employer_Identification_Number | EU26: 47-3685236 | EV26: Berri Pro | EW26: FALSE | EX26: TRUE | EY26: Order | FA26: External-Seller | FC26: Express Freight | FD26: 2027 Williams St | FI26: San Leandro | FJ26: United States | FK26: CA | FL26: 94577 | FM26: 3pm | FN26: TRUE | FO26: 9am | FP26: UPS
A27: 45371.607 | B27: 2027 | C27: Sunco & Frenchie | D27: Suspended | E27: 2027 | F27: no | G27: USD | H27: u.altuntas@suncofrenchie.com | I27: no | J27: 0 | K27: 0 | L27: 3519.16 | M27: 0 | N27: 0 | O27: 0 | P27: Products | Q27: Every 21st of the month | R27: KYC passed | T27: 3519.16 | U27: 0 | V27: 0 | W27: 0 | X27: 0 | Y27: 67.68 | AI27: 52 | AJ27: 0 | AK27: 0 | AL27: 0 | AM27: 0 | AN27: 96.3 | AS27: 0 | AX27: 0 | BC27: 3.7 | BH27: 20.37 | BM27: 27519 | BR27: 21000 | CB27: 54 | CC27: 0 | CD27: 0 | CE27: 0 | CF27: 0 | CG27: 45973 | CH27: Manual suspension | CP27: USA | CQ27: yes | CR27: Sunco & Frenchie LLC | CS27: 0400439462 | CT27: 45-3182013 | CU27: Mr | CV27: Ugur | CW27: Altuntas | CX27: 973 478 1011 Ext 107 | CY27: 3478277542 | DA27: 1 Chapin Rd | DB27: Ste 5 | DC27: 07058 | DD27: Pine Brook | DE27: NJ | DF27: USA | DG27: https://sunbestnatural.com/ | DH27: yes | DI27: By default | DJ27: 0 | DK27: no | DL27: 0 | DO27: Commission grid 0 | DP27: 30 days, net | DQ27: 0 | DR27: Tier 3 | DX27: 1.92 | EC27: kkhu6683@sysco.com | EF27: No | EI27: Not_Declared | EJ27: I_choose_not_to_disclose | EK27: Yes | EL27: FALSE | EM27: 73050 | EN27: 45769 | EO27: 45769 | EP27: 45769 | EQ27: 45769 | ER27: 2,000,000 | ES27: 40762 | ET27: Employer_Identification_Number | EU27: 45-3182013 | EV27: Sunco & Frenchie | EW27: FALSE | EX27: FALSE | FA27: External-Seller | FC27: Sunco & Frenchie | FD27: 1 Chapin Rd | FE27: Suite 5 | FI27: Pine Brook | FJ27: United States | FK27: NJ | FL27: 07058 | FM27: 2:00 pm | FN27: TRUE | FO27: Unsure | FP27: USPS
A28: 45372.635 | B28: 2028 | C28: Gatzies | D28: Open | E28: 2028 | F28: no | G28: USD | H28: kolson@acktify.com | I28: no | J28: 0 | K28: 0 | L28: 0 | M28: 0 | N28: 0 | O28: 0 | P28: Products | Q28: Every 21st of the month | R28: KYC passed | T28: 0 | U28: 0 | V28: 0 | W28: 0 | X28: 0 | AI28: 0 | AJ28: 0 | AK28: 0 | AL28: 0 | AM28: 0 | CB28: 0 | CC28: 0 | CD28: 0 | CE28: 0 | CF28: 0 | CQ28: yes | CR28: Promax Supply DBA Acktify/Gatzies/Promax Commerce | CS28: 320231219 | CT28: 320231219 | CU28: Miss | CV28: Kirstin | CW28: Olson | CX28: 17819410405 | DA28: 42 franklin street | DC28: 02176 | DD28: melrose | DE28: Massachusetts | DF28: USA | DG28: https://www.acktify.com/ | DH28: yes | DI28: By default | DJ28: 0 | DK28: no | DL28: 0 | DO28: Commission grid 18 | DP28: 30 days, net | DQ28: 0 | DR28: Tier 3 | EC28: kkhu6683@sysco.com | EF28: No | EI28: Not_Declared | EJ28: Small_Business_Enterprise_(SBE)_Certified | EK28: Yes | EL28: TRUE | EM28: 73050 | EN28: 45474 | EO28: 45474 | EP28: 45474 | EQ28: 45474 | ER28: 17,000,000 | ES28: 39264 | ET28: Employer_Identification_Number | EU28: 320231219 | EV28: Promax Supply DBA Acktify/Gatzies/Promax Commerce | EW28: TRUE | EX28: FALSE | FA28: External-Seller | FC28: PROMAX COMMERCE | FD28: 333 Harvey Rd | FI28: Manchester | FJ28: United | FK28: NH | FL28: 03103 | FM28: 1:00 PM | FN28: TRUE | FO28: 8:00 - 5:00 | FP28: Fed Ex
A29: 45372.767 | B29: 2029 | C29: Chef Blackanese | D29: Suspended | E29: 2029 | F29: no | G29: USD | H29: mfoy@chefblackanese.com | I29: no | J29: 0 | K29: 0 | L29: 0 | M29: 0 | N29: 0 | O29: 2 | P29: Products | Q29: Every 21st of the month | R29: KYC passed | T29: 0 | U29: 0 | V29: 0 | W29: 0 | X29: 0 | AI29: 0 | AJ29: 0 | AK29: 0 | AL29: 0 | AM29: 0 | AN29: 0 | BC29: 100 | BH29: 100 | BM29: 263215 | CB29: 2 | CC29: 0 | CD29: 0 | CE29: 0 | CF29: 0 | CG29: 45826 | CH29: Manual suspension | CP29: USA | CQ29: yes | CR29: foy family food llc | CT29: 844068371 | CU29: Mr | CV29: Michial | CW29: Foy | CX29: 17087932624 | DA29: 1712 S Dixie Hwy #204 | DC29: 60417 | DD29: Crete | DE29: Illinois | DF29: USA | DG29: https://www.achievewithchefblackanese.com | DH29: yes | DI29: By default | DJ29: 0 | DK29: no | DL29: 0 | DO29: Commission grid 18 | DP29: 30 days, net | DQ29: 0 | DR29: Tier 3 | EC29: kkhu6683@sysco.com | EF29: Yes | EG29: Black_or_African_American | EH29: Third-party | EI29: Woman_Supplier | EJ29: Disadvantaged_Business_Enterprise_(DBE)_Certified,Small_Business_Enterprise_(SBE)_Certified,Small_Disadvantaged_Business_(SDB)_Certified | EK29: Yes | EL29: TRUE | EM29: 73050 | EN29: 45451 | EO29: 45451 | EP29: 45479 | EQ29: 45451 | ER29: 2000000 | ES29: 43489 | ET29: Employer_Identification_Number | EU29: 844068371 | EV29: Chef Blackanese Food, LLC | EW29: FALSE | EX29: FALSE | FA29: External-Seller | FC29: Chef Blackanese Warehouse | FD29: 1712 S Dixie Hwy #204 | FE29: 204 | FI29: Crete | FJ29: United States | FK29: IL | FL29: 60417 | FM29: 8pm | FN29: FALSE | FO29: 8am-8pm | FP29: old dominion
A30: 45377.234 | B30: 2030 | C30: The Supplant Company | D30: Open | E30: 2030 | F30: no | G30: USD | H30: m.mace@camglyco.com | I30: no | J30: 0 | K30: 0 | L30: 307.46 | M30: 1 | N30: 0 | O30: 0 | P30: Products | Q30: Every 21st of the month | R30: KYC passed | T30: 374.95 | U30: 0 | V30: 0 | W30: 0 | X30: 0 | Y30: 374.95 | AI30: 1 | AJ30: 0 | AK30: 0 | AL30: 0 | AM30: 0 | AN30: 100 | AS30: 0 | AX30: 0 | BC30: 0 | BH30: 100 | BM30: 5090 | BR30: 468908 | CB30: 1 | CC30: 0 | CD30: 0 | CE30: 0 | CF30: 0 | CP30: USA | CQ30: yes | CR30: Supplant Inc | CS30: 6896301 | CT30: 371900139 | CU30: Mr | CV30: Martin | CW30: Mace | CX30: 887344626 | DA30: 10685-B HAZELHURST DR #27917 | DC30: 77043 | DD30: HOUSTON | DE30: TX | DF30: USA | DG30: https://www.supplant.com | DH30: yes | DI30: By default | DJ30: 0 | DK30: no | DL30: 0 | DO30: Commission grid 18 | DP30: 30 days, net | DQ30: 0 | DR30: Tier 3 | DX30: 0 | EC30: kkhu6683@sysco.com | EF30: No | EI30: Not_Declared | EJ30: I_choose_not_to_disclose | EK30: Yes | EL30: TRUE | EM30: 73050 | EN30: 45844 | EO30: 45844 | EP30: 45844 | EQ30: 45844 | ER30: 2000000 | ES30: 43242 | ET30: Employer_Identification_Number | EU30: 910189318 | EV30: SUPPLANT INC | EW30: FALSE | EX30: TRUE | EY30: Order,Invoicing | FA30: External-Seller | FC30: Accurate Fulfillment | FD30: 10641 S Sam Houston Parkway | FE30: West Suite 200 | FI30: Stafford | FJ30: USA | FK30: TX | FL30: 77477 | FM30: 11:00 | FN30: FALSE | FO30: 11:00 | FP30: UPS
